Workbook

Sheet Cover
A1: Meridian Growth Partners III, L.P.
A2: Capital Call, Distribution Waterfall & NAV Model
B4: Prepared as of | C4: Q2 2026 (2026-06-30)
B5: Fund size (committed capital) | C5: 50000000
B6: Limited partners | C6: 15
B7: Vintage / investment period | C7: Q1 2022 – Q4 2024 (12 quarters)
B8: Fund term modeled | C8: Q1 2022 – Q2 2026 (18 quarters)
B10: How this workbook is organized
B11: Assumptions | C11: Fund terms: fee rate, preferred return, carry split, catch-up
B12: Quarters | C12: The 18-quarter calendar used throughout the model
B13: LP Register | C13: 15 limited partners and their commitments
B14: Portfolio Companies | C14: 10 portfolio company investments (cost, invest date, sector)
B15: Portfolio Marks | C15: Quarterly fair value marks and exit/recap events, by company
B16: Mgmt Fee Schedule | C16: 2% of committed capital during the investment period, stepping down to 2% of invested cost thereafter
B17: Capital Call Schedule | C17: Fund-level quarterly capital calls (investment + fee)
B18: LP Capital Calls | C18: Each LP's pro-rata share of every capital call
B19: Distribution Waterfall | C19: Return of capital → 8% preferred return → GP catch-up → 80/20 carry split, run cumulatively by quarter
B20: NAV Rollforward | C20: Quarterly Beginning NAV → Ending NAV bridge
B21: LP Capital Accounts | C21: Each LP's quarterly capital account statement
B22: LP Statement (Select LP) | C22: A single formatted LP statement — pick any LP from the dropdown
... B24: Variance Reconciliation | C24: GP ledger vs. fund administrator records — 4 identified breaks
B26: Legend
B27: Blue text | C27: Hardcoded input
B28: Black text | C28: Formula
B29: Green text | C29: Link to another sheet
B30: Yellow fill | C30: Key assumption
B32: Synthetic fund for portfolio/demonstration purposes. All LPs, portfolio companies, valuations and cash flows are generated data — see README.md.

Sheet Assumptions
A1: Fund Assumptions
A2: Key economic terms — change these and the model recalculates
B4: Fund name | C4: Meridian Growth Partners III, L.P.
B5: Committed capital | C5: 50000000
B6: Number of LPs | C6: 15
B7: Investment period (quarters) | C7: 12
B8: Total quarters modeled | C8: 18
B9: Management fee rate (annual, % of committed capital during investment period) | C9: 0.02
B10: Management fee rate post-investment-period (annual, % of invested cost) | C10: 0.02
B11: Preferred return / hurdle rate (annual, compounded quarterly) | C11: 0.08
B12: GP catch-up (% of catch-up tier to GP) | C12: 1
B13: Carried interest rate (GP share of profit above hurdle) | C13: 0.2
B15: Waterfall structure
B16: 1. Return of Capital — 100% to LPs until cumulative capital contributed has been returned
B17: 2. Preferred Return — 100% to LPs until the compounding hurdle above is paid in full
B18: 3. GP Catch-up — 100% to GP until GP has received 20% of (preferred + catch-up) paid to date
B19: 4. Carried Interest Split — 80% LP / 20% GP on all remaining distributions

Sheet Quarters
A1: Quarterly Calendar
B3: Quarter Index | C3: Year | D3: Quarter | E3: Label | F3: Quarter End | G3: In Investment Period
B4: 1 | C4: 2022 | D4: 1 | E4: Q1 2022 | F4: 44651 | G4: =B4<=Assumptions!$C$7 -> TRUE
B5: 2 | C5: 2022 | D5: 2 | E5: Q2 2022 | F5: 44742 | G5: =B5<=Assumptions!$C$7 -> TRUE
B6: 3 | C6: 2022 | D6: 3 | E6: Q3 2022 | F6: 44834 | G6: =B6<=Assumptions!$C$7 -> TRUE
B7: 4 | C7: 2022 | D7: 4 | E7: Q4 2022 | F7: 44926 | G7: =B7<=Assumptions!$C$7 -> TRUE
B8: 5 | C8: 2023 | D8: 1 | E8: Q1 2023 | F8: 45016 | G8: =B8<=Assumptions!$C$7 -> TRUE
B9: 6 | C9: 2023 | D9: 2 | E9: Q2 2023 | F9: 45107 | G9: =B9<=Assumptions!$C$7 -> TRUE
B10: 7 | C10: 2023 | D10: 3 | E10: Q3 2023 | F10: 45199 | G10: =B10<=Assumptions!$C$7 -> TRUE
B11: 8 | C11: 2023 | D11: 4 | E11: Q4 2023 | F11: 45291 | G11: =B11<=Assumptions!$C$7 -> TRUE
B12: 9 | C12: 2024 | D12: 1 | E12: Q1 2024 | F12: 45382 | G12: =B12<=Assumptions!$C$7 -> TRUE
B13: 10 | C13: 2024 | D13: 2 | E13: Q2 2024 | F13: 45473 | G13: =B13<=Assumptions!$C$7 -> TRUE
B14: 11 | C14: 2024 | D14: 3 | E14: Q3 2024 | F14: 45565 | G14: =B14<=Assumptions!$C$7 -> TRUE
B15: 12 | C15: 2024 | D15: 4 | E15: Q4 2024 | F15: 45657 | G15: =B15<=Assumptions!$C$7 -> TRUE
... B21: 18 | C21: 2026 | D21: 2 | E21: Q2 2026 | F21: 46203 | G21: =B21<=Assumptions!$C$7 -> FALSE

Sheet LP Register
A1: LP Register
A2: 15 limited partners, commitments summing to committed capital
B3: LP ID | C3: LP Name | D3: LP Type | E3: Commitment ($) | F3: Commitment %
B4: LP-01 | C4: Northbridge State Pension Fund | D4: Pension Fund | E4: 8000000 | F4: =E4/Assumptions!$C$5 -> 0.16
B5: LP-02 | C5: Meridian University Endowment | D5: Endowment | E5: 6000000 | F5: =E5/Assumptions!$C$5 -> 0.12
B6: LP-03 | C6: Harborview Insurance Co. | D6: Insurance Company | E6: 5500000 | F6: =E6/Assumptions!$C$5 -> 0.11
B7: LP-04 | C7: Cascade Partners Fund of Funds | D7: Fund of Funds | E7: 5000000 | F7: =E7/Assumptions!$C$5 -> 0.1
B8: LP-05 | C8: Elmwood Family Office | D8: Family Office | E8: 4000000 | F8: =E8/Assumptions!$C$5 -> 0.08
B9: LP-06 | C9: Tanager Sovereign Partners | D9: Sovereign Wealth Fund | E9: 4000000 | F9: =E9/Assumptions!$C$5 -> 0.08
B10: LP-07 | C10: Birchwood College Endowment | D10: Endowment | E10: 3000000 | F10: =E10/Assumptions!$C$5 -> 0.06
B11: LP-08 | C11: Kestrel Insurance Group | D11: Insurance Company | E11: 2500000 | F11: =E11/Assumptions!$C$5 -> 0.05
B12: LP-09 | C12: Wrenfield Family Office | D12: Family Office | E12: 2000000 | F12: =E12/Assumptions!$C$5 -> 0.04
B13: LP-10 | C13: Alder Street Foundation | D13: Foundation | E13: 2000000 | F13: =E13/Assumptions!$C$5 -> 0.04
B14: LP-11 | C14: Pinecrest Pension Trust | D14: Pension Fund | E14: 1800000 | F14: =E14/Assumptions!$C$5 -> 0.036
B15: LP-12 | C15: Ivywood Capital Partners (FoF) | D15: Fund of Funds | E15: 1500000 | F15: =E15/Assumptions!$C$5 -> 0.03
... B18: LP-15 | C18: Sable Foundation | D18: Foundation | E18: 1600000 | F18: =E18/Assumptions!$C$5 -> 0.032
C19: Total | E19: =SUM(E4:E18) -> 50000000 | F19: =SUM(F4:F18) -> 1
C20: =IF(E19=Assumptions!$C$5,"OK — ties to committed capital","ERROR — does not tie") -> OK — ties to committed capital

Sheet Portfolio Companies
A1: Portfolio Companies
A2: 10 investments made during the 3-year investment period
B3: Company ID | C3: Company Name | D3: Sector | E3: Invest Quarter # | F3: Invest Quarter | G3: Cost Basis ($) | H3: Notes
B4: PC-01 | C4: Vantage Robotics | D4: Industrial Tech | E4: 1 | F4: =INDEX(Quarters!$E:$E,MATCH(E4,Quarters!$B:$B,0)) -> Q1 2022 | G4: 6000000 | H4: Strong performer — full exit
B5: PC-02 | C5: Coastal Foods Group | D5: Consumer | E5: 2 | F5: =INDEX(Quarters!$E:$E,MATCH(E5,Quarters!$B:$B,0)) -> Q2 2022 | G5: 5500000 | H5: Steady grower — full exit
B6: PC-03 | C6: Nimbus Data Systems | D6: Software | E6: 3 | F6: =INDEX(Quarters!$E:$E,MATCH(E6,Quarters!$B:$B,0)) -> Q3 2022 | G6: 4500000 | H6: Written down — held at reduced value
B7: PC-04 | C7: Harbor Dental Partners | D7: Healthcare Services | E7: 4 | F7: =INDEX(Quarters!$E:$E,MATCH(E7,Quarters!$B:$B,0)) -> Q4 2022 | G7: 5000000 | H7: Dividend recap — partial realization, remainder held
B8: PC-05 | C8: Trailhead Outdoor Co. | D8: Consumer | E8: 5 | F8: =INDEX(Quarters!$E:$E,MATCH(E8,Quarters!$B:$B,0)) -> Q1 2023 | G8: 4000000 | H8: Below-plan growth — held
B9: PC-06 | C9: Summit Logistics | D9: Transportation | E9: 6 | F9: =INDEX(Quarters!$E:$E,MATCH(E9,Quarters!$B:$B,0)) -> Q2 2023 | G9: 5000000 | H9: Strong performer — full exit
B10: PC-07 | C10: BluePeak Software | D10: Software | E10: 7 | F10: =INDEX(Quarters!$E:$E,MATCH(E10,Quarters!$B:$B,0)) -> Q3 2023 | G10: 4500000 | H10: Steady grower — full exit
B11: PC-08 | C11: Ridgeline Materials | D11: Industrials | E11: 8 | F11: =INDEX(Quarters!$E:$E,MATCH(E11,Quarters!$B:$B,0)) -> Q4 2023 | G11: 3500000 | H11: Below-plan growth — held
B12: PC-09 | C12: Fairmont Health Services | D12: Healthcare Services | E12: 9 | F12: =INDEX(Quarters!$E:$E,MATCH(E12,Quarters!$B:$B,0)) -> Q1 2024 | G12: 4000000 | H12: Steady grower — full exit
B13: PC-10 | C13: Alpine Consumer Brands | D13: Consumer | E13: 10 | F13: =INDEX(Quarters!$E:$E,MATCH(E13,Quarters!$B:$B,0)) -> Q2 2024 | G13: 3500000 | H13: Steady grower — full exit
C14: Total invested at cost | G14: =SUM(G4:G13) -> 45500000

Sheet Portfolio Marks
A1: Portfolio Marks
A2: Quarterly fair value marks and exit/recap events, by company
B3: Company ID | C3: Company Name | D3: Qtr # | E3: Quarter | F3: Cost Basis ($, BOP) | G3: Fair Value ($) | H3: Event Type | I3: % Realized | J3: Proceeds ($) | K3: Realized Cost Basis ($) | L3: Realized Gain ($)
B4: PC-01 | C4: Vantage Robotics | D4: 1 | E4: =INDEX(Quarters!$E:$E,MATCH(D4,Quarters!$B:$B,0)) -> Q1 2022 | F4: 6000000 | G4: 6000000 | J4: 0 | K4: 0 | L4: =J4-K4 -> 0
B5: PC-01 | C5: Vantage Robotics | D5: 2 | E5: =INDEX(Quarters!$E:$E,MATCH(D5,Quarters!$B:$B,0)) -> Q2 2022 | F5: 6000000 | G5: 6657424.5 | J5: 0 | K5: 0 | L5: =J5-K5 -> 0
B6: PC-01 | C6: Vantage Robotics | D6: 3 | E6: =INDEX(Quarters!$E:$E,MATCH(D6,Quarters!$B:$B,0)) -> Q3 2022 | F6: 6000000 | G6: 7252599.9 | J6: 0 | K6: 0 | L6: =J6-K6 -> 0
B7: PC-01 | C7: Vantage Robotics | D7: 4 | E7: =INDEX(Quarters!$E:$E,MATCH(D7,Quarters!$B:$B,0)) -> Q4 2022 | F7: 6000000 | G7: 8095763.7 | J7: 0 | K7: 0 | L7: =J7-K7 -> 0
B8: PC-01 | C8: Vantage Robotics | D8: 5 | E8: =INDEX(Quarters!$E:$E,MATCH(D8,Quarters!$B:$B,0)) -> Q1 2023 | F8: 6000000 | G8: 9060037.7 | J8: 0 | K8: 0 | L8: =J8-K8 -> 0
B9: PC-01 | C9: Vantage Robotics | D9: 6 | E9: =INDEX(Quarters!$E:$E,MATCH(D9,Quarters!$B:$B,0)) -> Q2 2023 | F9: 6000000 | G9: 9746194.9 | J9: 0 | K9: 0 | L9: =J9-K9 -> 0
B10: PC-01 | C10: Vantage Robotics | D10: 7 | E10: =INDEX(Quarters!$E:$E,MATCH(D10,Quarters!$B:$B,0)) -> Q3 2023 | F10: 6000000 | G10: 10579176 | J10: 0 | K10: 0 | L10: =J10-K10 -> 0
B11: PC-01 | C11: Vantage Robotics | D11: 8 | E11: =INDEX(Quarters!$E:$E,MATCH(D11,Quarters!$B:$B,0)) -> Q4 2023 | F11: 6000000 | G11: 11710276 | J11: 0 | K11: 0 | L11: =J11-K11 -> 0
B12: PC-01 | C12: Vantage Robotics | D12: 9 | E12: =INDEX(Quarters!$E:$E,MATCH(D12,Quarters!$B:$B,0)) -> Q1 2024 | F12: 6000000 | G12: 12884306 | J12: 0 | K12: 0 | L12: =J12-K12 -> 0
B13: PC-01 | C13: Vantage Robotics | D13: 10 | E13: =INDEX(Quarters!$E:$E,MATCH(D13,Quarters!$B:$B,0)) -> Q2 2024 | F13: 6000000 | G13: 14233911 | J13: 0 | K13: 0 | L13: =J13-K13 -> 0
B14: PC-01 | C14: Vantage Robotics | D14: 11 | E14: =INDEX(Quarters!$E:$E,MATCH(D14,Quarters!$B:$B,0)) -> Q3 2024 | F14: 6000000 | G14: 15546339 | J14: 0 | K14: 0 | L14: =J14-K14 -> 0
B15: PC-01 | C15: Vantage Robotics | D15: 12 | E15: =INDEX(Quarters!$E:$E,MATCH(D15,Quarters!$B:$B,0)) -> Q4 2024 | F15: 6000000 | G15: 17383776 | J15: 0 | K15: 0 | L15: =J15-K15 -> 0
B16: PC-01 | C16: Vantage Robotics | D16: 13 | E16: =INDEX(Quarters!$E:$E,MATCH(D16,Quarters!$B:$B,0)) -> Q1 2025 | F16: 6000000 | G16: 19411887 | H16: full_exit | I16: 1 | J16: 19411887 | K16: 6000000 | L16: =J16-K16 -> 13411887
B17: PC-02 | C17: Coastal Foods Group | D17: 2 | E17: =INDEX(Quarters!$E:$E,MATCH(D17,Quarters!$B:$B,0)) -> Q2 2022 | F17: 5500000 | G17: 5500000 | J17: 0 | K17: 0 | L17: =J17-K17 -> 0
B18: PC-02 | C18: Coastal Foods Group | D18: 3 | E18: =INDEX(Quarters!$E:$E,MATCH(D18,Quarters!$B:$B,0)) -> Q3 2022 | F18: 5500000 | G18: 5801358 | J18: 0 | K18: 0 | L18: =J18-K18 -> 0
B19: PC-02 | C19: Coastal Foods Group | D19: 4 | E19: =INDEX(Quarters!$E:$E,MATCH(D19,Quarters!$B:$B,0)) -> Q4 2022 | F19: 5500000 | G19: 6193105.7 | J19: 0 | K19: 0 | L19: =J19-K19 -> 0
B20: PC-02 | C20: Coastal Foods Group | D20: 5 | E20: =INDEX(Quarters!$E:$E,MATCH(D20,Quarters!$B:$B,0)) -> Q1 2023 | F20: 5500000 | G20: 6562277.4 | J20: 0 | K20: 0 | L20: =J20-K20 -> 0
B21: PC-02 | C21: Coastal Foods Group | D21: 6 | E21: =INDEX(Quarters!$E:$E,MATCH(D21,Quarters!$B:$B,0)) -> Q2 2023 | F21: 5500000 | G21: 6848973.4 | J21: 0 | K21: 0 | L21: =J21-K21 -> 0
B22: PC-02 | C22: Coastal Foods Group | D22: 7 | E22: =INDEX(Quarters!$E:$E,MATCH(D22,Quarters!$B:$B,0)) -> Q3 2023 | F22: 5500000 | G22: 7249124.8 | J22: 0 | K22: 0 | L22: =J22-K22 -> 0
B23: PC-02 | C23: Coastal Foods Group | D23: 8 | E23: =INDEX(Quarters!$E:$E,MATCH(D23,Quarters!$B:$B,0)) -> Q4 2023 | F23: 5500000 | G23: 7557164.8 | J23: 0 | K23: 0 | L23: =J23-K23 -> 0
B24: PC-02 | C24: Coastal Foods Group | D24: 9 | E24: =INDEX(Quarters!$E:$E,MATCH(D24,Quarters!$B:$B,0)) -> Q1 2024 | F24: 5500000 | G24: 8044914.8 | J24: 0 | K24: 0 | L24: =J24-K24 -> 0
B25: PC-02 | C25: Coastal Foods Group | D25: 10 | E25: =INDEX(Quarters!$E:$E,MATCH(D25,Quarters!$B:$B,0)) -> Q2 2024 | F25: 5500000 | G25: 8474520.4 | J25: 0 | K25: 0 | L25: =J25-K25 -> 0
B26: PC-02 | C26: Coastal Foods Group | D26: 11 | E26: =INDEX(Quarters!$E:$E,MATCH(D26,Quarters!$B:$B,0)) -> Q3 2024 | F26: 5500000 | G26: 8913345.1 | J26: 0 | K26: 0 | L26: =J26-K26 -> 0
B27: PC-02 | C27: Coastal Foods Group | D27: 12 | E27: =INDEX(Quarters!$E:$E,MATCH(D27,Quarters!$B:$B,0)) -> Q4 2024 | F27: 5500000 | G27: 9321833.4 | J27: 0 | K27: 0 | L27: =J27-K27 -> 0
B28: PC-02 | C28: Coastal Foods Group | D28: 13 | E28: =INDEX(Quarters!$E:$E,MATCH(D28,Quarters!$B:$B,0)) -> Q1 2025 | F28: 5500000 | G28: 9961968.3 | J28: 0 | K28: 0 | L28: =J28-K28 -> 0
B29: PC-02 | C29: Coastal Foods Group | D29: 14 | E29: =INDEX(Quarters!$E:$E,MATCH(D29,Quarters!$B:$B,0)) -> Q2 2025 | F29: 5500000 | G29: 10481442 | J29: 0 | K29: 0 | L29: =J29-K29 -> 0
B30: PC-02 | C30: Coastal Foods Group | D30: 15 | E30: =INDEX(Quarters!$E:$E,MATCH(D30,Quarters!$B:$B,0)) -> Q3 2025 | F30: 5500000 | G30: 10993566 | H30: full_exit | I30: 1 | J30: 10993566 | K30: 5500000 | L30: =J30-K30 -> 5493565.5
B31: PC-03 | C31: Nimbus Data Systems | D31: 3 | E31: =INDEX(Quarters!$E:$E,MATCH(D31,Quarters!$B:$B,0)) -> Q3 2022 | F31: 4500000 | G31: 4500000 | J31: 0 | K31: 0 | L31: =J31-K31 -> 0
B32: PC-03 | C32: Nimbus Data Systems | D32: 4 | E32: =INDEX(Quarters!$E:$E,MATCH(D32,Quarters!$B:$B,0)) -> Q4 2022 | F32: 4500000 | G32: 4273731 | J32: 0 | K32: 0 | L32: =J32-K32 -> 0
B33: PC-03 | C33: Nimbus Data Systems | D33: 5 | E33: =INDEX(Quarters!$E:$E,MATCH(D33,Quarters!$B:$B,0)) -> Q1 2023 | F33: 4500000 | G33: 4115537.3 | J33: 0 | K33: 0 | L33: =J33-K33 -> 0
B34: PC-03 | C34: Nimbus Data Systems | D34: 6 | E34: =INDEX(Quarters!$E:$E,MATCH(D34,Quarters!$B:$B,0)) -> Q2 2023 | F34: 4500000 | G34: 3952898.1 | J34: 0 | K34: 0 | L34: =J34-K34 -> 0
B35: PC-03 | C35: Nimbus Data Systems | D35: 7 | E35: =INDEX(Quarters!$E:$E,MATCH(D35,Quarters!$B:$B,0)) -> Q3 2023 | F35: 4500000 | G35: 3799490 | J35: 0 | K35: 0 | L35: =J35-K35 -> 0
B36: PC-03 | C36: Nimbus Data Systems | D36: 8 | E36: =INDEX(Quarters!$E:$E,MATCH(D36,Quarters!$B:$B,0)) -> Q4 2023 | F36: 4500000 | G36: 3653066.5 | J36: 0 | K36: 0 | L36: =J36-K36 -> 0
B37: PC-03 | C37: Nimbus Data Systems | D37: 9 | E37: =INDEX(Quarters!$E:$E,MATCH(D37,Quarters!$B:$B,0)) -> Q1 2024 | F37: 4500000 | G37: 3606032.2 | J37: 0 | K37: 0 | L37: =J37-K37 -> 0
B38: PC-03 | C38: Nimbus Data Systems | D38: 10 | E38: =INDEX(Quarters!$E:$E,MATCH(D38,Quarters!$B:$B,0)) -> Q2 2024 | F38: 4500000 | G38: 3421777.6 | J38: 0 | K38: 0 | L38: =J38-K38 -> 0
B39: PC-03 | C39: Nimbus Data Systems | D39: 11 | E39: =INDEX(Quarters!$E:$E,MATCH(D39,Quarters!$B:$B,0)) -> Q3 2024 | F39: 4500000 | G39: 3405070.3 | J39: 0 | K39: 0 | L39: =J39-K39 -> 0
B40: PC-03 | C40: Nimbus Data Systems | D40: 12 | E40: =INDEX(Quarters!$E:$E,MATCH(D40,Quarters!$B:$B,0)) -> Q4 2024 | F40: 4500000 | G40: 3428135.6 | J40: 0 | K40: 0 | L40: =J40-K40 -> 0
B41: PC-03 | C41: Nimbus Data Systems | D41: 13 | E41: =INDEX(Quarters!$E:$E,MATCH(D41,Quarters!$B:$B,0)) -> Q1 2025 | F41: 4500000 | G41: 3410854.6 | J41: 0 | K41: 0 | L41: =J41-K41 -> 0
B42: PC-03 | C42: Nimbus Data Systems | D42: 14 | E42: =INDEX(Quarters!$E:$E,MATCH(D42,Quarters!$B:$B,0)) -> Q2 2025 | F42: 4500000 | G42: 3424169.1 | J42: 0 | K42: 0 | L42: =J42-K42 -> 0
... B60: PC-04 | C60: Harbor Dental Partners | D60: 17 | E60: =INDEX(Quarters!$E:$E,MATCH(D60,Quarters!$B:$B,0)) -> Q1 2026 | F60: 5000000 | G60: 9722689 | J60: 0 | K60: 0 | L60: =J60-K60 -> 0
B61: PC-04 | C61: Harbor Dental Partners | D61: 18 | E61: =INDEX(Quarters!$E:$E,MATCH(D61,Quarters!$B:$B,0)) -> Q2 2026 | F61: 5000000 | G61: 10208642 | H61: partial_recap | I61: 0.6 | J61: 6125185.5 | K61: 3000000 | L61: =J61-K61 -> 3125185.5
B62: PC-05 | C62: Trailhead Outdoor Co. | D62: 5 | E62: =INDEX(Quarters!$E:$E,MATCH(D62,Quarters!$B:$B,0)) -> Q1 2023 | F62: 4000000 | G62: 4000000 | J62: 0 | K62: 0 | L62: =J62-K62 -> 0
B63: PC-05 | C63: Trailhead Outdoor Co. | D63: 6 | E63: =INDEX(Quarters!$E:$E,MATCH(D63,Quarters!$B:$B,0)) -> Q2 2023 | F63: 4000000 | G63: 4062510.1 | J63: 0 | K63: 0 | L63: =J63-K63 -> 0
B64: PC-05 | C64: Trailhead Outdoor Co. | D64: 7 | E64: =INDEX(Quarters!$E:$E,MATCH(D64,Quarters!$B:$B,0)) -> Q3 2023 | F64: 4000000 | G64: 4143200.6 | J64: 0 | K64: 0 | L64: =J64-K64 -> 0
B65: PC-05 | C65: Trailhead Outdoor Co. | D65: 8 | E65: =INDEX(Quarters!$E:$E,MATCH(D65,Quarters!$B:$B,0)) -> Q4 2023 | F65: 4000000 | G65: 4230673 | J65: 0 | K65: 0 | L65: =J65-K65 -> 0
B66: PC-05 | C66: Trailhead Outdoor Co. | D66: 9 | E66: =INDEX(Quarters!$E:$E,MATCH(D66,Quarters!$B:$B,0)) -> Q1 2024 | F66: 4000000 | G66: 4323466.3 | J66: 0 | K66: 0 | L66: =J66-K66 -> 0
B67: PC-05 | C67: Trailhead Outdoor Co. | D67: 10 | E67: =INDEX(Quarters!$E:$E,MATCH(D67,Quarters!$B:$B,0)) -> Q2 2024 | F67: 4000000 | G67: 4368917.8 | J67: 0 | K67: 0 | L67: =J67-K67 -> 0
B68: PC-05 | C68: Trailhead Outdoor Co. | D68: 11 | E68: =INDEX(Quarters!$E:$E,MATCH(D68,Quarters!$B:$B,0)) -> Q3 2024 | F68: 4000000 | G68: 4409882.9 | J68: 0 | K68: 0 | L68: =J68-K68 -> 0
B69: PC-05 | C69: Trailhead Outdoor Co. | D69: 12 | E69: =INDEX(Quarters!$E:$E,MATCH(D69,Quarters!$B:$B,0)) -> Q4 2024 | F69: 4000000 | G69: 4509457 | J69: 0 | K69: 0 | L69: =J69-K69 -> 0
B70: PC-05 | C70: Trailhead Outdoor Co. | D70: 13 | E70: =INDEX(Quarters!$E:$E,MATCH(D70,Quarters!$B:$B,0)) -> Q1 2025 | F70: 4000000 | G70: 4563962.6 | J70: 0 | K70: 0 | L70: =J70-K70 -> 0
B71: PC-05 | C71: Trailhead Outdoor Co. | D71: 14 | E71: =INDEX(Quarters!$E:$E,MATCH(D71,Quarters!$B:$B,0)) -> Q2 2025 | F71: 4000000 | G71: 4569636.2 | J71: 0 | K71: 0 | L71: =J71-K71 -> 0
B72: PC-05 | C72: Trailhead Outdoor Co. | D72: 15 | E72: =INDEX(Quarters!$E:$E,MATCH(D72,Quarters!$B:$B,0)) -> Q3 2025 | F72: 4000000 | G72: 4581824 | J72: 0 | K72: 0 | L72: =J72-K72 -> 0
B73: PC-05 | C73: Trailhead Outdoor Co. | D73: 16 | E73: =INDEX(Quarters!$E:$E,MATCH(D73,Quarters!$B:$B,0)) -> Q4 2025 | F73: 4000000 | G73: 4603841.9 | J73: 0 | K73: 0 | L73: =J73-K73 -> 0
... B86: PC-06 | C86: Summit Logistics | D86: 16 | E86: =INDEX(Quarters!$E:$E,MATCH(D86,Quarters!$B:$B,0)) -> Q4 2025 | F86: 5000000 | G86: 13309195 | J86: 0 | K86: 0 | L86: =J86-K86 -> 0
B87: PC-06 | C87: Summit Logistics | D87: 17 | E87: =INDEX(Quarters!$E:$E,MATCH(D87,Quarters!$B:$B,0)) -> Q1 2026 | F87: 5000000 | G87: 14803879 | H87: full_exit | I87: 1 | J87: 14803879 | K87: 5000000 | L87: =J87-K87 -> 9803878.7
B88: PC-07 | C88: BluePeak Software | D88: 7 | E88: =INDEX(Quarters!$E:$E,MATCH(D88,Quarters!$B:$B,0)) -> Q3 2023 | F88: 4500000 | G88: 4500000 | J88: 0 | K88: 0 | L88: =J88-K88 -> 0
B89: PC-07 | C89: BluePeak Software | D89: 8 | E89: =INDEX(Quarters!$E:$E,MATCH(D89,Quarters!$B:$B,0)) -> Q4 2023 | F89: 4500000 | G89: 4717652.3 | J89: 0 | K89: 0 | L89: =J89-K89 -> 0
B90: PC-07 | C90: BluePeak Software | D90: 9 | E90: =INDEX(Quarters!$E:$E,MATCH(D90,Quarters!$B:$B,0)) -> Q1 2024 | F90: 4500000 | G90: 4973112.8 | J90: 0 | K90: 0 | L90: =J90-K90 -> 0
B91: PC-07 | C91: BluePeak Software | D91: 10 | E91: =INDEX(Quarters!$E:$E,MATCH(D91,Quarters!$B:$B,0)) -> Q2 2024 | F91: 4500000 | G91: 5270350.6 | J91: 0 | K91: 0 | L91: =J91-K91 -> 0
B92: PC-07 | C92: BluePeak Software | D92: 11 | E92: =INDEX(Quarters!$E:$E,MATCH(D92,Quarters!$B:$B,0)) -> Q3 2024 | F92: 4500000 | G92: 5583190 | J92: 0 | K92: 0 | L92: =J92-K92 -> 0
B93: PC-07 | C93: BluePeak Software | D93: 12 | E93: =INDEX(Quarters!$E:$E,MATCH(D93,Quarters!$B:$B,0)) -> Q4 2024 | F93: 4500000 | G93: 5929262 | J93: 0 | K93: 0 | L93: =J93-K93 -> 0
B94: PC-07 | C94: BluePeak Software | D94: 13 | E94: =INDEX(Quarters!$E:$E,MATCH(D94,Quarters!$B:$B,0)) -> Q1 2025 | F94: 4500000 | G94: 6242434.7 | J94: 0 | K94: 0 | L94: =J94-K94 -> 0
B95: PC-07 | C95: BluePeak Software | D95: 14 | E95: =INDEX(Quarters!$E:$E,MATCH(D95,Quarters!$B:$B,0)) -> Q2 2025 | F95: 4500000 | G95: 6547817.3 | J95: 0 | K95: 0 | L95: =J95-K95 -> 0
B96: PC-07 | C96: BluePeak Software | D96: 15 | E96: =INDEX(Quarters!$E:$E,MATCH(D96,Quarters!$B:$B,0)) -> Q3 2025 | F96: 4500000 | G96: 6895135.6 | J96: 0 | K96: 0 | L96: =J96-K96 -> 0
B97: PC-07 | C97: BluePeak Software | D97: 16 | E97: =INDEX(Quarters!$E:$E,MATCH(D97,Quarters!$B:$B,0)) -> Q4 2025 | F97: 4500000 | G97: 7127860.2 | J97: 0 | K97: 0 | L97: =J97-K97 -> 0
B98: PC-07 | C98: BluePeak Software | D98: 17 | E98: =INDEX(Quarters!$E:$E,MATCH(D98,Quarters!$B:$B,0)) -> Q1 2026 | F98: 4500000 | G98: 7388986.8 | J98: 0 | K98: 0 | L98: =J98-K98 -> 0
B99: PC-07 | C99: BluePeak Software | D99: 18 | E99: =INDEX(Quarters!$E:$E,MATCH(D99,Quarters!$B:$B,0)) -> Q2 2026 | F99: 4500000 | G99: 7670711.2 | H99: full_exit | I99: 1 | J99: 7670711.2 | K99: 4500000 | L99: =J99-K99 -> 3170711.2
B100: PC-08 | C100: Ridgeline Materials | D100: 8 | E100: =INDEX(Quarters!$E:$E,MATCH(D100,Quarters!$B:$B,0)) -> Q4 2023 | F100: 3500000 | G100: 3500000 | J100: 0 | K100: 0 | L100: =J100-K100 -> 0
B101: PC-08 | C101: Ridgeline Materials | D101: 9 | E101: =INDEX(Quarters!$E:$E,MATCH(D101,Quarters!$B:$B,0)) -> Q1 2024 | F101: 3500000 | G101: 3514096.4 | J101: 0 | K101: 0 | L101: =J101-K101 -> 0
B102: PC-08 | C102: Ridgeline Materials | D102: 10 | E102: =INDEX(Quarters!$E:$E,MATCH(D102,Quarters!$B:$B,0)) -> Q2 2024 | F102: 3500000 | G102: 3577342.2 | J102: 0 | K102: 0 | L102: =J102-K102 -> 0
B103: PC-08 | C103: Ridgeline Materials | D103: 11 | E103: =INDEX(Quarters!$E:$E,MATCH(D103,Quarters!$B:$B,0)) -> Q3 2024 | F103: 3500000 | G103: 3595032.9 | J103: 0 | K103: 0 | L103: =J103-K103 -> 0
B104: PC-08 | C104: Ridgeline Materials | D104: 12 | E104: =INDEX(Quarters!$E:$E,MATCH(D104,Quarters!$B:$B,0)) -> Q4 2024 | F104: 3500000 | G104: 3631768.3 | J104: 0 | K104: 0 | L104: =J104-K104 -> 0
B105: PC-08 | C105: Ridgeline Materials | D105: 13 | E105: =INDEX(Quarters!$E:$E,MATCH(D105,Quarters!$B:$B,0)) -> Q1 2025 | F105: 3500000 | G105: 3729798 | J105: 0 | K105: 0 | L105: =J105-K105 -> 0
B106: PC-08 | C106: Ridgeline Materials | D106: 14 | E106: =INDEX(Quarters!$E:$E,MATCH(D106,Quarters!$B:$B,0)) -> Q2 2025 | F106: 3500000 | G106: 3768727.2 | J106: 0 | K106: 0 | L106: =J106-K106 -> 0
B107: PC-08 | C107: Ridgeline Materials | D107: 15 | E107: =INDEX(Quarters!$E:$E,MATCH(D107,Quarters!$B:$B,0)) -> Q3 2025 | F107: 3500000 | G107: 3849284.4 | J107: 0 | K107: 0 | L107: =J107-K107 -> 0
B108: PC-08 | C108: Ridgeline Materials | D108: 16 | E108: =INDEX(Quarters!$E:$E,MATCH(D108,Quarters!$B:$B,0)) -> Q4 2025 | F108: 3500000 | G108: 3867236.7 | J108: 0 | K108: 0 | L108: =J108-K108 -> 0
B109: PC-08 | C109: Ridgeline Materials | D109: 17 | E109: =INDEX(Quarters!$E:$E,MATCH(D109,Quarters!$B:$B,0)) -> Q1 2026 | F109: 3500000 | G109: 3913433.3 | J109: 0 | K109: 0 | L109: =J109-K109 -> 0
B110: PC-08 | C110: Ridgeline Materials | D110: 18 | E110: =INDEX(Quarters!$E:$E,MATCH(D110,Quarters!$B:$B,0)) -> Q2 2026 | F110: 3500000 | G110: 3931042.9 | J110: 0 | K110: 0 | L110: =J110-K110 -> 0
B111: PC-09 | C111: Fairmont Health Services | D111: 9 | E111: =INDEX(Quarters!$E:$E,MATCH(D111,Quarters!$B:$B,0)) -> Q1 2024 | F111: 4000000 | G111: 4000000 | J111: 0 | K111: 0 | L111: =J111-K111 -> 0
... B119: PC-09 | C119: Fairmont Health Services | D119: 17 | E119: =INDEX(Quarters!$E:$E,MATCH(D119,Quarters!$B:$B,0)) -> Q1 2026 | F119: 4000000 | G119: 5917392 | J119: 0 | K119: 0 | L119: =J119-K119 -> 0
B120: PC-09 | C120: Fairmont Health Services | D120: 18 | E120: =INDEX(Quarters!$E:$E,MATCH(D120,Quarters!$B:$B,0)) -> Q2 2026 | F120: 4000000 | G120: 6199332.5 | H120: full_exit | I120: 1 | J120: 6199332.5 | K120: 4000000 | L120: =J120-K120 -> 2199332.5
B121: PC-10 | C121: Alpine Consumer Brands | D121: 10 | E121: =INDEX(Quarters!$E:$E,MATCH(D121,Quarters!$B:$B,0)) -> Q2 2024 | F121: 3500000 | G121: 3500000 | J121: 0 | K121: 0 | L121: =J121-K121 -> 0
B122: PC-10 | C122: Alpine Consumer Brands | D122: 11 | E122: =INDEX(Quarters!$E:$E,MATCH(D122,Quarters!$B:$B,0)) -> Q3 2024 | F122: 3500000 | G122: 3698772.4 | J122: 0 | K122: 0 | L122: =J122-K122 -> 0
B123: PC-10 | C123: Alpine Consumer Brands | D123: 12 | E123: =INDEX(Quarters!$E:$E,MATCH(D123,Quarters!$B:$B,0)) -> Q4 2024 | F123: 3500000 | G123: 3899476 | J123: 0 | K123: 0 | L123: =J123-K123 -> 0
B124: PC-10 | C124: Alpine Consumer Brands | D124: 13 | E124: =INDEX(Quarters!$E:$E,MATCH(D124,Quarters!$B:$B,0)) -> Q1 2025 | F124: 3500000 | G124: 4185000.9 | J124: 0 | K124: 0 | L124: =J124-K124 -> 0
B125: PC-10 | C125: Alpine Consumer Brands | D125: 14 | E125: =INDEX(Quarters!$E:$E,MATCH(D125,Quarters!$B:$B,0)) -> Q2 2025 | F125: 3500000 | G125: 4398970.5 | J125: 0 | K125: 0 | L125: =J125-K125 -> 0
B126: PC-10 | C126: Alpine Consumer Brands | D126: 15 | E126: =INDEX(Quarters!$E:$E,MATCH(D126,Quarters!$B:$B,0)) -> Q3 2025 | F126: 3500000 | G126: 4582486.9 | J126: 0 | K126: 0 | L126: =J126-K126 -> 0
B127: PC-10 | C127: Alpine Consumer Brands | D127: 16 | E127: =INDEX(Quarters!$E:$E,MATCH(D127,Quarters!$B:$B,0)) -> Q4 2025 | F127: 3500000 | G127: 4839799.5 | J127: 0 | K127: 0 | L127: =J127-K127 -> 0
B128: PC-10 | C128: Alpine Consumer Brands | D128: 17 | E128: =INDEX(Quarters!$E:$E,MATCH(D128,Quarters!$B:$B,0)) -> Q1 2026 | F128: 3500000 | G128: 5113925.6 | J128: 0 | K128: 0 | L128: =J128-K128 -> 0
B129: PC-10 | C129: Alpine Consumer Brands | D129: 18 | E129: =INDEX(Quarters!$E:$E,MATCH(D129,Quarters!$B:$B,0)) -> Q2 2026 | F129: 3500000 | G129: 5473487 | J129: 0 | K129: 0 | L129: =J129-K129 -> 0

Sheet Mgmt Fee Schedule
A1: Management Fee Schedule
A2: 2% of committed capital during the investment period; 2% of remaining invested cost thereafter
B3: Qtr # | C3: Quarter | D3: In Investment Period | E3: Fee Basis ($) | F3: Fee Basis | G3: Management Fee ($)
B4: 1 | C4: =Quarters!$E$4 -> Q1 2022 | D4: =Quarters!$G$4 -> TRUE | E4: =IF(D4,Assumptions!$C$5,SUMIFS('Portfolio Marks'!$F:$F,'Portfolio Marks'!$D:$D,B4-1)) -> 50000000 | F4: =IF(D4,"Committed capital","Invested cost (step-down)") -> Committed capital | G4: =E4*Assumptions!$C$9/4 -> 250000
B5: 2 | C5: =Quarters!$E$5 -> Q2 2022 | D5: =Quarters!$G$5 -> TRUE | E5: =IF(D5,Assumptions!$C$5,SUMIFS('Portfolio Marks'!$F:$F,'Portfolio Marks'!$D:$D,B5-1)) -> 50000000 | F5: =IF(D5,"Committed capital","Invested cost (step-down)") -> Committed capital | G5: =E5*Assumptions!$C$9/4 -> 250000
B6: 3 | C6: =Quarters!$E$6 -> Q3 2022 | D6: =Quarters!$G$6 -> TRUE | E6: =IF(D6,Assumptions!$C$5,SUMIFS('Portfolio Marks'!$F:$F,'Portfolio Marks'!$D:$D,B6-1)) -> 50000000 | F6: =IF(D6,"Committed capital","Invested cost (step-down)") -> Committed capital | G6: =E6*Assumptions!$C$9/4 -> 250000
B7: 4 | C7: =Quarters!$E$7 -> Q4 2022 | D7: =Quarters!$G$7 -> TRUE | E7: =IF(D7,Assumptions!$C$5,SUMIFS('Portfolio Marks'!$F:$F,'Portfolio Marks'!$D:$D,B7-1)) -> 50000000 | F7: =IF(D7,"Committed capital","Invested cost (step-down)") -> Committed capital | G7: =E7*Assumptions!$C$9/4 -> 250000
B8: 5 | C8: =Quarters!$E$8 -> Q1 2023 | D8: =Quarters!$G$8 -> TRUE | E8: =IF(D8,Assumptions!$C$5,SUMIFS('Portfolio Marks'!$F:$F,'Portfolio Marks'!$D:$D,B8-1)) -> 50000000 | F8: =IF(D8,"Committed capital","Invested cost (step-down)") -> Committed capital | G8: =E8*Assumptions!$C$9/4 -> 250000
B9: 6 | C9: =Quarters!$E$9 -> Q2 2023 | D9: =Quarters!$G$9 -> TRUE | E9: =IF(D9,Assumptions!$C$5,SUMIFS('Portfolio Marks'!$F:$F,'Portfolio Marks'!$D:$D,B9-1)) -> 50000000 | F9: =IF(D9,"Committed capital","Invested cost (step-down)") -> Committed capital | G9: =E9*Assumptions!$C$9/4 -> 250000
B10: 7 | C10: =Quarters!$E$10 -> Q3 2023 | D10: =Quarters!$G$10 -> TRUE | E10: =IF(D10,Assumptions!$C$5,SUMIFS('Portfolio Marks'!$F:$F,'Portfolio Marks'!$D:$D,B10-1)) -> 50000000 | F10: =IF(D10,"Committed capital","Invested cost (step-down)") -> Committed capital | G10: =E10*Assumptions!$C$9/4 -> 250000
B11: 8 | C11: =Quarters!$E$11 -> Q4 2023 | D11: =Quarters!$G$11 -> TRUE | E11: =IF(D11,Assumptions!$C$5,SUMIFS('Portfolio Marks'!$F:$F,'Portfolio Marks'!$D:$D,B11-1)) -> 50000000 | F11: =IF(D11,"Committed capital","Invested cost (step-down)") -> Committed capital | G11: =E11*Assumptions!$C$9/4 -> 250000
B12: 9 | C12: =Quarters!$E$12 -> Q1 2024 | D12: =Quarters!$G$12 -> TRUE | E12: =IF(D12,Assumptions!$C$5,SUMIFS('Portfolio Marks'!$F:$F,'Portfolio Marks'!$D:$D,B12-1)) -> 50000000 | F12: =IF(D12,"Committed capital","Invested cost (step-down)") -> Committed capital | G12: =E12*Assumptions!$C$9/4 -> 250000
B13: 10 | C13: =Quarters!$E$13 -> Q2 2024 | D13: =Quarters!$G$13 -> TRUE | E13: =IF(D13,Assumptions!$C$5,SUMIFS('Portfolio Marks'!$F:$F,'Portfolio Marks'!$D:$D,B13-1)) -> 50000000 | F13: =IF(D13,"Committed capital","Invested cost (step-down)") -> Committed capital | G13: =E13*Assumptions!$C$9/4 -> 250000
B14: 11 | C14: =Quarters!$E$14 -> Q3 2024 | D14: =Quarters!$G$14 -> TRUE | E14: =IF(D14,Assumptions!$C$5,SUMIFS('Portfolio Marks'!$F:$F,'Portfolio Marks'!$D:$D,B14-1)) -> 50000000 | F14: =IF(D14,"Committed capital","Invested cost (step-down)") -> Committed capital | G14: =E14*Assumptions!$C$9/4 -> 250000
B15: 12 | C15: =Quarters!$E$15 -> Q4 2024 | D15: =Quarters!$G$15 -> TRUE | E15: =IF(D15,Assumptions!$C$5,SUMIFS('Portfolio Marks'!$F:$F,'Portfolio Marks'!$D:$D,B15-1)) -> 50000000 | F15: =IF(D15,"Committed capital","Invested cost (step-down)") -> Committed capital | G15: =E15*Assumptions!$C$9/4 -> 250000
B16: 13 | C16: =Quarters!$E$16 -> Q1 2025 | D16: =Quarters!$G$16 -> FALSE | E16: =IF(D16,Assumptions!$C$5,SUMIFS('Portfolio Marks'!$F:$F,'Portfolio Marks'!$D:$D,B16-1)) -> 45500000 | F16: =IF(D16,"Committed capital","Invested cost (step-down)") -> Invested cost (step-down) | G16: =E16*Assumptions!$C$9/4 -> 227500
B17: 14 | C17: =Quarters!$E$17 -> Q2 2025 | D17: =Quarters!$G$17 -> FALSE | E17: =IF(D17,Assumptions!$C$5,SUMIFS('Portfolio Marks'!$F:$F,'Portfolio Marks'!$D:$D,B17-1)) -> 45500000 | F17: =IF(D17,"Committed capital","Invested cost (step-down)") -> Invested cost (step-down) | G17: =E17*Assumptions!$C$9/4 -> 227500
B18: 15 | C18: =Quarters!$E$18 -> Q3 2025 | D18: =Quarters!$G$18 -> FALSE | E18: =IF(D18,Assumptions!$C$5,SUMIFS('Portfolio Marks'!$F:$F,'Portfolio Marks'!$D:$D,B18-1)) -> 39500000 | F18: =IF(D18,"Committed capital","Invested cost (step-down)") -> Invested cost (step-down) | G18: =E18*Assumptions!$C$9/4 -> 197500
B19: 16 | C19: =Quarters!$E$19 -> Q4 2025 | D19: =Quarters!$G$19 -> FALSE | E19: =IF(D19,Assumptions!$C$5,SUMIFS('Portfolio Marks'!$F:$F,'Portfolio Marks'!$D:$D,B19-1)) -> 39500000 | F19: =IF(D19,"Committed capital","Invested cost (step-down)") -> Invested cost (step-down) | G19: =E19*Assumptions!$C$9/4 -> 197500
B20: 17 | C20: =Quarters!$E$20 -> Q1 2026 | D20: =Quarters!$G$20 -> FALSE | E20: =IF(D20,Assumptions!$C$5,SUMIFS('Portfolio Marks'!$F:$F,'Portfolio Marks'!$D:$D,B20-1)) -> 34000000 | F20: =IF(D20,"Committed capital","Invested cost (step-down)") -> Invested cost (step-down) | G20: =E20*Assumptions!$C$9/4 -> 170000
B21: 18 | C21: =Quarters!$E$21 -> Q2 2026 | D21: =Quarters!$G$21 -> FALSE | E21: =IF(D21,Assumptions!$C$5,SUMIFS('Portfolio Marks'!$F:$F,'Portfolio Marks'!$D:$D,B21-1)) -> 34000000 | F21: =IF(D21,"Committed capital","Invested cost (step-down)") -> Invested cost (step-down) | G21: =E21*Assumptions!$C$9/4 -> 170000

Sheet Capital Call Schedule
A1: Capital Call Schedule
A2: Fund-level quarterly capital calls — investment need + management fee
B3: Qtr # | C3: Quarter | D3: Investment Call ($) | E3: Mgmt Fee Call ($) | F3: Total Call ($) | G3: Cumulative Called ($)
B4: 1 | C4: =Quarters!$E$4 -> Q1 2022 | D4: =SUMIFS('Portfolio Companies'!$G:$G,'Portfolio Companies'!$E:$E,B4) -> 6000000 | E4: ='Mgmt Fee Schedule'!$G$4 -> 250000 | F4: =D4+E4 -> 6250000 | G4: =F4 -> 6250000
B5: 2 | C5: =Quarters!$E$5 -> Q2 2022 | D5: =SUMIFS('Portfolio Companies'!$G:$G,'Portfolio Companies'!$E:$E,B5) -> 5500000 | E5: ='Mgmt Fee Schedule'!$G$5 -> 250000 | F5: =D5+E5 -> 5750000 | G5: =G4+F5 -> 12000000
B6: 3 | C6: =Quarters!$E$6 -> Q3 2022 | D6: =SUMIFS('Portfolio Companies'!$G:$G,'Portfolio Companies'!$E:$E,B6) -> 4500000 | E6: ='Mgmt Fee Schedule'!$G$6 -> 250000 | F6: =D6+E6 -> 4750000 | G6: =G5+F6 -> 16750000
B7: 4 | C7: =Quarters!$E$7 -> Q4 2022 | D7: =SUMIFS('Portfolio Companies'!$G:$G,'Portfolio Companies'!$E:$E,B7) -> 5000000 | E7: ='Mgmt Fee Schedule'!$G$7 -> 250000 | F7: =D7+E7 -> 5250000 | G7: =G6+F7 -> 22000000
B8: 5 | C8: =Quarters!$E$8 -> Q1 2023 | D8: =SUMIFS('Portfolio Companies'!$G:$G,'Portfolio Companies'!$E:$E,B8) -> 4000000 | E8: ='Mgmt Fee Schedule'!$G$8 -> 250000 | F8: =D8+E8 -> 4250000 | G8: =G7+F8 -> 26250000
B9: 6 | C9: =Quarters!$E$9 -> Q2 2023 | D9: =SUMIFS('Portfolio Companies'!$G:$G,'Portfolio Companies'!$E:$E,B9) -> 5000000 | E9: ='Mgmt Fee Schedule'!$G$9 -> 250000 | F9: =D9+E9 -> 5250000 | G9: =G8+F9 -> 31500000
B10: 7 | C10: =Quarters!$E$10 -> Q3 2023 | D10: =SUMIFS('Portfolio Companies'!$G:$G,'Portfolio Companies'!$E:$E,B10) -> 4500000 | E10: ='Mgmt Fee Schedule'!$G$10 -> 250000 | F10: =D10+E10 -> 4750000 | G10: =G9+F10 -> 36250000
B11: 8 | C11: =Quarters!$E$11 -> Q4 2023 | D11: =SUMIFS('Portfolio Companies'!$G:$G,'Portfolio Companies'!$E:$E,B11) -> 3500000 | E11: ='Mgmt Fee Schedule'!$G$11 -> 250000 | F11: =D11+E11 -> 3750000 | G11: =G10+F11 -> 40000000
B12: 9 | C12: =Quarters!$E$12 -> Q1 2024 | D12: =SUMIFS('Portfolio Companies'!$G:$G,'Portfolio Companies'!$E:$E,B12) -> 4000000 | E12: ='Mgmt Fee Schedule'!$G$12 -> 250000 | F12: =D12+E12 -> 4250000 | G12: =G11+F12 -> 44250000
B13: 10 | C13: =Quarters!$E$13 -> Q2 2024 | D13: =SUMIFS('Portfolio Companies'!$G:$G,'Portfolio Companies'!$E:$E,B13) -> 3500000 | E13: ='Mgmt Fee Schedule'!$G$13 -> 250000 | F13: =D13+E13 -> 3750000 | G13: =G12+F13 -> 48000000
B14: 11 | C14: =Quarters!$E$14 -> Q3 2024 | D14: =SUMIFS('Portfolio Companies'!$G:$G,'Portfolio Companies'!$E:$E,B14) -> 0 | E14: ='Mgmt Fee Schedule'!$G$14 -> 250000 | F14: =D14+E14 -> 250000 | G14: =G13+F14 -> 48250000
B15: 12 | C15: =Quarters!$E$15 -> Q4 2024 | D15: =SUMIFS('Portfolio Companies'!$G:$G,'Portfolio Companies'!$E:$E,B15) -> 0 | E15: ='Mgmt Fee Schedule'!$G$15 -> 250000 | F15: =D15+E15 -> 250000 | G15: =G14+F15 -> 48500000
B16: 13 | C16: =Quarters!$E$16 -> Q1 2025 | D16: =SUMIFS('Portfolio Companies'!$G:$G,'Portfolio Companies'!$E:$E,B16) -> 0 | E16: ='Mgmt Fee Schedule'!$G$16 -> 227500 | F16: =D16+E16 -> 227500 | G16: =G15+F16 -> 48727500
B17: 14 | C17: =Quarters!$E$17 -> Q2 2025 | D17: =SUMIFS('Portfolio Companies'!$G:$G,'Portfolio Companies'!$E:$E,B17) -> 0 | E17: ='Mgmt Fee Schedule'!$G$17 -> 227500 | F17: =D17+E17 -> 227500 | G17: =G16+F17 -> 48955000
B18: 15 | C18: =Quarters!$E$18 -> Q3 2025 | D18: =SUMIFS('Portfolio Companies'!$G:$G,'Portfolio Companies'!$E:$E,B18) -> 0 | E18: ='Mgmt Fee Schedule'!$G$18 -> 197500 | F18: =D18+E18 -> 197500 | G18: =G17+F18 -> 49152500
B19: 16 | C19: =Quarters!$E$19 -> Q4 2025 | D19: =SUMIFS('Portfolio Companies'!$G:$G,'Portfolio Companies'!$E:$E,B19) -> 0 | E19: ='Mgmt Fee Schedule'!$G$19 -> 197500 | F19: =D19+E19 -> 197500 | G19: =G18+F19 -> 49350000
B20: 17 | C20: =Quarters!$E$20 -> Q1 2026 | D20: =SUMIFS('Portfolio Companies'!$G:$G,'Portfolio Companies'!$E:$E,B20) -> 0 | E20: ='Mgmt Fee Schedule'!$G$20 -> 170000 | F20: =D20+E20 -> 170000 | G20: =G19+F20 -> 49520000
B21: 18 | C21: =Quarters!$E$21 -> Q2 2026 | D21: =SUMIFS('Portfolio Companies'!$G:$G,'Portfolio Companies'!$E:$E,B21) -> 0 | E21: ='Mgmt Fee Schedule'!$G$21 -> 170000 | F21: =D21+E21 -> 170000 | G21: =G20+F21 -> 49690000
C22: Total / Unfunded Commitment | F22: =SUM(F4:F21) -> 49690000 | G22: =Assumptions!$C$5-G21 -> 310000
C23: (Unfunded commitment remaining)

Sheet Distribution Waterfall
A1: Distribution Waterfall
A2: European (whole-fund) waterfall, run cumulatively by quarter: Return of Capital -> Preferred Return -> GP Catch-up -> 80/20 Carry Split
B3: Qtr # | C3: Quarter | D3: Distributable ($) | E3: Cum. Contributions (BOP) | F3: Cum. Contributions (EOP) | G3: Cum. ROC Distributed (BOP) | H3: Preferred Accrual (Qtr) | I3: Cum. Preferred Accrued (EOP) | J3: Cum. Preferred Paid (BOP) | K3: Cum. GP Catch-up Paid (BOP) | L3: Tier 1: Return of Capital | M3: Cum. ROC Distributed (EOP) | N3: Tier 2: Preferred Return | O3: Cum. Preferred Paid (EOP) | P3: Target Cum. Catch-up (Total) | Q3: Tier 3: GP Catch-up | R3: Cum. GP Catch-up Paid (EOP) | S3: Tier 4: Carry (Total) | T3: Tier 4: Carry to LPs (80%) | U3: Tier 4: Carry to GP (20%) | V3: Total to LPs | W3: Total to GP
B4: 1 | C4: =Quarters!$E$4 -> Q1 2022 | D4: =SUMIFS('Portfolio Marks'!$J:$J,'Portfolio Marks'!$D:$D,B4) -> 0 | E4: 0 | F4: =E4+'Capital Call Schedule'!$F$4 -> 6250000 | G4: 0 | H4: =(E4-G4)*Assumptions!$C$11/4 -> 0 | I4: =H4 -> 0 | J4: 0 | K4: 0 | L4: =MIN(D4,MAX(F4-G4,0)) -> 0 | M4: =G4+L4 -> 0 | N4: =MIN(D4-L4,MAX(I4-J4,0)) -> 0 | O4: =J4+N4 -> 0 | P4: =(Assumptions!$C$13/(1-Assumptions!$C$13))*O4 -> 0 | Q4: =MIN(D4-L4-N4,MAX(P4-K4,0)) -> 0 | R4: =K4+Q4 -> 0 | S4: =D4-L4-N4-Q4 -> 0 | T4: =S4*(1-Assumptions!$C$13) -> 0 | U4: =S4*Assumptions!$C$13 -> 0 | V4: =L4+N4+T4 -> 0 | W4: =Q4+U4 -> 0
B5: 2 | C5: =Quarters!$E$5 -> Q2 2022 | D5: =SUMIFS('Portfolio Marks'!$J:$J,'Portfolio Marks'!$D:$D,B5) -> 0 | E5: =F4 -> 6250000 | F5: =E5+'Capital Call Schedule'!$F$5 -> 12000000 | G5: =M4 -> 0 | H5: =(E5-G5)*Assumptions!$C$11/4 -> 125000 | I5: =I4+H5 -> 125000 | J5: =O4 -> 0 | K5: =R4 -> 0 | L5: =MIN(D5,MAX(F5-G5,0)) -> 0 | M5: =G5+L5 -> 0 | N5: =MIN(D5-L5,MAX(I5-J5,0)) -> 0 | O5: =J5+N5 -> 0 | P5: =(Assumptions!$C$13/(1-Assumptions!$C$13))*O5 -> 0 | Q5: =MIN(D5-L5-N5,MAX(P5-K5,0)) -> 0 | R5: =K5+Q5 -> 0 | S5: =D5-L5-N5-Q5 -> 0 | T5: =S5*(1-Assumptions!$C$13) -> 0 | U5: =S5*Assumptions!$C$13 -> 0 | V5: =L5+N5+T5 -> 0 | W5: =Q5+U5 -> 0
B6: 3 | C6: =Quarters!$E$6 -> Q3 2022 | D6: =SUMIFS('Portfolio Marks'!$J:$J,'Portfolio Marks'!$D:$D,B6) -> 0 | E6: =F5 -> 12000000 | F6: =E6+'Capital Call Schedule'!$F$6 -> 16750000 | G6: =M5 -> 0 | H6: =(E6-G6)*Assumptions!$C$11/4 -> 240000 | I6: =I5+H6 -> 365000 | J6: =O5 -> 0 | K6: =R5 -> 0 | L6: =MIN(D6,MAX(F6-G6,0)) -> 0 | M6: =G6+L6 -> 0 | N6: =MIN(D6-L6,MAX(I6-J6,0)) -> 0 | O6: =J6+N6 -> 0 | P6: =(Assumptions!$C$13/(1-Assumptions!$C$13))*O6 -> 0 | Q6: =MIN(D6-L6-N6,MAX(P6-K6,0)) -> 0 | R6: =K6+Q6 -> 0 | S6: =D6-L6-N6-Q6 -> 0 | T6: =S6*(1-Assumptions!$C$13) -> 0 | U6: =S6*Assumptions!$C$13 -> 0 | V6: =L6+N6+T6 -> 0 | W6: =Q6+U6 -> 0
B7: 4 | C7: =Quarters!$E$7 -> Q4 2022 | D7: =SUMIFS('Portfolio Marks'!$J:$J,'Portfolio Marks'!$D:$D,B7) -> 0 | E7: =F6 -> 16750000 | F7: =E7+'Capital Call Schedule'!$F$7 -> 22000000 | G7: =M6 -> 0 | H7: =(E7-G7)*Assumptions!$C$11/4 -> 335000 | I7: =I6+H7 -> 700000 | J7: =O6 -> 0 | K7: =R6 -> 0 | L7: =MIN(D7,MAX(F7-G7,0)) -> 0 | M7: =G7+L7 -> 0 | N7: =MIN(D7-L7,MAX(I7-J7,0)) -> 0 | O7: =J7+N7 -> 0 | P7: =(Assumptions!$C$13/(1-Assumptions!$C$13))*O7 -> 0 | Q7: =MIN(D7-L7-N7,MAX(P7-K7,0)) -> 0 | R7: =K7+Q7 -> 0 | S7: =D7-L7-N7-Q7 -> 0 | T7: =S7*(1-Assumptions!$C$13) -> 0 | U7: =S7*Assumptions!$C$13 -> 0 | V7: =L7+N7+T7 -> 0 | W7: =Q7+U7 -> 0
B8: 5 | C8: =Quarters!$E$8 -> Q1 2023 | D8: =SUMIFS('Portfolio Marks'!$J:$J,'Portfolio Marks'!$D:$D,B8) -> 0 | E8: =F7 -> 22000000 | F8: =E8+'Capital Call Schedule'!$F$8 -> 26250000 | G8: =M7 -> 0 | H8: =(E8-G8)*Assumptions!$C$11/4 -> 440000 | I8: =I7+H8 -> 1140000 | J8: =O7 -> 0 | K8: =R7 -> 0 | L8: =MIN(D8,MAX(F8-G8,0)) -> 0 | M8: =G8+L8 -> 0 | N8: =MIN(D8-L8,MAX(I8-J8,0)) -> 0 | O8: =J8+N8 -> 0 | P8: =(Assumptions!$C$13/(1-Assumptions!$C$13))*O8 -> 0 | Q8: =MIN(D8-L8-N8,MAX(P8-K8,0)) -> 0 | R8: =K8+Q8 -> 0 | S8: =D8-L8-N8-Q8 -> 0 | T8: =S8*(1-Assumptions!$C$13) -> 0 | U8: =S8*Assumptions!$C$13 -> 0 | V8: =L8+N8+T8 -> 0 | W8: =Q8+U8 -> 0
B9: 6 | C9: =Quarters!$E$9 -> Q2 2023 | D9: =SUMIFS('Portfolio Marks'!$J:$J,'Portfolio Marks'!$D:$D,B9) -> 0 | E9: =F8 -> 26250000 | F9: =E9+'Capital Call Schedule'!$F$9 -> 31500000 | G9: =M8 -> 0 | H9: =(E9-G9)*Assumptions!$C$11/4 -> 525000 | I9: =I8+H9 -> 1665000 | J9: =O8 -> 0 | K9: =R8 -> 0 | L9: =MIN(D9,MAX(F9-G9,0)) -> 0 | M9: =G9+L9 -> 0 | N9: =MIN(D9-L9,MAX(I9-J9,0)) -> 0 | O9: =J9+N9 -> 0 | P9: =(Assumptions!$C$13/(1-Assumptions!$C$13))*O9 -> 0 | Q9: =MIN(D9-L9-N9,MAX(P9-K9,0)) -> 0 | R9: =K9+Q9 -> 0 | S9: =D9-L9-N9-Q9 -> 0 | T9: =S9*(1-Assumptions!$C$13) -> 0 | U9: =S9*Assumptions!$C$13 -> 0 | V9: =L9+N9+T9 -> 0 | W9: =Q9+U9 -> 0
B10: 7 | C10: =Quarters!$E$10 -> Q3 2023 | D10: =SUMIFS('Portfolio Marks'!$J:$J,'Portfolio Marks'!$D:$D,B10) -> 0 | E10: =F9 -> 31500000 | F10: =E10+'Capital Call Schedule'!$F$10 -> 36250000 | G10: =M9 -> 0 | H10: =(E10-G10)*Assumptions!$C$11/4 -> 630000 | I10: =I9+H10 -> 2295000 | J10: =O9 -> 0 | K10: =R9 -> 0 | L10: =MIN(D10,MAX(F10-G10,0)) -> 0 | M10: =G10+L10 -> 0 | N10: =MIN(D10-L10,MAX(I10-J10,0)) -> 0 | O10: =J10+N10 -> 0 | P10: =(Assumptions!$C$13/(1-Assumptions!$C$13))*O10 -> 0 | Q10: =MIN(D10-L10-N10,MAX(P10-K10,0)) -> 0 | R10: =K10+Q10 -> 0 | S10: =D10-L10-N10-Q10 -> 0 | T10: =S10*(1-Assumptions!$C$13) -> 0 | U10: =S10*Assumptions!$C$13 -> 0 | V10: =L10+N10+T10 -> 0 | W10: =Q10+U10 -> 0
B11: 8 | C11: =Quarters!$E$11 -> Q4 2023 | D11: =SUMIFS('Portfolio Marks'!$J:$J,'Portfolio Marks'!$D:$D,B11) -> 0 | E11: =F10 -> 36250000 | F11: =E11+'Capital Call Schedule'!$F$11 -> 40000000 | G11: =M10 -> 0 | H11: =(E11-G11)*Assumptions!$C$11/4 -> 725000 | I11: =I10+H11 -> 3020000 | J11: =O10 -> 0 | K11: =R10 -> 0 | L11: =MIN(D11,MAX(F11-G11,0)) -> 0 | M11: =G11+L11 -> 0 | N11: =MIN(D11-L11,MAX(I11-J11,0)) -> 0 | O11: =J11+N11 -> 0 | P11: =(Assumptions!$C$13/(1-Assumptions!$C$13))*O11 -> 0 | Q11: =MIN(D11-L11-N11,MAX(P11-K11,0)) -> 0 | R11: =K11+Q11 -> 0 | S11: =D11-L11-N11-Q11 -> 0 | T11: =S11*(1-Assumptions!$C$13) -> 0 | U11: =S11*Assumptions!$C$13 -> 0 | V11: =L11+N11+T11 -> 0 | W11: =Q11+U11 -> 0
B12: 9 | C12: =Quarters!$E$12 -> Q1 2024 | D12: =SUMIFS('Portfolio Marks'!$J:$J,'Portfolio Marks'!$D:$D,B12) -> 0 | E12: =F11 -> 40000000 | F12: =E12+'Capital Call Schedule'!$F$12 -> 44250000 | G12: =M11 -> 0 | H12: =(E12-G12)*Assumptions!$C$11/4 -> 800000 | I12: =I11+H12 -> 3820000 | J12: =O11 -> 0 | K12: =R11 -> 0 | L12: =MIN(D12,MAX(F12-G12,0)) -> 0 | M12: =G12+L12 -> 0 | N12: =MIN(D12-L12,MAX(I12-J12,0)) -> 0 | O12: =J12+N12 -> 0 | P12: =(Assumptions!$C$13/(1-Assumptions!$C$13))*O12 -> 0 | Q12: =MIN(D12-L12-N12,MAX(P12-K12,0)) -> 0 | R12: =K12+Q12 -> 0 | S12: =D12-L12-N12-Q12 -> 0 | T12: =S12*(1-Assumptions!$C$13) -> 0 | U12: =S12*Assumptions!$C$13 -> 0 | V12: =L12+N12+T12 -> 0 | W12: =Q12+U12 -> 0
B13: 10 | C13: =Quarters!$E$13 -> Q2 2024 | D13: =SUMIFS('Portfolio Marks'!$J:$J,'Portfolio Marks'!$D:$D,B13) -> 0 | E13: =F12 -> 44250000 | F13: =E13+'Capital Call Schedule'!$F$13 -> 48000000 | G13: =M12 -> 0 | H13: =(E13-G13)*Assumptions!$C$11/4 -> 885000 | I13: =I12+H13 -> 4705000 | J13: =O12 -> 0 | K13: =R12 -> 0 | L13: =MIN(D13,MAX(F13-G13,0)) -> 0 | M13: =G13+L13 -> 0 | N13: =MIN(D13-L13,MAX(I13-J13,0)) -> 0 | O13: =J13+N13 -> 0 | P13: =(Assumptions!$C$13/(1-Assumptions!$C$13))*O13 -> 0 | Q13: =MIN(D13-L13-N13,MAX(P13-K13,0)) -> 0 | R13: =K13+Q13 -> 0 | S13: =D13-L13-N13-Q13 -> 0 | T13: =S13*(1-Assumptions!$C$13) -> 0 | U13: =S13*Assumptions!$C$13 -> 0 | V13: =L13+N13+T13 -> 0 | W13: =Q13+U13 -> 0
B14: 11 | C14: =Quarters!$E$14 -> Q3 2024 | D14: =SUMIFS('Portfolio Marks'!$J:$J,'Portfolio Marks'!$D:$D,B14) -> 0 | E14: =F13 -> 48000000 | F14: =E14+'Capital Call Schedule'!$F$14 -> 48250000 | G14: =M13 -> 0 | H14: =(E14-G14)*Assumptions!$C$11/4 -> 960000 | I14: =I13+H14 -> 5665000 | J14: =O13 -> 0 | K14: =R13 -> 0 | L14: =MIN(D14,MAX(F14-G14,0)) -> 0 | M14: =G14+L14 -> 0 | N14: =MIN(D14-L14,MAX(I14-J14,0)) -> 0 | O14: =J14+N14 -> 0 | P14: =(Assumptions!$C$13/(1-Assumptions!$C$13))*O14 -> 0 | Q14: =MIN(D14-L14-N14,MAX(P14-K14,0)) -> 0 | R14: =K14+Q14 -> 0 | S14: =D14-L14-N14-Q14 -> 0 | T14: =S14*(1-Assumptions!$C$13) -> 0 | U14: =S14*Assumptions!$C$13 -> 0 | V14: =L14+N14+T14 -> 0 | W14: =Q14+U14 -> 0
B15: 12 | C15: =Quarters!$E$15 -> Q4 2024 | D15: =SUMIFS('Portfolio Marks'!$J:$J,'Portfolio Marks'!$D:$D,B15) -> 0 | E15: =F14 -> 48250000 | F15: =E15+'Capital Call Schedule'!$F$15 -> 48500000 | G15: =M14 -> 0 | H15: =(E15-G15)*Assumptions!$C$11/4 -> 965000 | I15: =I14+H15 -> 6630000 | J15: =O14 -> 0 | K15: =R14 -> 0 | L15: =MIN(D15,MAX(F15-G15,0)) -> 0 | M15: =G15+L15 -> 0 | N15: =MIN(D15-L15,MAX(I15-J15,0)) -> 0 | O15: =J15+N15 -> 0 | P15: =(Assumptions!$C$13/(1-Assumptions!$C$13))*O15 -> 0 | Q15: =MIN(D15-L15-N15,MAX(P15-K15,0)) -> 0 | R15: =K15+Q15 -> 0 | S15: =D15-L15-N15-Q15 -> 0 | T15: =S15*(1-Assumptions!$C$13) -> 0 | U15: =S15*Assumptions!$C$13 -> 0 | V15: =L15+N15+T15 -> 0 | W15: =Q15+U15 -> 0
B16: 13 | C16: =Quarters!$E$16 -> Q1 2025 | D16: =SUMIFS('Portfolio Marks'!$J:$J,'Portfolio Marks'!$D:$D,B16) -> 19411887 | E16: =F15 -> 48500000 | F16: =E16+'Capital Call Schedule'!$F$16 -> 48727500 | G16: =M15 -> 0 | H16: =(E16-G16)*Assumptions!$C$11/4 -> 970000 | I16: =I15+H16 -> 7600000 | J16: =O15 -> 0 | K16: =R15 -> 0 | L16: =MIN(D16,MAX(F16-G16,0)) -> 19411887 | M16: =G16+L16 -> 19411887 | N16: =MIN(D16-L16,MAX(I16-J16,0)) -> 0 | O16: =J16+N16 -> 0 | P16: =(Assumptions!$C$13/(1-Assumptions!$C$13))*O16 -> 0 | Q16: =MIN(D16-L16-N16,MAX(P16-K16,0)) -> 0 | R16: =K16+Q16 -> 0 | S16: =D16-L16-N16-Q16 -> 0 | T16: =S16*(1-Assumptions!$C$13) -> 0 | U16: =S16*Assumptions!$C$13 -> 0 | V16: =L16+N16+T16 -> 19411887 | W16: =Q16+U16 -> 0
B17: 14 | C17: =Quarters!$E$17 -> Q2 2025 | D17: =SUMIFS('Portfolio Marks'!$J:$J,'Portfolio Marks'!$D:$D,B17) -> 0 | E17: =F16 -> 48727500 | F17: =E17+'Capital Call Schedule'!$F$17 -> 48955000 | G17: =M16 -> 19411887 | H17: =(E17-G17)*Assumptions!$C$11/4 -> 586312.26 | I17: =I16+H17 -> 8186312.3 | J17: =O16 -> 0 | K17: =R16 -> 0 | L17: =MIN(D17,MAX(F17-G17,0)) -> 0 | M17: =G17+L17 -> 19411887 | N17: =MIN(D17-L17,MAX(I17-J17,0)) -> 0 | O17: =J17+N17 -> 0 | P17: =(Assumptions!$C$13/(1-Assumptions!$C$13))*O17 -> 0 | Q17: =MIN(D17-L17-N17,MAX(P17-K17,0)) -> 0 | R17: =K17+Q17 -> 0 | S17: =D17-L17-N17-Q17 -> 0 | T17: =S17*(1-Assumptions!$C$13) -> 0 | U17: =S17*Assumptions!$C$13 -> 0 | V17: =L17+N17+T17 -> 0 | W17: =Q17+U17 -> 0
B18: 15 | C18: =Quarters!$E$18 -> Q3 2025 | D18: =SUMIFS('Portfolio Marks'!$J:$J,'Portfolio Marks'!$D:$D,B18) -> 10993566 | E18: =F17 -> 48955000 | F18: =E18+'Capital Call Schedule'!$F$18 -> 49152500 | G18: =M17 -> 19411887 | H18: =(E18-G18)*Assumptions!$C$11/4 -> 590862.26 | I18: =I17+H18 -> 8777174.5 | J18: =O17 -> 0 | K18: =R17 -> 0 | L18: =MIN(D18,MAX(F18-G18,0)) -> 10993566 | M18: =G18+L18 -> 30405453 | N18: =MIN(D18-L18,MAX(I18-J18,0)) -> 0 | O18: =J18+N18 -> 0 | P18: =(Assumptions!$C$13/(1-Assumptions!$C$13))*O18 -> 0 | Q18: =MIN(D18-L18-N18,MAX(P18-K18,0)) -> 0 | R18: =K18+Q18 -> 0 | S18: =D18-L18-N18-Q18 -> 0 | T18: =S18*(1-Assumptions!$C$13) -> 0 | U18: =S18*Assumptions!$C$13 -> 0 | V18: =L18+N18+T18 -> 10993566 | W18: =Q18+U18 -> 0
B19: 16 | C19: =Quarters!$E$19 -> Q4 2025 | D19: =SUMIFS('Portfolio Marks'!$J:$J,'Portfolio Marks'!$D:$D,B19) -> 0 | E19: =F18 -> 49152500 | F19: =E19+'Capital Call Schedule'!$F$19 -> 49350000 | G19: =M18 -> 30405453 | H19: =(E19-G19)*Assumptions!$C$11/4 -> 374940.95 | I19: =I18+H19 -> 9152115.5 | J19: =O18 -> 0 | K19: =R18 -> 0 | L19: =MIN(D19,MAX(F19-G19,0)) -> 0 | M19: =G19+L19 -> 30405453 | N19: =MIN(D19-L19,MAX(I19-J19,0)) -> 0 | O19: =J19+N19 -> 0 | P19: =(Assumptions!$C$13/(1-Assumptions!$C$13))*O19 -> 0 | Q19: =MIN(D19-L19-N19,MAX(P19-K19,0)) -> 0 | R19: =K19+Q19 -> 0 | S19: =D19-L19-N19-Q19 -> 0 | T19: =S19*(1-Assumptions!$C$13) -> 0 | U19: =S19*Assumptions!$C$13 -> 0 | V19: =L19+N19+T19 -> 0 | W19: =Q19+U19 -> 0
B20: 17 | C20: =Quarters!$E$20 -> Q1 2026 | D20: =SUMIFS('Portfolio Marks'!$J:$J,'Portfolio Marks'!$D:$D,B20) -> 14803879 | E20: =F19 -> 49350000 | F20: =E20+'Capital Call Schedule'!$F$20 -> 49520000 | G20: =M19 -> 30405453 | H20: =(E20-G20)*Assumptions!$C$11/4 -> 378890.95 | I20: =I19+H20 -> 9531006.4 | J20: =O19 -> 0 | K20: =R19 -> 0 | L20: =MIN(D20,MAX(F20-G20,0)) -> 14803879 | M20: =G20+L20 -> 45209331 | N20: =MIN(D20-L20,MAX(I20-J20,0)) -> 0 | O20: =J20+N20 -> 0 | P20: =(Assumptions!$C$13/(1-Assumptions!$C$13))*O20 -> 0 | Q20: =MIN(D20-L20-N20,MAX(P20-K20,0)) -> 0 | R20: =K20+Q20 -> 0 | S20: =D20-L20-N20-Q20 -> 0 | T20: =S20*(1-Assumptions!$C$13) -> 0 | U20: =S20*Assumptions!$C$13 -> 0 | V20: =L20+N20+T20 -> 14803879 | W20: =Q20+U20 -> 0
B21: 18 | C21: =Quarters!$E$21 -> Q2 2026 | D21: =SUMIFS('Portfolio Marks'!$J:$J,'Portfolio Marks'!$D:$D,B21) -> 19995229 | E21: =F20 -> 49520000 | F21: =E21+'Capital Call Schedule'!$F$21 -> 49690000 | G21: =M20 -> 45209331 | H21: =(E21-G21)*Assumptions!$C$11/4 -> 86213.375 | I21: =I20+H21 -> 9617219.8 | J21: =O20 -> 0 | K21: =R20 -> 0 | L21: =MIN(D21,MAX(F21-G21,0)) -> 4480668.7 | M21: =G21+L21 -> 49690000 | N21: =MIN(D21-L21,MAX(I21-J21,0)) -> 9617219.8 | O21: =J21+N21 -> 9617219.8 | P21: =(Assumptions!$C$13/(1-Assumptions!$C$13))*O21 -> 2404304.9 | Q21: =MIN(D21-L21-N21,MAX(P21-K21,0)) -> 2404304.9 | R21: =K21+Q21 -> 2404304.9 | S21: =D21-L21-N21-Q21 -> 3493035.7 | T21: =S21*(1-Assumptions!$C$13) -> 2794428.6 | U21: =S21*Assumptions!$C$13 -> 698607.14 | V21: =L21+N21+T21 -> 16892317 | W21: =Q21+U21 -> 3102912.1
C22: Cumulative | V22: =SUM(V4:V21) -> 62101648 | W22: =SUM(W4:W21) -> 3102912.1

Sheet NAV Rollforward
A1: Quarterly NAV Rollforward
A2: Beginning NAV -> Ending NAV bridge, tying to portfolio fair values each quarter
B3: Qtr # | C3: Quarter | D3: Beginning NAV | E3: Contributions | F3: Management Fees | G3: Realized Gain/(Loss) | H3: Unrealized Gain/(Loss) | I3: Distributions | J3: Ending NAV | K3: Ties?
B4: 1 | C4: =Quarters!$E$4 -> Q1 2022 | D4: 0 | E4: ='Capital Call Schedule'!$F$4 -> 6250000 | F4: =-'Mgmt Fee Schedule'!$G$4 -> -250000 | G4: =SUMIFS('Portfolio Marks'!$L:$L,'Portfolio Marks'!$D:$D,B4) -> 0 | H4: =(SUMIFS('Portfolio Marks'!$G:$G,'Portfolio Marks'!$D:$D,B4)-SUMIFS('Portfolio Marks'!$J:$J,'Portfolio Marks'!$D:$D,B4))-D4-E4+'Mgmt Fee Schedule'!$G$4-G4+'Distribution Waterfall'!$D$4 -> 0 | I4: =-'Distribution Waterfall'!$D$4 -> 0 | J4: =D4+E4+F4+G4+H4+I4 -> 6000000 | K4: =IF(ROUND(J4-(SUMIFS('Portfolio Marks'!$G:$G,'Portfolio Marks'!$D:$D,B4)-SUMIFS('Portfolio Marks'!$J:$J,'Portfolio Marks'!$D:$D,B4)),2)=0,"OK","ERROR") -> OK
B5: 2 | C5: =Quarters!$E$5 -> Q2 2022 | D5: =J4 -> 6000000 | E5: ='Capital Call Schedule'!$F$5 -> 5750000 | F5: =-'Mgmt Fee Schedule'!$G$5 -> -250000 | G5: =SUMIFS('Portfolio Marks'!$L:$L,'Portfolio Marks'!$D:$D,B5) -> 0 | H5: =(SUMIFS('Portfolio Marks'!$G:$G,'Portfolio Marks'!$D:$D,B5)-SUMIFS('Portfolio Marks'!$J:$J,'Portfolio Marks'!$D:$D,B5))-D5-E5+'Mgmt Fee Schedule'!$G$5-G5+'Distribution Waterfall'!$D$5 -> 657424.54 | I5: =-'Distribution Waterfall'!$D$5 -> 0 | J5: =D5+E5+F5+G5+H5+I5 -> 12157425 | K5: =IF(ROUND(J5-(SUMIFS('Portfolio Marks'!$G:$G,'Portfolio Marks'!$D:$D,B5)-SUMIFS('Portfolio Marks'!$J:$J,'Portfolio Marks'!$D:$D,B5)),2)=0,"OK","ERROR") -> OK
B6: 3 | C6: =Quarters!$E$6 -> Q3 2022 | D6: =J5 -> 12157425 | E6: ='Capital Call Schedule'!$F$6 -> 4750000 | F6: =-'Mgmt Fee Schedule'!$G$6 -> -250000 | G6: =SUMIFS('Portfolio Marks'!$L:$L,'Portfolio Marks'!$D:$D,B6) -> 0 | H6: =(SUMIFS('Portfolio Marks'!$G:$G,'Portfolio Marks'!$D:$D,B6)-SUMIFS('Portfolio Marks'!$J:$J,'Portfolio Marks'!$D:$D,B6))-D6-E6+'Mgmt Fee Schedule'!$G$6-G6+'Distribution Waterfall'!$D$6 -> 896533.37 | I6: =-'Distribution Waterfall'!$D$6 -> 0 | J6: =D6+E6+F6+G6+H6+I6 -> 17553958 | K6: =IF(ROUND(J6-(SUMIFS('Portfolio Marks'!$G:$G,'Portfolio Marks'!$D:$D,B6)-SUMIFS('Portfolio Marks'!$J:$J,'Portfolio Marks'!$D:$D,B6)),2)=0,"OK","ERROR") -> OK
B7: 4 | C7: =Quarters!$E$7 -> Q4 2022 | D7: =J6 -> 17553958 | E7: ='Capital Call Schedule'!$F$7 -> 5250000 | F7: =-'Mgmt Fee Schedule'!$G$7 -> -250000 | G7: =SUMIFS('Portfolio Marks'!$L:$L,'Portfolio Marks'!$D:$D,B7) -> 0 | H7: =(SUMIFS('Portfolio Marks'!$G:$G,'Portfolio Marks'!$D:$D,B7)-SUMIFS('Portfolio Marks'!$J:$J,'Portfolio Marks'!$D:$D,B7))-D7-E7+'Mgmt Fee Schedule'!$G$7-G7+'Distribution Waterfall'!$D$7 -> 1008642.5 | I7: =-'Distribution Waterfall'!$D$7 -> 0 | J7: =D7+E7+F7+G7+H7+I7 -> 23562600 | K7: =IF(ROUND(J7-(SUMIFS('Portfolio Marks'!$G:$G,'Portfolio Marks'!$D:$D,B7)-SUMIFS('Portfolio Marks'!$J:$J,'Portfolio Marks'!$D:$D,B7)),2)=0,"OK","ERROR") -> OK
B8: 5 | C8: =Quarters!$E$8 -> Q1 2023 | D8: =J7 -> 23562600 | E8: ='Capital Call Schedule'!$F$8 -> 4250000 | F8: =-'Mgmt Fee Schedule'!$G$8 -> -250000 | G8: =SUMIFS('Portfolio Marks'!$L:$L,'Portfolio Marks'!$D:$D,B8) -> 0 | H8: =(SUMIFS('Portfolio Marks'!$G:$G,'Portfolio Marks'!$D:$D,B8)-SUMIFS('Portfolio Marks'!$J:$J,'Portfolio Marks'!$D:$D,B8))-D8-E8+'Mgmt Fee Schedule'!$G$8-G8+'Distribution Waterfall'!$D$8 -> 1485986.9 | I8: =-'Distribution Waterfall'!$D$8 -> 0 | J8: =D8+E8+F8+G8+H8+I8 -> 29048587 | K8: =IF(ROUND(J8-(SUMIFS('Portfolio Marks'!$G:$G,'Portfolio Marks'!$D:$D,B8)-SUMIFS('Portfolio Marks'!$J:$J,'Portfolio Marks'!$D:$D,B8)),2)=0,"OK","ERROR") -> OK
B9: 6 | C9: =Quarters!$E$9 -> Q2 2023 | D9: =J8 -> 29048587 | E9: ='Capital Call Schedule'!$F$9 -> 5250000 | F9: =-'Mgmt Fee Schedule'!$G$9 -> -250000 | G9: =SUMIFS('Portfolio Marks'!$L:$L,'Portfolio Marks'!$D:$D,B9) -> 0 | H9: =(SUMIFS('Portfolio Marks'!$G:$G,'Portfolio Marks'!$D:$D,B9)-SUMIFS('Portfolio Marks'!$J:$J,'Portfolio Marks'!$D:$D,B9))-D9-E9+'Mgmt Fee Schedule'!$G$9-G9+'Distribution Waterfall'!$D$9 -> 1163810.5 | I9: =-'Distribution Waterfall'!$D$9 -> 0 | J9: =D9+E9+F9+G9+H9+I9 -> 35212398 | K9: =IF(ROUND(J9-(SUMIFS('Portfolio Marks'!$G:$G,'Portfolio Marks'!$D:$D,B9)-SUMIFS('Portfolio Marks'!$J:$J,'Portfolio Marks'!$D:$D,B9)),2)=0,"OK","ERROR") -> OK
B10: 7 | C10: =Quarters!$E$10 -> Q3 2023 | D10: =J9 -> 35212398 | E10: ='Capital Call Schedule'!$F$10 -> 4750000 | F10: =-'Mgmt Fee Schedule'!$G$10 -> -250000 | G10: =SUMIFS('Portfolio Marks'!$L:$L,'Portfolio Marks'!$D:$D,B10) -> 0 | H10: =(SUMIFS('Portfolio Marks'!$G:$G,'Portfolio Marks'!$D:$D,B10)-SUMIFS('Portfolio Marks'!$J:$J,'Portfolio Marks'!$D:$D,B10))-D10-E10+'Mgmt Fee Schedule'!$G$10-G10+'Distribution Waterfall'!$D$10 -> 2059134.7 | I10: =-'Distribution Waterfall'!$D$10 -> 0 | J10: =D10+E10+F10+G10+H10+I10 -> 41771532 | K10: =IF(ROUND(J10-(SUMIFS('Portfolio Marks'!$G:$G,'Portfolio Marks'!$D:$D,B10)-SUMIFS('Portfolio Marks'!$J:$J,'Portfolio Marks'!$D:$D,B10)),2)=0,"OK","ERROR") -> OK
B11: 8 | C11: =Quarters!$E$11 -> Q4 2023 | D11: =J10 -> 41771532 | E11: ='Capital Call Schedule'!$F$11 -> 3750000 | F11: =-'Mgmt Fee Schedule'!$G$11 -> -250000 | G11: =SUMIFS('Portfolio Marks'!$L:$L,'Portfolio Marks'!$D:$D,B11) -> 0 | H11: =(SUMIFS('Portfolio Marks'!$G:$G,'Portfolio Marks'!$D:$D,B11)-SUMIFS('Portfolio Marks'!$J:$J,'Portfolio Marks'!$D:$D,B11))-D11-E11+'Mgmt Fee Schedule'!$G$11-G11+'Distribution Waterfall'!$D$11 -> 2512421.3 | I11: =-'Distribution Waterfall'!$D$11 -> 0 | J11: =D11+E11+F11+G11+H11+I11 -> 47783954 | K11: =IF(ROUND(J11-(SUMIFS('Portfolio Marks'!$G:$G,'Portfolio Marks'!$D:$D,B11)-SUMIFS('Portfolio Marks'!$J:$J,'Portfolio Marks'!$D:$D,B11)),2)=0,"OK","ERROR") -> OK
B12: 9 | C12: =Quarters!$E$12 -> Q1 2024 | D12: =J11 -> 47783954 | E12: ='Capital Call Schedule'!$F$12 -> 4250000 | F12: =-'Mgmt Fee Schedule'!$G$12 -> -250000 | G12: =SUMIFS('Portfolio Marks'!$L:$L,'Portfolio Marks'!$D:$D,B12) -> 0 | H12: =(SUMIFS('Portfolio Marks'!$G:$G,'Portfolio Marks'!$D:$D,B12)-SUMIFS('Portfolio Marks'!$J:$J,'Portfolio Marks'!$D:$D,B12))-D12-E12+'Mgmt Fee Schedule'!$G$12-G12+'Distribution Waterfall'!$D$12 -> 2864578.8 | I12: =-'Distribution Waterfall'!$D$12 -> 0 | J12: =D12+E12+F12+G12+H12+I12 -> 54648533 | K12: =IF(ROUND(J12-(SUMIFS('Portfolio Marks'!$G:$G,'Portfolio Marks'!$D:$D,B12)-SUMIFS('Portfolio Marks'!$J:$J,'Portfolio Marks'!$D:$D,B12)),2)=0,"OK","ERROR") -> OK
B13: 10 | C13: =Quarters!$E$13 -> Q2 2024 | D13: =J12 -> 54648533 | E13: ='Capital Call Schedule'!$F$13 -> 3750000 | F13: =-'Mgmt Fee Schedule'!$G$13 -> -250000 | G13: =SUMIFS('Portfolio Marks'!$L:$L,'Portfolio Marks'!$D:$D,B13) -> 0 | H13: =(SUMIFS('Portfolio Marks'!$G:$G,'Portfolio Marks'!$D:$D,B13)-SUMIFS('Portfolio Marks'!$J:$J,'Portfolio Marks'!$D:$D,B13))-D13-E13+'Mgmt Fee Schedule'!$G$13-G13+'Distribution Waterfall'!$D$13 -> 3303626.8 | I13: =-'Distribution Waterfall'!$D$13 -> 0 | J13: =D13+E13+F13+G13+H13+I13 -> 61452159 | K13: =IF(ROUND(J13-(SUMIFS('Portfolio Marks'!$G:$G,'Portfolio Marks'!$D:$D,B13)-SUMIFS('Portfolio Marks'!$J:$J,'Portfolio Marks'!$D:$D,B13)),2)=0,"OK","ERROR") -> OK
B14: 11 | C14: =Quarters!$E$14 -> Q3 2024 | D14: =J13 -> 61452159 | E14: ='Capital Call Schedule'!$F$14 -> 250000 | F14: =-'Mgmt Fee Schedule'!$G$14 -> -250000 | G14: =SUMIFS('Portfolio Marks'!$L:$L,'Portfolio Marks'!$D:$D,B14) -> 0 | H14: =(SUMIFS('Portfolio Marks'!$G:$G,'Portfolio Marks'!$D:$D,B14)-SUMIFS('Portfolio Marks'!$J:$J,'Portfolio Marks'!$D:$D,B14))-D14-E14+'Mgmt Fee Schedule'!$G$14-G14+'Distribution Waterfall'!$D$14 -> 3663717 | I14: =-'Distribution Waterfall'!$D$14 -> 0 | J14: =D14+E14+F14+G14+H14+I14 -> 65115876 | K14: =IF(ROUND(J14-(SUMIFS('Portfolio Marks'!$G:$G,'Portfolio Marks'!$D:$D,B14)-SUMIFS('Portfolio Marks'!$J:$J,'Portfolio Marks'!$D:$D,B14)),2)=0,"OK","ERROR") -> OK
B15: 12 | C15: =Quarters!$E$15 -> Q4 2024 | D15: =J14 -> 65115876 | E15: ='Capital Call Schedule'!$F$15 -> 250000 | F15: =-'Mgmt Fee Schedule'!$G$15 -> -250000 | G15: =SUMIFS('Portfolio Marks'!$L:$L,'Portfolio Marks'!$D:$D,B15) -> 0 | H15: =(SUMIFS('Portfolio Marks'!$G:$G,'Portfolio Marks'!$D:$D,B15)-SUMIFS('Portfolio Marks'!$J:$J,'Portfolio Marks'!$D:$D,B15))-D15-E15+'Mgmt Fee Schedule'!$G$15-G15+'Distribution Waterfall'!$D$15 -> 4363782.8 | I15: =-'Distribution Waterfall'!$D$15 -> 0 | J15: =D15+E15+F15+G15+H15+I15 -> 69479659 | K15: =IF(ROUND(J15-(SUMIFS('Portfolio Marks'!$G:$G,'Portfolio Marks'!$D:$D,B15)-SUMIFS('Portfolio Marks'!$J:$J,'Portfolio Marks'!$D:$D,B15)),2)=0,"OK","ERROR") -> OK
B16: 13 | C16: =Quarters!$E$16 -> Q1 2025 | D16: =J15 -> 69479659 | E16: ='Capital Call Schedule'!$F$16 -> 227500 | F16: =-'Mgmt Fee Schedule'!$G$16 -> -227500 | G16: =SUMIFS('Portfolio Marks'!$L:$L,'Portfolio Marks'!$D:$D,B16) -> 13411887 | H16: =(SUMIFS('Portfolio Marks'!$G:$G,'Portfolio Marks'!$D:$D,B16)-SUMIFS('Portfolio Marks'!$J:$J,'Portfolio Marks'!$D:$D,B16))-D16-E16+'Mgmt Fee Schedule'!$G$16-G16+'Distribution Waterfall'!$D$16 -> -8476207.7 | I16: =-'Distribution Waterfall'!$D$16 -> -19411887 | J16: =D16+E16+F16+G16+H16+I16 -> 55003452 | K16: =IF(ROUND(J16-(SUMIFS('Portfolio Marks'!$G:$G,'Portfolio Marks'!$D:$D,B16)-SUMIFS('Portfolio Marks'!$J:$J,'Portfolio Marks'!$D:$D,B16)),2)=0,"OK","ERROR") -> OK
B17: 14 | C17: =Quarters!$E$17 -> Q2 2025 | D17: =J16 -> 55003452 | E17: ='Capital Call Schedule'!$F$17 -> 227500 | F17: =-'Mgmt Fee Schedule'!$G$17 -> -227500 | G17: =SUMIFS('Portfolio Marks'!$L:$L,'Portfolio Marks'!$D:$D,B17) -> 0 | H17: =(SUMIFS('Portfolio Marks'!$G:$G,'Portfolio Marks'!$D:$D,B17)-SUMIFS('Portfolio Marks'!$J:$J,'Portfolio Marks'!$D:$D,B17))-D17-E17+'Mgmt Fee Schedule'!$G$17-G17+'Distribution Waterfall'!$D$17 -> 2950760.3 | I17: =-'Distribution Waterfall'!$D$17 -> 0 | J17: =D17+E17+F17+G17+H17+I17 -> 57954212 | K17: =IF(ROUND(J17-(SUMIFS('Portfolio Marks'!$G:$G,'Portfolio Marks'!$D:$D,B17)-SUMIFS('Portfolio Marks'!$J:$J,'Portfolio Marks'!$D:$D,B17)),2)=0,"OK","ERROR") -> OK
B18: 15 | C18: =Quarters!$E$18 -> Q3 2025 | D18: =J17 -> 57954212 | E18: ='Capital Call Schedule'!$F$18 -> 197500 | F18: =-'Mgmt Fee Schedule'!$G$18 -> -197500 | G18: =SUMIFS('Portfolio Marks'!$L:$L,'Portfolio Marks'!$D:$D,B18) -> 5493565.5 | H18: =(SUMIFS('Portfolio Marks'!$G:$G,'Portfolio Marks'!$D:$D,B18)-SUMIFS('Portfolio Marks'!$J:$J,'Portfolio Marks'!$D:$D,B18))-D18-E18+'Mgmt Fee Schedule'!$G$18-G18+'Distribution Waterfall'!$D$18 -> -2629954.2 | I18: =-'Distribution Waterfall'!$D$18 -> -10993566 | J18: =D18+E18+F18+G18+H18+I18 -> 49824258 | K18: =IF(ROUND(J18-(SUMIFS('Portfolio Marks'!$G:$G,'Portfolio Marks'!$D:$D,B18)-SUMIFS('Portfolio Marks'!$J:$J,'Portfolio Marks'!$D:$D,B18)),2)=0,"OK","ERROR") -> OK
B19: 16 | C19: =Quarters!$E$19 -> Q4 2025 | D19: =J18 -> 49824258 | E19: ='Capital Call Schedule'!$F$19 -> 197500 | F19: =-'Mgmt Fee Schedule'!$G$19 -> -197500 | G19: =SUMIFS('Portfolio Marks'!$L:$L,'Portfolio Marks'!$D:$D,B19) -> 0 | H19: =(SUMIFS('Portfolio Marks'!$G:$G,'Portfolio Marks'!$D:$D,B19)-SUMIFS('Portfolio Marks'!$J:$J,'Portfolio Marks'!$D:$D,B19))-D19-E19+'Mgmt Fee Schedule'!$G$19-G19+'Distribution Waterfall'!$D$19 -> 2378162.4 | I19: =-'Distribution Waterfall'!$D$19 -> 0 | J19: =D19+E19+F19+G19+H19+I19 -> 52202420 | K19: =IF(ROUND(J19-(SUMIFS('Portfolio Marks'!$G:$G,'Portfolio Marks'!$D:$D,B19)-SUMIFS('Portfolio Marks'!$J:$J,'Portfolio Marks'!$D:$D,B19)),2)=0,"OK","ERROR") -> OK
B20: 17 | C20: =Quarters!$E$20 -> Q1 2026 | D20: =J19 -> 52202420 | E20: ='Capital Call Schedule'!$F$20 -> 170000 | F20: =-'Mgmt Fee Schedule'!$G$20 -> -170000 | G20: =SUMIFS('Portfolio Marks'!$L:$L,'Portfolio Marks'!$D:$D,B20) -> 9803878.7 | H20: =(SUMIFS('Portfolio Marks'!$G:$G,'Portfolio Marks'!$D:$D,B20)-SUMIFS('Portfolio Marks'!$J:$J,'Portfolio Marks'!$D:$D,B20))-D20-E20+'Mgmt Fee Schedule'!$G$20-G20+'Distribution Waterfall'!$D$20 -> -7010181.8 | I20: =-'Distribution Waterfall'!$D$20 -> -14803879 | J20: =D20+E20+F20+G20+H20+I20 -> 40192238 | K20: =IF(ROUND(J20-(SUMIFS('Portfolio Marks'!$G:$G,'Portfolio Marks'!$D:$D,B20)-SUMIFS('Portfolio Marks'!$J:$J,'Portfolio Marks'!$D:$D,B20)),2)=0,"OK","ERROR") -> OK
B21: 18 | C21: =Quarters!$E$21 -> Q2 2026 | D21: =J20 -> 40192238 | E21: ='Capital Call Schedule'!$F$21 -> 170000 | F21: =-'Mgmt Fee Schedule'!$G$21 -> -170000 | G21: =SUMIFS('Portfolio Marks'!$L:$L,'Portfolio Marks'!$D:$D,B21) -> 8495229.2 | H21: =(SUMIFS('Portfolio Marks'!$G:$G,'Portfolio Marks'!$D:$D,B21)-SUMIFS('Portfolio Marks'!$J:$J,'Portfolio Marks'!$D:$D,B21))-D21-E21+'Mgmt Fee Schedule'!$G$21-G21+'Distribution Waterfall'!$D$21 -> -6991460.6 | I21: =-'Distribution Waterfall'!$D$21 -> -19995229 | J21: =D21+E21+F21+G21+H21+I21 -> 21700778 | K21: =IF(ROUND(J21-(SUMIFS('Portfolio Marks'!$G:$G,'Portfolio Marks'!$D:$D,B21)-SUMIFS('Portfolio Marks'!$J:$J,'Portfolio Marks'!$D:$D,B21)),2)=0,"OK","ERROR") -> OK

Sheet LP Capital Calls
A1: LP Capital Calls
A2: Each LP's pro-rata share of every quarterly capital call
B3: Qtr # | C3: Quarter | D3: LP ID | E3: LP Name | F3: Investment Call ($) | G3: Mgmt Fee Call ($) | H3: Total Call ($)
B4: 1 | C4: =Quarters!$E$4 -> Q1 2022 | D4: LP-01 | E4: Northbridge State Pension Fund | F4: ='Capital Call Schedule'!$D$4*'LP Register'!$F$4 -> 960000 | G4: ='Capital Call Schedule'!$E$4*'LP Register'!$F$4 -> 40000 | H4: =F4+G4 -> 1000000
B5: 1 | C5: =Quarters!$E$4 -> Q1 2022 | D5: LP-02 | E5: Meridian University Endowment | F5: ='Capital Call Schedule'!$D$4*'LP Register'!$F$5 -> 720000 | G5: ='Capital Call Schedule'!$E$4*'LP Register'!$F$5 -> 30000 | H5: =F5+G5 -> 750000
B6: 1 | C6: =Quarters!$E$4 -> Q1 2022 | D6: LP-03 | E6: Harborview Insurance Co. | F6: ='Capital Call Schedule'!$D$4*'LP Register'!$F$6 -> 660000 | G6: ='Capital Call Schedule'!$E$4*'LP Register'!$F$6 -> 27500 | H6: =F6+G6 -> 687500
B7: 1 | C7: =Quarters!$E$4 -> Q1 2022 | D7: LP-04 | E7: Cascade Partners Fund of Funds | F7: ='Capital Call Schedule'!$D$4*'LP Register'!$F$7 -> 600000 | G7: ='Capital Call Schedule'!$E$4*'LP Register'!$F$7 -> 25000 | H7: =F7+G7 -> 625000
B8: 1 | C8: =Quarters!$E$4 -> Q1 2022 | D8: LP-05 | E8: Elmwood Family Office | F8: ='Capital Call Schedule'!$D$4*'LP Register'!$F$8 -> 480000 | G8: ='Capital Call Schedule'!$E$4*'LP Register'!$F$8 -> 20000 | H8: =F8+G8 -> 500000
B9: 1 | C9: =Quarters!$E$4 -> Q1 2022 | D9: LP-06 | E9: Tanager Sovereign Partners | F9: ='Capital Call Schedule'!$D$4*'LP Register'!$F$9 -> 480000 | G9: ='Capital Call Schedule'!$E$4*'LP Register'!$F$9 -> 20000 | H9: =F9+G9 -> 500000
B10: 1 | C10: =Quarters!$E$4 -> Q1 2022 | D10: LP-07 | E10: Birchwood College Endowment | F10: ='Capital Call Schedule'!$D$4*'LP Register'!$F$10 -> 360000 | G10: ='Capital Call Schedule'!$E$4*'LP Register'!$F$10 -> 15000 | H10: =F10+G10 -> 375000
B11: 1 | C11: =Quarters!$E$4 -> Q1 2022 | D11: LP-08 | E11: Kestrel Insurance Group | F11: ='Capital Call Schedule'!$D$4*'LP Register'!$F$11 -> 300000 | G11: ='Capital Call Schedule'!$E$4*'LP Register'!$F$11 -> 12500 | H11: =F11+G11 -> 312500
B12: 1 | C12: =Quarters!$E$4 -> Q1 2022 | D12: LP-09 | E12: Wrenfield Family Office | F12: ='Capital Call Schedule'!$D$4*'LP Register'!$F$12 -> 240000 | G12: ='Capital Call Schedule'!$E$4*'LP Register'!$F$12 -> 10000 | H12: =F12+G12 -> 250000
B13: 1 | C13: =Quarters!$E$4 -> Q1 2022 | D13: LP-10 | E13: Alder Street Foundation | F13: ='Capital Call Schedule'!$D$4*'LP Register'!$F$13 -> 240000 | G13: ='Capital Call Schedule'!$E$4*'LP Register'!$F$13 -> 10000 | H13: =F13+G13 -> 250000
B14: 1 | C14: =Quarters!$E$4 -> Q1 2022 | D14: LP-11 | E14: Pinecrest Pension Trust | F14: ='Capital Call Schedule'!$D$4*'LP Register'!$F$14 -> 216000 | G14: ='Capital Call Schedule'!$E$4*'LP Register'!$F$14 -> 9000 | H14: =F14+G14 -> 225000
B15: 1 | C15: =Quarters!$E$4 -> Q1 2022 | D15: LP-12 | E15: Ivywood Capital Partners (FoF) | F15: ='Capital Call Schedule'!$D$4*'LP Register'!$F$15 -> 180000 | G15: ='Capital Call Schedule'!$E$4*'LP Register'!$F$15 -> 7500 | H15: =F15+G15 -> 187500
B16: 1 | C16: =Quarters!$E$4 -> Q1 2022 | D16: LP-13 | E16: Grayling Family Office | F16: ='Capital Call Schedule'!$D$4*'LP Register'!$F$16 -> 180000 | G16: ='Capital Call Schedule'!$E$4*'LP Register'!$F$16 -> 7500 | H16: =F16+G16 -> 187500
B17: 1 | C17: =Quarters!$E$4 -> Q1 2022 | D17: LP-14 | E17: Redstone Family Office | F17: ='Capital Call Schedule'!$D$4*'LP Register'!$F$17 -> 192000 | G17: ='Capital Call Schedule'!$E$4*'LP Register'!$F$17 -> 8000 | H17: =F17+G17 -> 200000
B18: 1 | C18: =Quarters!$E$4 -> Q1 2022 | D18: LP-15 | E18: Sable Foundation | F18: ='Capital Call Schedule'!$D$4*'LP Register'!$F$18 -> 192000 | G18: ='Capital Call Schedule'!$E$4*'LP Register'!$F$18 -> 8000 | H18: =F18+G18 -> 200000
B19: 2 | C19: =Quarters!$E$5 -> Q2 2022 | D19: LP-01 | E19: Northbridge State Pension Fund | F19: ='Capital Call Schedule'!$D$5*'LP Register'!$F$4 -> 880000 | G19: ='Capital Call Schedule'!$E$5*'LP Register'!$F$4 -> 40000 | H19: =F19+G19 -> 920000
B20: 2 | C20: =Quarters!$E$5 -> Q2 2022 | D20: LP-02 | E20: Meridian University Endowment | F20: ='Capital Call Schedule'!$D$5*'LP Register'!$F$5 -> 660000 | G20: ='Capital Call Schedule'!$E$5*'LP Register'!$F$5 -> 30000 | H20: =F20+G20 -> 690000
B21: 2 | C21: =Quarters!$E$5 -> Q2 2022 | D21: LP-03 | E21: Harborview Insurance Co. | F21: ='Capital Call Schedule'!$D$5*'LP Register'!$F$6 -> 605000 | G21: ='Capital Call Schedule'!$E$5*'LP Register'!$F$6 -> 27500 | H21: =F21+G21 -> 632500
B22: 2 | C22: =Quarters!$E$5 -> Q2 2022 | D22: LP-04 | E22: Cascade Partners Fund of Funds | F22: ='Capital Call Schedule'!$D$5*'LP Register'!$F$7 -> 550000 | G22: ='Capital Call Schedule'!$E$5*'LP Register'!$F$7 -> 25000 | H22: =F22+G22 -> 575000
B23: 2 | C23: =Quarters!$E$5 -> Q2 2022 | D23: LP-05 | E23: Elmwood Family Office | F23: ='Capital Call Schedule'!$D$5*'LP Register'!$F$8 -> 440000 | G23: ='Capital Call Schedule'!$E$5*'LP Register'!$F$8 -> 20000 | H23: =F23+G23 -> 460000
B24: 2 | C24: =Quarters!$E$5 -> Q2 2022 | D24: LP-06 | E24: Tanager Sovereign Partners | F24: ='Capital Call Schedule'!$D$5*'LP Register'!$F$9 -> 440000 | G24: ='Capital Call Schedule'!$E$5*'LP Register'!$F$9 -> 20000 | H24: =F24+G24 -> 460000
B25: 2 | C25: =Quarters!$E$5 -> Q2 2022 | D25: LP-07 | E25: Birchwood College Endowment | F25: ='Capital Call Schedule'!$D$5*'LP Register'!$F$10 -> 330000 | G25: ='Capital Call Schedule'!$E$5*'LP Register'!$F$10 -> 15000 | H25: =F25+G25 -> 345000
B26: 2 | C26: =Quarters!$E$5 -> Q2 2022 | D26: LP-08 | E26: Kestrel Insurance Group | F26: ='Capital Call Schedule'!$D$5*'LP Register'!$F$11 -> 275000 | G26: ='Capital Call Schedule'!$E$5*'LP Register'!$F$11 -> 12500 | H26: =F26+G26 -> 287500
B27: 2 | C27: =Quarters!$E$5 -> Q2 2022 | D27: LP-09 | E27: Wrenfield Family Office | F27: ='Capital Call Schedule'!$D$5*'LP Register'!$F$12 -> 220000 | G27: ='Capital Call Schedule'!$E$5*'LP Register'!$F$12 -> 10000 | H27: =F27+G27 -> 230000
B28: 2 | C28: =Quarters!$E$5 -> Q2 2022 | D28: LP-10 | E28: Alder Street Foundation | F28: ='Capital Call Schedule'!$D$5*'LP Register'!$F$13 -> 220000 | G28: ='Capital Call Schedule'!$E$5*'LP Register'!$F$13 -> 10000 | H28: =F28+G28 -> 230000
B29: 2 | C29: =Quarters!$E$5 -> Q2 2022 | D29: LP-11 | E29: Pinecrest Pension Trust | F29: ='Capital Call Schedule'!$D$5*'LP Register'!$F$14 -> 198000 | G29: ='Capital Call Schedule'!$E$5*'LP Register'!$F$14 -> 9000 | H29: =F29+G29 -> 207000
B30: 2 | C30: =Quarters!$E$5 -> Q2 2022 | D30: LP-12 | E30: Ivywood Capital Partners (FoF) | F30: ='Capital Call Schedule'!$D$5*'LP Register'!$F$15 -> 165000 | G30: ='Capital Call Schedule'!$E$5*'LP Register'!$F$15 -> 7500 | H30: =F30+G30 -> 172500
B31: 2 | C31: =Quarters!$E$5 -> Q2 2022 | D31: LP-13 | E31: Grayling Family Office | F31: ='Capital Call Schedule'!$D$5*'LP Register'!$F$16 -> 165000 | G31: ='Capital Call Schedule'!$E$5*'LP Register'!$F$16 -> 7500 | H31: =F31+G31 -> 172500
B32: 2 | C32: =Quarters!$E$5 -> Q2 2022 | D32: LP-14 | E32: Redstone Family Office | F32: ='Capital Call Schedule'!$D$5*'LP Register'!$F$17 -> 176000 | G32: ='Capital Call Schedule'!$E$5*'LP Register'!$F$17 -> 8000 | H32: =F32+G32 -> 184000
B33: 2 | C33: =Quarters!$E$5 -> Q2 2022 | D33: LP-15 | E33: Sable Foundation | F33: ='Capital Call Schedule'!$D$5*'LP Register'!$F$18 -> 176000 | G33: ='Capital Call Schedule'!$E$5*'LP Register'!$F$18 -> 8000 | H33: =F33+G33 -> 184000
B34: 3 | C34: =Quarters!$E$6 -> Q3 2022 | D34: LP-01 | E34: Northbridge State Pension Fund | F34: ='Capital Call Schedule'!$D$6*'LP Register'!$F$4 -> 720000 | G34: ='Capital Call Schedule'!$E$6*'LP Register'!$F$4 -> 40000 | H34: =F34+G34 -> 760000
B35: 3 | C35: =Quarters!$E$6 -> Q3 2022 | D35: LP-02 | E35: Meridian University Endowment | F35: ='Capital Call Schedule'!$D$6*'LP Register'!$F$5 -> 540000 | G35: ='Capital Call Schedule'!$E$6*'LP Register'!$F$5 -> 30000 | H35: =F35+G35 -> 570000
B36: 3 | C36: =Quarters!$E$6 -> Q3 2022 | D36: LP-03 | E36: Harborview Insurance Co. | F36: ='Capital Call Schedule'!$D$6*'LP Register'!$F$6 -> 495000 | G36: ='Capital Call Schedule'!$E$6*'LP Register'!$F$6 -> 27500 | H36: =F36+G36 -> 522500
B37: 3 | C37: =Quarters!$E$6 -> Q3 2022 | D37: LP-04 | E37: Cascade Partners Fund of Funds | F37: ='Capital Call Schedule'!$D$6*'LP Register'!$F$7 -> 450000 | G37: ='Capital Call Schedule'!$E$6*'LP Register'!$F$7 -> 25000 | H37: =F37+G37 -> 475000
B38: 3 | C38: =Quarters!$E$6 -> Q3 2022 | D38: LP-05 | E38: Elmwood Family Office | F38: ='Capital Call Schedule'!$D$6*'LP Register'!$F$8 -> 360000 | G38: ='Capital Call Schedule'!$E$6*'LP Register'!$F$8 -> 20000 | H38: =F38+G38 -> 380000
B39: 3 | C39: =Quarters!$E$6 -> Q3 2022 | D39: LP-06 | E39: Tanager Sovereign Partners | F39: ='Capital Call Schedule'!$D$6*'LP Register'!$F$9 -> 360000 | G39: ='Capital Call Schedule'!$E$6*'LP Register'!$F$9 -> 20000 | H39: =F39+G39 -> 380000
B40: 3 | C40: =Quarters!$E$6 -> Q3 2022 | D40: LP-07 | E40: Birchwood College Endowment | F40: ='Capital Call Schedule'!$D$6*'LP Register'!$F$10 -> 270000 | G40: ='Capital Call Schedule'!$E$6*'LP Register'!$F$10 -> 15000 | H40: =F40+G40 -> 285000
B41: 3 | C41: =Quarters!$E$6 -> Q3 2022 | D41: LP-08 | E41: Kestrel Insurance Group | F41: ='Capital Call Schedule'!$D$6*'LP Register'!$F$11 -> 225000 | G41: ='Capital Call Schedule'!$E$6*'LP Register'!$F$11 -> 12500 | H41: =F41+G41 -> 237500
B42: 3 | C42: =Quarters!$E$6 -> Q3 2022 | D42: LP-09 | E42: Wrenfield Family Office | F42: ='Capital Call Schedule'!$D$6*'LP Register'!$F$12 -> 180000 | G42: ='Capital Call Schedule'!$E$6*'LP Register'!$F$12 -> 10000 | H42: =F42+G42 -> 190000
B43: 3 | C43: =Quarters!$E$6 -> Q3 2022 | D43: LP-10 | E43: Alder Street Foundation | F43: ='Capital Call Schedule'!$D$6*'LP Register'!$F$13 -> 180000 | G43: ='Capital Call Schedule'!$E$6*'LP Register'!$F$13 -> 10000 | H43: =F43+G43 -> 190000
B44: 3 | C44: =Quarters!$E$6 -> Q3 2022 | D44: LP-11 | E44: Pinecrest Pension Trust | F44: ='Capital Call Schedule'!$D$6*'LP Register'!$F$14 -> 162000 | G44: ='Capital Call Schedule'!$E$6*'LP Register'!$F$14 -> 9000 | H44: =F44+G44 -> 171000
B45: 3 | C45: =Quarters!$E$6 -> Q3 2022 | D45: LP-12 | E45: Ivywood Capital Partners (FoF) | F45: ='Capital Call Schedule'!$D$6*'LP Register'!$F$15 -> 135000 | G45: ='Capital Call Schedule'!$E$6*'LP Register'!$F$15 -> 7500 | H45: =F45+G45 -> 142500
B46: 3 | C46: =Quarters!$E$6 -> Q3 2022 | D46: LP-13 | E46: Grayling Family Office | F46: ='Capital Call Schedule'!$D$6*'LP Register'!$F$16 -> 135000 | G46: ='Capital Call Schedule'!$E$6*'LP Register'!$F$16 -> 7500 | H46: =F46+G46 -> 142500
B47: 3 | C47: =Quarters!$E$6 -> Q3 2022 | D47: LP-14 | E47: Redstone Family Office | F47: ='Capital Call Schedule'!$D$6*'LP Register'!$F$17 -> 144000 | G47: ='Capital Call Schedule'!$E$6*'LP Register'!$F$17 -> 8000 | H47: =F47+G47 -> 152000
B48: 3 | C48: =Quarters!$E$6 -> Q3 2022 | D48: LP-15 | E48: Sable Foundation | F48: ='Capital Call Schedule'!$D$6*'LP Register'!$F$18 -> 144000 | G48: ='Capital Call Schedule'!$E$6*'LP Register'!$F$18 -> 8000 | H48: =F48+G48 -> 152000
B49: 4 | C49: =Quarters!$E$7 -> Q4 2022 | D49: LP-01 | E49: Northbridge State Pension Fund | F49: ='Capital Call Schedule'!$D$7*'LP Register'!$F$4 -> 800000 | G49: ='Capital Call Schedule'!$E$7*'LP Register'!$F$4 -> 40000 | H49: =F49+G49 -> 840000
B50: 4 | C50: =Quarters!$E$7 -> Q4 2022 | D50: LP-02 | E50: Meridian University Endowment | F50: ='Capital Call Schedule'!$D$7*'LP Register'!$F$5 -> 600000 | G50: ='Capital Call Schedule'!$E$7*'LP Register'!$F$5 -> 30000 | H50: =F50+G50 -> 630000
B51: 4 | C51: =Quarters!$E$7 -> Q4 2022 | D51: LP-03 | E51: Harborview Insurance Co. | F51: ='Capital Call Schedule'!$D$7*'LP Register'!$F$6 -> 550000 | G51: ='Capital Call Schedule'!$E$7*'LP Register'!$F$6 -> 27500 | H51: =F51+G51 -> 577500
B52: 4 | C52: =Quarters!$E$7 -> Q4 2022 | D52: LP-04 | E52: Cascade Partners Fund of Funds | F52: ='Capital Call Schedule'!$D$7*'LP Register'!$F$7 -> 500000 | G52: ='Capital Call Schedule'!$E$7*'LP Register'!$F$7 -> 25000 | H52: =F52+G52 -> 525000
B53: 4 | C53: =Quarters!$E$7 -> Q4 2022 | D53: LP-05 | E53: Elmwood Family Office | F53: ='Capital Call Schedule'!$D$7*'LP Register'!$F$8 -> 400000 | G53: ='Capital Call Schedule'!$E$7*'LP Register'!$F$8 -> 20000 | H53: =F53+G53 -> 420000
B54: 4 | C54: =Quarters!$E$7 -> Q4 2022 | D54: LP-06 | E54: Tanager Sovereign Partners | F54: ='Capital Call Schedule'!$D$7*'LP Register'!$F$9 -> 400000 | G54: ='Capital Call Schedule'!$E$7*'LP Register'!$F$9 -> 20000 | H54: =F54+G54 -> 420000
B55: 4 | C55: =Quarters!$E$7 -> Q4 2022 | D55: LP-07 | E55: Birchwood College Endowment | F55: ='Capital Call Schedule'!$D$7*'LP Register'!$F$10 -> 300000 | G55: ='Capital Call Schedule'!$E$7*'LP Register'!$F$10 -> 15000 | H55: =F55+G55 -> 315000
B56: 4 | C56: =Quarters!$E$7 -> Q4 2022 | D56: LP-08 | E56: Kestrel Insurance Group | F56: ='Capital Call Schedule'!$D$7*'LP Register'!$F$11 -> 250000 | G56: ='Capital Call Schedule'!$E$7*'LP Register'!$F$11 -> 12500 | H56: =F56+G56 -> 262500
B57: 4 | C57: =Quarters!$E$7 -> Q4 2022 | D57: LP-09 | E57: Wrenfield Family Office | F57: ='Capital Call Schedule'!$D$7*'LP Register'!$F$12 -> 200000 | G57: ='Capital Call Schedule'!$E$7*'LP Register'!$F$12 -> 10000 | H57: =F57+G57 -> 210000
B58: 4 | C58: =Quarters!$E$7 -> Q4 2022 | D58: LP-10 | E58: Alder Street Foundation | F58: ='Capital Call Schedule'!$D$7*'LP Register'!$F$13 -> 200000 | G58: ='Capital Call Schedule'!$E$7*'LP Register'!$F$13 -> 10000 | H58: =F58+G58 -> 210000
B59: 4 | C59: =Quarters!$E$7 -> Q4 2022 | D59: LP-11 | E59: Pinecrest Pension Trust | F59: ='Capital Call Schedule'!$D$7*'LP Register'!$F$14 -> 180000 | G59: ='Capital Call Schedule'!$E$7*'LP Register'!$F$14 -> 9000 | H59: =F59+G59 -> 189000
B60: 4 | C60: =Quarters!$E$7 -> Q4 2022 | D60: LP-12 | E60: Ivywood Capital Partners (FoF) | F60: ='Capital Call Schedule'!$D$7*'LP Register'!$F$15 -> 150000 | G60: ='Capital Call Schedule'!$E$7*'LP Register'!$F$15 -> 7500 | H60: =F60+G60 -> 157500
B61: 4 | C61: =Quarters!$E$7 -> Q4 2022 | D61: LP-13 | E61: Grayling Family Office | F61: ='Capital Call Schedule'!$D$7*'LP Register'!$F$16 -> 150000 | G61: ='Capital Call Schedule'!$E$7*'LP Register'!$F$16 -> 7500 | H61: =F61+G61 -> 157500
B62: 4 | C62: =Quarters!$E$7 -> Q4 2022 | D62: LP-14 | E62: Redstone Family Office | F62: ='Capital Call Schedule'!$D$7*'LP Register'!$F$17 -> 160000 | G62: ='Capital Call Schedule'!$E$7*'LP Register'!$F$17 -> 8000 | H62: =F62+G62 -> 168000
B63: 4 | C63: =Quarters!$E$7 -> Q4 2022 | D63: LP-15 | E63: Sable Foundation | F63: ='Capital Call Schedule'!$D$7*'LP Register'!$F$18 -> 160000 | G63: ='Capital Call Schedule'!$E$7*'LP Register'!$F$18 -> 8000 | H63: =F63+G63 -> 168000
B64: 5 | C64: =Quarters!$E$8 -> Q1 2023 | D64: LP-01 | E64: Northbridge State Pension Fund | F64: ='Capital Call Schedule'!$D$8*'LP Register'!$F$4 -> 640000 | G64: ='Capital Call Schedule'!$E$8*'LP Register'!$F$4 -> 40000 | H64: =F64+G64 -> 680000
B65: 5 | C65: =Quarters!$E$8 -> Q1 2023 | D65: LP-02 | E65: Meridian University Endowment | F65: ='Capital Call Schedule'!$D$8*'LP Register'!$F$5 -> 480000 | G65: ='Capital Call Schedule'!$E$8*'LP Register'!$F$5 -> 30000 | H65: =F65+G65 -> 510000
B66: 5 | C66: =Quarters!$E$8 -> Q1 2023 | D66: LP-03 | E66: Harborview Insurance Co. | F66: ='Capital Call Schedule'!$D$8*'LP Register'!$F$6 -> 440000 | G66: ='Capital Call Schedule'!$E$8*'LP Register'!$F$6 -> 27500 | H66: =F66+G66 -> 467500
B67: 5 | C67: =Quarters!$E$8 -> Q1 2023 | D67: LP-04 | E67: Cascade Partners Fund of Funds | F67: ='Capital Call Schedule'!$D$8*'LP Register'!$F$7 -> 400000 | G67: ='Capital Call Schedule'!$E$8*'LP Register'!$F$7 -> 25000 | H67: =F67+G67 -> 425000
B68: 5 | C68: =Quarters!$E$8 -> Q1 2023 | D68: LP-05 | E68: Elmwood Family Office | F68: ='Capital Call Schedule'!$D$8*'LP Register'!$F$8 -> 320000 | G68: ='Capital Call Schedule'!$E$8*'LP Register'!$F$8 -> 20000 | H68: =F68+G68 -> 340000
B69: 5 | C69: =Quarters!$E$8 -> Q1 2023 | D69: LP-06 | E69: Tanager Sovereign Partners | F69: ='Capital Call Schedule'!$D$8*'LP Register'!$F$9 -> 320000 | G69: ='Capital Call Schedule'!$E$8*'LP Register'!$F$9 -> 20000 | H69: =F69+G69 -> 340000
B70: 5 | C70: =Quarters!$E$8 -> Q1 2023 | D70: LP-07 | E70: Birchwood College Endowment | F70: ='Capital Call Schedule'!$D$8*'LP Register'!$F$10 -> 240000 | G70: ='Capital Call Schedule'!$E$8*'LP Register'!$F$10 -> 15000 | H70: =F70+G70 -> 255000
B71: 5 | C71: =Quarters!$E$8 -> Q1 2023 | D71: LP-08 | E71: Kestrel Insurance Group | F71: ='Capital Call Schedule'!$D$8*'LP Register'!$F$11 -> 200000 | G71: ='Capital Call Schedule'!$E$8*'LP Register'!$F$11 -> 12500 | H71: =F71+G71 -> 212500
B72: 5 | C72: =Quarters!$E$8 -> Q1 2023 | D72: LP-09 | E72: Wrenfield Family Office | F72: ='Capital Call Schedule'!$D$8*'LP Register'!$F$12 -> 160000 | G72: ='Capital Call Schedule'!$E$8*'LP Register'!$F$12 -> 10000 | H72: =F72+G72 -> 170000
B73: 5 | C73: =Quarters!$E$8 -> Q1 2023 | D73: LP-10 | E73: Alder Street Foundation | F73: ='Capital Call Schedule'!$D$8*'LP Register'!$F$13 -> 160000 | G73: ='Capital Call Schedule'!$E$8*'LP Register'!$F$13 -> 10000 | H73: =F73+G73 -> 170000
B74: 5 | C74: =Quarters!$E$8 -> Q1 2023 | D74: LP-11 | E74: Pinecrest Pension Trust | F74: ='Capital Call Schedule'!$D$8*'LP Register'!$F$14 -> 144000 | G74: ='Capital Call Schedule'!$E$8*'LP Register'!$F$14 -> 9000 | H74: =F74+G74 -> 153000
B75: 5 | C75: =Quarters!$E$8 -> Q1 2023 | D75: LP-12 | E75: Ivywood Capital Partners (FoF) | F75: ='Capital Call Schedule'!$D$8*'LP Register'!$F$15 -> 120000 | G75: ='Capital Call Schedule'!$E$8*'LP Register'!$F$15 -> 7500 | H75: =F75+G75 -> 127500
B76: 5 | C76: =Quarters!$E$8 -> Q1 2023 | D76: LP-13 | E76: Grayling Family Office | F76: ='Capital Call Schedule'!$D$8*'LP Register'!$F$16 -> 120000 | G76: ='Capital Call Schedule'!$E$8*'LP Register'!$F$16 -> 7500 | H76: =F76+G76 -> 127500
B77: 5 | C77: =Quarters!$E$8 -> Q1 2023 | D77: LP-14 | E77: Redstone Family Office | F77: ='Capital Call Schedule'!$D$8*'LP Register'!$F$17 -> 128000 | G77: ='Capital Call Schedule'!$E$8*'LP Register'!$F$17 -> 8000 | H77: =F77+G77 -> 136000
B78: 5 | C78: =Quarters!$E$8 -> Q1 2023 | D78: LP-15 | E78: Sable Foundation | F78: ='Capital Call Schedule'!$D$8*'LP Register'!$F$18 -> 128000 | G78: ='Capital Call Schedule'!$E$8*'LP Register'!$F$18 -> 8000 | H78: =F78+G78 -> 136000
B79: 6 | C79: =Quarters!$E$9 -> Q2 2023 | D79: LP-01 | E79: Northbridge State Pension Fund | F79: ='Capital Call Schedule'!$D$9*'LP Register'!$F$4 -> 800000 | G79: ='Capital Call Schedule'!$E$9*'LP Register'!$F$4 -> 40000 | H79: =F79+G79 -> 840000
B80: 6 | C80: =Quarters!$E$9 -> Q2 2023 | D80: LP-02 | E80: Meridian University Endowment | F80: ='Capital Call Schedule'!$D$9*'LP Register'!$F$5 -> 600000 | G80: ='Capital Call Schedule'!$E$9*'LP Register'!$F$5 -> 30000 | H80: =F80+G80 -> 630000
B81: 6 | C81: =Quarters!$E$9 -> Q2 2023 | D81: LP-03 | E81: Harborview Insurance Co. | F81: ='Capital Call Schedule'!$D$9*'LP Register'!$F$6 -> 550000 | G81: ='Capital Call Schedule'!$E$9*'LP Register'!$F$6 -> 27500 | H81: =F81+G81 -> 577500
B82: 6 | C82: =Quarters!$E$9 -> Q2 2023 | D82: LP-04 | E82: Cascade Partners Fund of Funds | F82: ='Capital Call Schedule'!$D$9*'LP Register'!$F$7 -> 500000 | G82: ='Capital Call Schedule'!$E$9*'LP Register'!$F$7 -> 25000 | H82: =F82+G82 -> 525000
B83: 6 | C83: =Quarters!$E$9 -> Q2 2023 | D83: LP-05 | E83: Elmwood Family Office | F83: ='Capital Call Schedule'!$D$9*'LP Register'!$F$8 -> 400000 | G83: ='Capital Call Schedule'!$E$9*'LP Register'!$F$8 -> 20000 | H83: =F83+G83 -> 420000
B84: 6 | C84: =Quarters!$E$9 -> Q2 2023 | D84: LP-06 | E84: Tanager Sovereign Partners | F84: ='Capital Call Schedule'!$D$9*'LP Register'!$F$9 -> 400000 | G84: ='Capital Call Schedule'!$E$9*'LP Register'!$F$9 -> 20000 | H84: =F84+G84 -> 420000
B85: 6 | C85: =Quarters!$E$9 -> Q2 2023 | D85: LP-07 | E85: Birchwood College Endowment | F85: ='Capital Call Schedule'!$D$9*'LP Register'!$F$10 -> 300000 | G85: ='Capital Call Schedule'!$E$9*'LP Register'!$F$10 -> 15000 | H85: =F85+G85 -> 315000
B86: 6 | C86: =Quarters!$E$9 -> Q2 2023 | D86: LP-08 | E86: Kestrel Insurance Group | F86: ='Capital Call Schedule'!$D$9*'LP Register'!$F$11 -> 250000 | G86: ='Capital Call Schedule'!$E$9*'LP Register'!$F$11 -> 12500 | H86: =F86+G86 -> 262500
B87: 6 | C87: =Quarters!$E$9 -> Q2 2023 | D87: LP-09 | E87: Wrenfield Family Office | F87: ='Capital Call Schedule'!$D$9*'LP Register'!$F$12 -> 200000 | G87: ='Capital Call Schedule'!$E$9*'LP Register'!$F$12 -> 10000 | H87: =F87+G87 -> 210000
B88: 6 | C88: =Quarters!$E$9 -> Q2 2023 | D88: LP-10 | E88: Alder Street Foundation | F88: ='Capital Call Schedule'!$D$9*'LP Register'!$F$13 -> 200000 | G88: ='Capital Call Schedule'!$E$9*'LP Register'!$F$13 -> 10000 | H88: =F88+G88 -> 210000
B89: 6 | C89: =Quarters!$E$9 -> Q2 2023 | D89: LP-11 | E89: Pinecrest Pension Trust | F89: ='Capital Call Schedule'!$D$9*'LP Register'!$F$14 -> 180000 | G89: ='Capital Call Schedule'!$E$9*'LP Register'!$F$14 -> 9000 | H89: =F89+G89 -> 189000
B90: 6 | C90: =Quarters!$E$9 -> Q2 2023 | D90: LP-12 | E90: Ivywood Capital Partners (FoF) | F90: ='Capital Call Schedule'!$D$9*'LP Register'!$F$15 -> 150000 | G90: ='Capital Call Schedule'!$E$9*'LP Register'!$F$15 -> 7500 | H90: =F90+G90 -> 157500
B91: 6 | C91: =Quarters!$E$9 -> Q2 2023 | D91: LP-13 | E91: Grayling Family Office | F91: ='Capital Call Schedule'!$D$9*'LP Register'!$F$16 -> 150000 | G91: ='Capital Call Schedule'!$E$9*'LP Register'!$F$16 -> 7500 | H91: =F91+G91 -> 157500
B92: 6 | C92: =Quarters!$E$9 -> Q2 2023 | D92: LP-14 | E92: Redstone Family Office | F92: ='Capital Call Schedule'!$D$9*'LP Register'!$F$17 -> 160000 | G92: ='Capital Call Schedule'!$E$9*'LP Register'!$F$17 -> 8000 | H92: =F92+G92 -> 168000
B93: 6 | C93: =Quarters!$E$9 -> Q2 2023 | D93: LP-15 | E93: Sable Foundation | F93: ='Capital Call Schedule'!$D$9*'LP Register'!$F$18 -> 160000 | G93: ='Capital Call Schedule'!$E$9*'LP Register'!$F$18 -> 8000 | H93: =F93+G93 -> 168000
B94: 7 | C94: =Quarters!$E$10 -> Q3 2023 | D94: LP-01 | E94: Northbridge State Pension Fund | F94: ='Capital Call Schedule'!$D$10*'LP Register'!$F$4 -> 720000 | G94: ='Capital Call Schedule'!$E$10*'LP Register'!$F$4 -> 40000 | H94: =F94+G94 -> 760000
B95: 7 | C95: =Quarters!$E$10 -> Q3 2023 | D95: LP-02 | E95: Meridian University Endowment | F95: ='Capital Call Schedule'!$D$10*'LP Register'!$F$5 -> 540000 | G95: ='Capital Call Schedule'!$E$10*'LP Register'!$F$5 -> 30000 | H95: =F95+G95 -> 570000
B96: 7 | C96: =Quarters!$E$10 -> Q3 2023 | D96: LP-03 | E96: Harborview Insurance Co. | F96: ='Capital Call Schedule'!$D$10*'LP Register'!$F$6 -> 495000 | G96: ='Capital Call Schedule'!$E$10*'LP Register'!$F$6 -> 27500 | H96: =F96+G96 -> 522500
B97: 7 | C97: =Quarters!$E$10 -> Q3 2023 | D97: LP-04 | E97: Cascade Partners Fund of Funds | F97: ='Capital Call Schedule'!$D$10*'LP Register'!$F$7 -> 450000 | G97: ='Capital Call Schedule'!$E$10*'LP Register'!$F$7 -> 25000 | H97: =F97+G97 -> 475000
B98: 7 | C98: =Quarters!$E$10 -> Q3 2023 | D98: LP-05 | E98: Elmwood Family Office | F98: ='Capital Call Schedule'!$D$10*'LP Register'!$F$8 -> 360000 | G98: ='Capital Call Schedule'!$E$10*'LP Register'!$F$8 -> 20000 | H98: =F98+G98 -> 380000
B99: 7 | C99: =Quarters!$E$10 -> Q3 2023 | D99: LP-06 | E99: Tanager Sovereign Partners | F99: ='Capital Call Schedule'!$D$10*'LP Register'!$F$9 -> 360000 | G99: ='Capital Call Schedule'!$E$10*'LP Register'!$F$9 -> 20000 | H99: =F99+G99 -> 380000
B100: 7 | C100: =Quarters!$E$10 -> Q3 2023 | D100: LP-07 | E100: Birchwood College Endowment | F100: ='Capital Call Schedule'!$D$10*'LP Register'!$F$10 -> 270000 | G100: ='Capital Call Schedule'!$E$10*'LP Register'!$F$10 -> 15000 | H100: =F100+G100 -> 285000
...

Sheet LP Capital Accounts
A1: LP Capital Account Statements
A2: Each LP's quarterly capital account — beginning balance through ending balance
B3: Qtr # | C3: Quarter | D3: LP ID | E3: LP Name | F3: Beginning Balance | G3: Contributions | H3: Dist: Return of Capital | I3: Dist: Preferred Return | J3: Dist: Carry Split (LP 80%) | K3: Total Cash Distributions | L3: Gain/(Loss) Allocation, Net of Fees | M3: Less: Carried Interest to GP | N3: Ending Balance | O3: Lookup Key
B4: 1 | C4: =Quarters!$E$4 -> Q1 2022 | D4: LP-01 | E4: Northbridge State Pension Fund | F4: 0 | G4: ='LP Capital Calls'!$H$4 -> 1000000 | H4: ='Distribution Waterfall'!$L$4*'LP Register'!$F$4 -> 0 | I4: ='Distribution Waterfall'!$N$4*'LP Register'!$F$4 -> 0 | J4: ='Distribution Waterfall'!$T$4*'LP Register'!$F$4 -> 0 | K4: =H4+I4+J4 -> 0 | L4: =('NAV Rollforward'!$G$4+'NAV Rollforward'!$H$4-'Mgmt Fee Schedule'!$G$4)*'LP Register'!$F$4 -> -40000 | M4: =-('Distribution Waterfall'!$Q$4+'Distribution Waterfall'!$U$4)*'LP Register'!$F$4 -> 0 | N4: =F4+G4-K4+L4+M4 -> 960000 | O4: =B4&"|"&D4 -> 1|LP-01
B5: 1 | C5: =Quarters!$E$4 -> Q1 2022 | D5: LP-02 | E5: Meridian University Endowment | F5: 0 | G5: ='LP Capital Calls'!$H$5 -> 750000 | H5: ='Distribution Waterfall'!$L$4*'LP Register'!$F$5 -> 0 | I5: ='Distribution Waterfall'!$N$4*'LP Register'!$F$5 -> 0 | J5: ='Distribution Waterfall'!$T$4*'LP Register'!$F$5 -> 0 | K5: =H5+I5+J5 -> 0 | L5: =('NAV Rollforward'!$G$4+'NAV Rollforward'!$H$4-'Mgmt Fee Schedule'!$G$4)*'LP Register'!$F$5 -> -30000 | M5: =-('Distribution Waterfall'!$Q$4+'Distribution Waterfall'!$U$4)*'LP Register'!$F$5 -> 0 | N5: =F5+G5-K5+L5+M5 -> 720000 | O5: =B5&"|"&D5 -> 1|LP-02
B6: 1 | C6: =Quarters!$E$4 -> Q1 2022 | D6: LP-03 | E6: Harborview Insurance Co. | F6: 0 | G6: ='LP Capital Calls'!$H$6 -> 687500 | H6: ='Distribution Waterfall'!$L$4*'LP Register'!$F$6 -> 0 | I6: ='Distribution Waterfall'!$N$4*'LP Register'!$F$6 -> 0 | J6: ='Distribution Waterfall'!$T$4*'LP Register'!$F$6 -> 0 | K6: =H6+I6+J6 -> 0 | L6: =('NAV Rollforward'!$G$4+'NAV Rollforward'!$H$4-'Mgmt Fee Schedule'!$G$4)*'LP Register'!$F$6 -> -27500 | M6: =-('Distribution Waterfall'!$Q$4+'Distribution Waterfall'!$U$4)*'LP Register'!$F$6 -> 0 | N6: =F6+G6-K6+L6+M6 -> 660000 | O6: =B6&"|"&D6 -> 1|LP-03
B7: 1 | C7: =Quarters!$E$4 -> Q1 2022 | D7: LP-04 | E7: Cascade Partners Fund of Funds | F7: 0 | G7: ='LP Capital Calls'!$H$7 -> 625000 | H7: ='Distribution Waterfall'!$L$4*'LP Register'!$F$7 -> 0 | I7: ='Distribution Waterfall'!$N$4*'LP Register'!$F$7 -> 0 | J7: ='Distribution Waterfall'!$T$4*'LP Register'!$F$7 -> 0 | K7: =H7+I7+J7 -> 0 | L7: =('NAV Rollforward'!$G$4+'NAV Rollforward'!$H$4-'Mgmt Fee Schedule'!$G$4)*'LP Register'!$F$7 -> -25000 | M7: =-('Distribution Waterfall'!$Q$4+'Distribution Waterfall'!$U$4)*'LP Register'!$F$7 -> 0 | N7: =F7+G7-K7+L7+M7 -> 600000 | O7: =B7&"|"&D7 -> 1|LP-04
B8: 1 | C8: =Quarters!$E$4 -> Q1 2022 | D8: LP-05 | E8: Elmwood Family Office | F8: 0 | G8: ='LP Capital Calls'!$H$8 -> 500000 | H8: ='Distribution Waterfall'!$L$4*'LP Register'!$F$8 -> 0 | I8: ='Distribution Waterfall'!$N$4*'LP Register'!$F$8 -> 0 | J8: ='Distribution Waterfall'!$T$4*'LP Register'!$F$8 -> 0 | K8: =H8+I8+J8 -> 0 | L8: =('NAV Rollforward'!$G$4+'NAV Rollforward'!$H$4-'Mgmt Fee Schedule'!$G$4)*'LP Register'!$F$8 -> -20000 | M8: =-('Distribution Waterfall'!$Q$4+'Distribution Waterfall'!$U$4)*'LP Register'!$F$8 -> 0 | N8: =F8+G8-K8+L8+M8 -> 480000 | O8: =B8&"|"&D8 -> 1|LP-05
B9: 1 | C9: =Quarters!$E$4 -> Q1 2022 | D9: LP-06 | E9: Tanager Sovereign Partners | F9: 0 | G9: ='LP Capital Calls'!$H$9 -> 500000 | H9: ='Distribution Waterfall'!$L$4*'LP Register'!$F$9 -> 0 | I9: ='Distribution Waterfall'!$N$4*'LP Register'!$F$9 -> 0 | J9: ='Distribution Waterfall'!$T$4*'LP Register'!$F$9 -> 0 | K9: =H9+I9+J9 -> 0 | L9: =('NAV Rollforward'!$G$4+'NAV Rollforward'!$H$4-'Mgmt Fee Schedule'!$G$4)*'LP Register'!$F$9 -> -20000 | M9: =-('Distribution Waterfall'!$Q$4+'Distribution Waterfall'!$U$4)*'LP Register'!$F$9 -> 0 | N9: =F9+G9-K9+L9+M9 -> 480000 | O9: =B9&"|"&D9 -> 1|LP-06
B10: 1 | C10: =Quarters!$E$4 -> Q1 2022 | D10: LP-07 | E10: Birchwood College Endowment | F10: 0 | G10: ='LP Capital Calls'!$H$10 -> 375000 | H10: ='Distribution Waterfall'!$L$4*'LP Register'!$F$10 -> 0 | I10: ='Distribution Waterfall'!$N$4*'LP Register'!$F$10 -> 0 | J10: ='Distribution Waterfall'!$T$4*'LP Register'!$F$10 -> 0 | K10: =H10+I10+J10 -> 0 | L10: =('NAV Rollforward'!$G$4+'NAV Rollforward'!$H$4-'Mgmt Fee Schedule'!$G$4)*'LP Register'!$F$10 -> -15000 | M10: =-('Distribution Waterfall'!$Q$4+'Distribution Waterfall'!$U$4)*'LP Register'!$F$10 -> 0 | N10: =F10+G10-K10+L10+M10 -> 360000 | O10: =B10&"|"&D10 -> 1|LP-07
B11: 1 | C11: =Quarters!$E$4 -> Q1 2022 | D11: LP-08 | E11: Kestrel Insurance Group | F11: 0 | G11: ='LP Capital Calls'!$H$11 -> 312500 | H11: ='Distribution Waterfall'!$L$4*'LP Register'!$F$11 -> 0 | I11: ='Distribution Waterfall'!$N$4*'LP Register'!$F$11 -> 0 | J11: ='Distribution Waterfall'!$T$4*'LP Register'!$F$11 -> 0 | K11: =H11+I11+J11 -> 0 | L11: =('NAV Rollforward'!$G$4+'NAV Rollforward'!$H$4-'Mgmt Fee Schedule'!$G$4)*'LP Register'!$F$11 -> -12500 | M11: =-('Distribution Waterfall'!$Q$4+'Distribution Waterfall'!$U$4)*'LP Register'!$F$11 -> 0 | N11: =F11+G11-K11+L11+M11 -> 300000 | O11: =B11&"|"&D11 -> 1|LP-08
B12: 1 | C12: =Quarters!$E$4 -> Q1 2022 | D12: LP-09 | E12: Wrenfield Family Office | F12: 0 | G12: ='LP Capital Calls'!$H$12 -> 250000 | H12: ='Distribution Waterfall'!$L$4*'LP Register'!$F$12 -> 0 | I12: ='Distribution Waterfall'!$N$4*'LP Register'!$F$12 -> 0 | J12: ='Distribution Waterfall'!$T$4*'LP Register'!$F$12 -> 0 | K12: =H12+I12+J12 -> 0 | L12: =('NAV Rollforward'!$G$4+'NAV Rollforward'!$H$4-'Mgmt Fee Schedule'!$G$4)*'LP Register'!$F$12 -> -10000 | M12: =-('Distribution Waterfall'!$Q$4+'Distribution Waterfall'!$U$4)*'LP Register'!$F$12 -> 0 | N12: =F12+G12-K12+L12+M12 -> 240000 | O12: =B12&"|"&D12 -> 1|LP-09
B13: 1 | C13: =Quarters!$E$4 -> Q1 2022 | D13: LP-10 | E13: Alder Street Foundation | F13: 0 | G13: ='LP Capital Calls'!$H$13 -> 250000 | H13: ='Distribution Waterfall'!$L$4*'LP Register'!$F$13 -> 0 | I13: ='Distribution Waterfall'!$N$4*'LP Register'!$F$13 -> 0 | J13: ='Distribution Waterfall'!$T$4*'LP Register'!$F$13 -> 0 | K13: =H13+I13+J13 -> 0 | L13: =('NAV Rollforward'!$G$4+'NAV Rollforward'!$H$4-'Mgmt Fee Schedule'!$G$4)*'LP Register'!$F$13 -> -10000 | M13: =-('Distribution Waterfall'!$Q$4+'Distribution Waterfall'!$U$4)*'LP Register'!$F$13 -> 0 | N13: =F13+G13-K13+L13+M13 -> 240000 | O13: =B13&"|"&D13 -> 1|LP-10
B14: 1 | C14: =Quarters!$E$4 -> Q1 2022 | D14: LP-11 | E14: Pinecrest Pension Trust | F14: 0 | G14: ='LP Capital Calls'!$H$14 -> 225000 | H14: ='Distribution Waterfall'!$L$4*'LP Register'!$F$14 -> 0 | I14: ='Distribution Waterfall'!$N$4*'LP Register'!$F$14 -> 0 | J14: ='Distribution Waterfall'!$T$4*'LP Register'!$F$14 -> 0 | K14: =H14+I14+J14 -> 0 | L14: =('NAV Rollforward'!$G$4+'NAV Rollforward'!$H$4-'Mgmt Fee Schedule'!$G$4)*'LP Register'!$F$14 -> -9000 | M14: =-('Distribution Waterfall'!$Q$4+'Distribution Waterfall'!$U$4)*'LP Register'!$F$14 -> 0 | N14: =F14+G14-K14+L14+M14 -> 216000 | O14: =B14&"|"&D14 -> 1|LP-11
B15: 1 | C15: =Quarters!$E$4 -> Q1 2022 | D15: LP-12 | E15: Ivywood Capital Partners (FoF) | F15: 0 | G15: ='LP Capital Calls'!$H$15 -> 187500 | H15: ='Distribution Waterfall'!$L$4*'LP Register'!$F$15 -> 0 | I15: ='Distribution Waterfall'!$N$4*'LP Register'!$F$15 -> 0 | J15: ='Distribution Waterfall'!$T$4*'LP Register'!$F$15 -> 0 | K15: =H15+I15+J15 -> 0 | L15: =('NAV Rollforward'!$G$4+'NAV Rollforward'!$H$4-'Mgmt Fee Schedule'!$G$4)*'LP Register'!$F$15 -> -7500 | M15: =-('Distribution Waterfall'!$Q$4+'Distribution Waterfall'!$U$4)*'LP Register'!$F$15 -> 0 | N15: =F15+G15-K15+L15+M15 -> 180000 | O15: =B15&"|"&D15 -> 1|LP-12
B16: 1 | C16: =Quarters!$E$4 -> Q1 2022 | D16: LP-13 | E16: Grayling Family Office | F16: 0 | G16: ='LP Capital Calls'!$H$16 -> 187500 | H16: ='Distribution Waterfall'!$L$4*'LP Register'!$F$16 -> 0 | I16: ='Distribution Waterfall'!$N$4*'LP Register'!$F$16 -> 0 | J16: ='Distribution Waterfall'!$T$4*'LP Register'!$F$16 -> 0 | K16: =H16+I16+J16 -> 0 | L16: =('NAV Rollforward'!$G$4+'NAV Rollforward'!$H$4-'Mgmt Fee Schedule'!$G$4)*'LP Register'!$F$16 -> -7500 | M16: =-('Distribution Waterfall'!$Q$4+'Distribution Waterfall'!$U$4)*'LP Register'!$F$16 -> 0 | N16: =F16+G16-K16+L16+M16 -> 180000 | O16: =B16&"|"&D16 -> 1|LP-13
B17: 1 | C17: =Quarters!$E$4 -> Q1 2022 | D17: LP-14 | E17: Redstone Family Office | F17: 0 | G17: ='LP Capital Calls'!$H$17 -> 200000 | H17: ='Distribution Waterfall'!$L$4*'LP Register'!$F$17 -> 0 | I17: ='Distribution Waterfall'!$N$4*'LP Register'!$F$17 -> 0 | J17: ='Distribution Waterfall'!$T$4*'LP Register'!$F$17 -> 0 | K17: =H17+I17+J17 -> 0 | L17: =('NAV Rollforward'!$G$4+'NAV Rollforward'!$H$4-'Mgmt Fee Schedule'!$G$4)*'LP Register'!$F$17 -> -8000 | M17: =-('Distribution Waterfall'!$Q$4+'Distribution Waterfall'!$U$4)*'LP Register'!$F$17 -> 0 | N17: =F17+G17-K17+L17+M17 -> 192000 | O17: =B17&"|"&D17 -> 1|LP-14
B18: 1 | C18: =Quarters!$E$4 -> Q1 2022 | D18: LP-15 | E18: Sable Foundation | F18: 0 | G18: ='LP Capital Calls'!$H$18 -> 200000 | H18: ='Distribution Waterfall'!$L$4*'LP Register'!$F$18 -> 0 | I18: ='Distribution Waterfall'!$N$4*'LP Register'!$F$18 -> 0 | J18: ='Distribution Waterfall'!$T$4*'LP Register'!$F$18 -> 0 | K18: =H18+I18+J18 -> 0 | L18: =('NAV Rollforward'!$G$4+'NAV Rollforward'!$H$4-'Mgmt Fee Schedule'!$G$4)*'LP Register'!$F$18 -> -8000 | M18: =-('Distribution Waterfall'!$Q$4+'Distribution Waterfall'!$U$4)*'LP Register'!$F$18 -> 0 | N18: =F18+G18-K18+L18+M18 -> 192000 | O18: =B18&"|"&D18 -> 1|LP-15
B19: 2 | C19: =Quarters!$E$5 -> Q2 2022 | D19: LP-01 | E19: Northbridge State Pension Fund | F19: =N4 -> 960000 | G19: ='LP Capital Calls'!$H$19 -> 920000 | H19: ='Distribution Waterfall'!$L$5*'LP Register'!$F$4 -> 0 | I19: ='Distribution Waterfall'!$N$5*'LP Register'!$F$4 -> 0 | J19: ='Distribution Waterfall'!$T$5*'LP Register'!$F$4 -> 0 | K19: =H19+I19+J19 -> 0 | L19: =('NAV Rollforward'!$G$5+'NAV Rollforward'!$H$5-'Mgmt Fee Schedule'!$G$5)*'LP Register'!$F$4 -> 65187.926 | M19: =-('Distribution Waterfall'!$Q$5+'Distribution Waterfall'!$U$5)*'LP Register'!$F$4 -> 0 | N19: =F19+G19-K19+L19+M19 -> 1945187.9 | O19: =B19&"|"&D19 -> 2|LP-01
B20: 2 | C20: =Quarters!$E$5 -> Q2 2022 | D20: LP-02 | E20: Meridian University Endowment | F20: =N5 -> 720000 | G20: ='LP Capital Calls'!$H$20 -> 690000 | H20: ='Distribution Waterfall'!$L$5*'LP Register'!$F$5 -> 0 | I20: ='Distribution Waterfall'!$N$5*'LP Register'!$F$5 -> 0 | J20: ='Distribution Waterfall'!$T$5*'LP Register'!$F$5 -> 0 | K20: =H20+I20+J20 -> 0 | L20: =('NAV Rollforward'!$G$5+'NAV Rollforward'!$H$5-'Mgmt Fee Schedule'!$G$5)*'LP Register'!$F$5 -> 48890.945 | M20: =-('Distribution Waterfall'!$Q$5+'Distribution Waterfall'!$U$5)*'LP Register'!$F$5 -> 0 | N20: =F20+G20-K20+L20+M20 -> 1458890.9 | O20: =B20&"|"&D20 -> 2|LP-02
B21: 2 | C21: =Quarters!$E$5 -> Q2 2022 | D21: LP-03 | E21: Harborview Insurance Co. | F21: =N6 -> 660000 | G21: ='LP Capital Calls'!$H$21 -> 632500 | H21: ='Distribution Waterfall'!$L$5*'LP Register'!$F$6 -> 0 | I21: ='Distribution Waterfall'!$N$5*'LP Register'!$F$6 -> 0 | J21: ='Distribution Waterfall'!$T$5*'LP Register'!$F$6 -> 0 | K21: =H21+I21+J21 -> 0 | L21: =('NAV Rollforward'!$G$5+'NAV Rollforward'!$H$5-'Mgmt Fee Schedule'!$G$5)*'LP Register'!$F$6 -> 44816.699 | M21: =-('Distribution Waterfall'!$Q$5+'Distribution Waterfall'!$U$5)*'LP Register'!$F$6 -> 0 | N21: =F21+G21-K21+L21+M21 -> 1337316.7 | O21: =B21&"|"&D21 -> 2|LP-03
B22: 2 | C22: =Quarters!$E$5 -> Q2 2022 | D22: LP-04 | E22: Cascade Partners Fund of Funds | F22: =N7 -> 600000 | G22: ='LP Capital Calls'!$H$22 -> 575000 | H22: ='Distribution Waterfall'!$L$5*'LP Register'!$F$7 -> 0 | I22: ='Distribution Waterfall'!$N$5*'LP Register'!$F$7 -> 0 | J22: ='Distribution Waterfall'!$T$5*'LP Register'!$F$7 -> 0 | K22: =H22+I22+J22 -> 0 | L22: =('NAV Rollforward'!$G$5+'NAV Rollforward'!$H$5-'Mgmt Fee Schedule'!$G$5)*'LP Register'!$F$7 -> 40742.454 | M22: =-('Distribution Waterfall'!$Q$5+'Distribution Waterfall'!$U$5)*'LP Register'!$F$7 -> 0 | N22: =F22+G22-K22+L22+M22 -> 1215742.5 | O22: =B22&"|"&D22 -> 2|LP-04
B23: 2 | C23: =Quarters!$E$5 -> Q2 2022 | D23: LP-05 | E23: Elmwood Family Office | F23: =N8 -> 480000 | G23: ='LP Capital Calls'!$H$23 -> 460000 | H23: ='Distribution Waterfall'!$L$5*'LP Register'!$F$8 -> 0 | I23: ='Distribution Waterfall'!$N$5*'LP Register'!$F$8 -> 0 | J23: ='Distribution Waterfall'!$T$5*'LP Register'!$F$8 -> 0 | K23: =H23+I23+J23 -> 0 | L23: =('NAV Rollforward'!$G$5+'NAV Rollforward'!$H$5-'Mgmt Fee Schedule'!$G$5)*'LP Register'!$F$8 -> 32593.963 | M23: =-('Distribution Waterfall'!$Q$5+'Distribution Waterfall'!$U$5)*'LP Register'!$F$8 -> 0 | N23: =F23+G23-K23+L23+M23 -> 972593.96 | O23: =B23&"|"&D23 -> 2|LP-05
B24: 2 | C24: =Quarters!$E$5 -> Q2 2022 | D24: LP-06 | E24: Tanager Sovereign Partners | F24: =N9 -> 480000 | G24: ='LP Capital Calls'!$H$24 -> 460000 | H24: ='Distribution Waterfall'!$L$5*'LP Register'!$F$9 -> 0 | I24: ='Distribution Waterfall'!$N$5*'LP Register'!$F$9 -> 0 | J24: ='Distribution Waterfall'!$T$5*'LP Register'!$F$9 -> 0 | K24: =H24+I24+J24 -> 0 | L24: =('NAV Rollforward'!$G$5+'NAV Rollforward'!$H$5-'Mgmt Fee Schedule'!$G$5)*'LP Register'!$F$9 -> 32593.963 | M24: =-('Distribution Waterfall'!$Q$5+'Distribution Waterfall'!$U$5)*'LP Register'!$F$9 -> 0 | N24: =F24+G24-K24+L24+M24 -> 972593.96 | O24: =B24&"|"&D24 -> 2|LP-06
B25: 2 | C25: =Quarters!$E$5 -> Q2 2022 | D25: LP-07 | E25: Birchwood College Endowment | F25: =N10 -> 360000 | G25: ='LP Capital Calls'!$H$25 -> 345000 | H25: ='Distribution Waterfall'!$L$5*'LP Register'!$F$10 -> 0 | I25: ='Distribution Waterfall'!$N$5*'LP Register'!$F$10 -> 0 | J25: ='Distribution Waterfall'!$T$5*'LP Register'!$F$10 -> 0 | K25: =H25+I25+J25 -> 0 | L25: =('NAV Rollforward'!$G$5+'NAV Rollforward'!$H$5-'Mgmt Fee Schedule'!$G$5)*'LP Register'!$F$10 -> 24445.472 | M25: =-('Distribution Waterfall'!$Q$5+'Distribution Waterfall'!$U$5)*'LP Register'!$F$10 -> 0 | N25: =F25+G25-K25+L25+M25 -> 729445.47 | O25: =B25&"|"&D25 -> 2|LP-07
B26: 2 | C26: =Quarters!$E$5 -> Q2 2022 | D26: LP-08 | E26: Kestrel Insurance Group | F26: =N11 -> 300000 | G26: ='LP Capital Calls'!$H$26 -> 287500 | H26: ='Distribution Waterfall'!$L$5*'LP Register'!$F$11 -> 0 | I26: ='Distribution Waterfall'!$N$5*'LP Register'!$F$11 -> 0 | J26: ='Distribution Waterfall'!$T$5*'LP Register'!$F$11 -> 0 | K26: =H26+I26+J26 -> 0 | L26: =('NAV Rollforward'!$G$5+'NAV Rollforward'!$H$5-'Mgmt Fee Schedule'!$G$5)*'LP Register'!$F$11 -> 20371.227 | M26: =-('Distribution Waterfall'!$Q$5+'Distribution Waterfall'!$U$5)*'LP Register'!$F$11 -> 0 | N26: =F26+G26-K26+L26+M26 -> 607871.23 | O26: =B26&"|"&D26 -> 2|LP-08
B27: 2 | C27: =Quarters!$E$5 -> Q2 2022 | D27: LP-09 | E27: Wrenfield Family Office | F27: =N12 -> 240000 | G27: ='LP Capital Calls'!$H$27 -> 230000 | H27: ='Distribution Waterfall'!$L$5*'LP Register'!$F$12 -> 0 | I27: ='Distribution Waterfall'!$N$5*'LP Register'!$F$12 -> 0 | J27: ='Distribution Waterfall'!$T$5*'LP Register'!$F$12 -> 0 | K27: =H27+I27+J27 -> 0 | L27: =('NAV Rollforward'!$G$5+'NAV Rollforward'!$H$5-'Mgmt Fee Schedule'!$G$5)*'LP Register'!$F$12 -> 16296.982 | M27: =-('Distribution Waterfall'!$Q$5+'Distribution Waterfall'!$U$5)*'LP Register'!$F$12 -> 0 | N27: =F27+G27-K27+L27+M27 -> 486296.98 | O27: =B27&"|"&D27 -> 2|LP-09
B28: 2 | C28: =Quarters!$E$5 -> Q2 2022 | D28: LP-10 | E28: Alder Street Foundation | F28: =N13 -> 240000 | G28: ='LP Capital Calls'!$H$28 -> 230000 | H28: ='Distribution Waterfall'!$L$5*'LP Register'!$F$13 -> 0 | I28: ='Distribution Waterfall'!$N$5*'LP Register'!$F$13 -> 0 | J28: ='Distribution Waterfall'!$T$5*'LP Register'!$F$13 -> 0 | K28: =H28+I28+J28 -> 0 | L28: =('NAV Rollforward'!$G$5+'NAV Rollforward'!$H$5-'Mgmt Fee Schedule'!$G$5)*'LP Register'!$F$13 -> 16296.982 | M28: =-('Distribution Waterfall'!$Q$5+'Distribution Waterfall'!$U$5)*'LP Register'!$F$13 -> 0 | N28: =F28+G28-K28+L28+M28 -> 486296.98 | O28: =B28&"|"&D28 -> 2|LP-10
B29: 2 | C29: =Quarters!$E$5 -> Q2 2022 | D29: LP-11 | E29: Pinecrest Pension Trust | F29: =N14 -> 216000 | G29: ='LP Capital Calls'!$H$29 -> 207000 | H29: ='Distribution Waterfall'!$L$5*'LP Register'!$F$14 -> 0 | I29: ='Distribution Waterfall'!$N$5*'LP Register'!$F$14 -> 0 | J29: ='Distribution Waterfall'!$T$5*'LP Register'!$F$14 -> 0 | K29: =H29+I29+J29 -> 0 | L29: =('NAV Rollforward'!$G$5+'NAV Rollforward'!$H$5-'Mgmt Fee Schedule'!$G$5)*'LP Register'!$F$14 -> 14667.283 | M29: =-('Distribution Waterfall'!$Q$5+'Distribution Waterfall'!$U$5)*'LP Register'!$F$14 -> 0 | N29: =F29+G29-K29+L29+M29 -> 437667.28 | O29: =B29&"|"&D29 -> 2|LP-11
B30: 2 | C30: =Quarters!$E$5 -> Q2 2022 | D30: LP-12 | E30: Ivywood Capital Partners (FoF) | F30: =N15 -> 180000 | G30: ='LP Capital Calls'!$H$30 -> 172500 | H30: ='Distribution Waterfall'!$L$5*'LP Register'!$F$15 -> 0 | I30: ='Distribution Waterfall'!$N$5*'LP Register'!$F$15 -> 0 | J30: ='Distribution Waterfall'!$T$5*'LP Register'!$F$15 -> 0 | K30: =H30+I30+J30 -> 0 | L30: =('NAV Rollforward'!$G$5+'NAV Rollforward'!$H$5-'Mgmt Fee Schedule'!$G$5)*'LP Register'!$F$15 -> 12222.736 | M30: =-('Distribution Waterfall'!$Q$5+'Distribution Waterfall'!$U$5)*'LP Register'!$F$15 -> 0 | N30: =F30+G30-K30+L30+M30 -> 364722.74 | O30: =B30&"|"&D30 -> 2|LP-12
B31: 2 | C31: =Quarters!$E$5 -> Q2 2022 | D31: LP-13 | E31: Grayling Family Office | F31: =N16 -> 180000 | G31: ='LP Capital Calls'!$H$31 -> 172500 | H31: ='Distribution Waterfall'!$L$5*'LP Register'!$F$16 -> 0 | I31: ='Distribution Waterfall'!$N$5*'LP Register'!$F$16 -> 0 | J31: ='Distribution Waterfall'!$T$5*'LP Register'!$F$16 -> 0 | K31: =H31+I31+J31 -> 0 | L31: =('NAV Rollforward'!$G$5+'NAV Rollforward'!$H$5-'Mgmt Fee Schedule'!$G$5)*'LP Register'!$F$16 -> 12222.736 | M31: =-('Distribution Waterfall'!$Q$5+'Distribution Waterfall'!$U$5)*'LP Register'!$F$16 -> 0 | N31: =F31+G31-K31+L31+M31 -> 364722.74 | O31: =B31&"|"&D31 -> 2|LP-13
B32: 2 | C32: =Quarters!$E$5 -> Q2 2022 | D32: LP-14 | E32: Redstone Family Office | F32: =N17 -> 192000 | G32: ='LP Capital Calls'!$H$32 -> 184000 | H32: ='Distribution Waterfall'!$L$5*'LP Register'!$F$17 -> 0 | I32: ='Distribution Waterfall'!$N$5*'LP Register'!$F$17 -> 0 | J32: ='Distribution Waterfall'!$T$5*'LP Register'!$F$17 -> 0 | K32: =H32+I32+J32 -> 0 | L32: =('NAV Rollforward'!$G$5+'NAV Rollforward'!$H$5-'Mgmt Fee Schedule'!$G$5)*'LP Register'!$F$17 -> 13037.585 | M32: =-('Distribution Waterfall'!$Q$5+'Distribution Waterfall'!$U$5)*'LP Register'!$F$17 -> 0 | N32: =F32+G32-K32+L32+M32 -> 389037.59 | O32: =B32&"|"&D32 -> 2|LP-14
B33: 2 | C33: =Quarters!$E$5 -> Q2 2022 | D33: LP-15 | E33: Sable Foundation | F33: =N18 -> 192000 | G33: ='LP Capital Calls'!$H$33 -> 184000 | H33: ='Distribution Waterfall'!$L$5*'LP Register'!$F$18 -> 0 | I33: ='Distribution Waterfall'!$N$5*'LP Register'!$F$18 -> 0 | J33: ='Distribution Waterfall'!$T$5*'LP Register'!$F$18 -> 0 | K33: =H33+I33+J33 -> 0 | L33: =('NAV Rollforward'!$G$5+'NAV Rollforward'!$H$5-'Mgmt Fee Schedule'!$G$5)*'LP Register'!$F$18 -> 13037.585 | M33: =-('Distribution Waterfall'!$Q$5+'Distribution Waterfall'!$U$5)*'LP Register'!$F$18 -> 0 | N33: =F33+G33-K33+L33+M33 -> 389037.59 | O33: =B33&"|"&D33 -> 2|LP-15
B34: 3 | C34: =Quarters!$E$6 -> Q3 2022 | D34: LP-01 | E34: Northbridge State Pension Fund | F34: =N19 -> 1945187.9 | G34: ='LP Capital Calls'!$H$34 -> 760000 | H34: ='Distribution Waterfall'!$L$6*'LP Register'!$F$4 -> 0 | I34: ='Distribution Waterfall'!$N$6*'LP Register'!$F$4 -> 0 | J34: ='Distribution Waterfall'!$T$6*'LP Register'!$F$4 -> 0 | K34: =H34+I34+J34 -> 0 | L34: =('NAV Rollforward'!$G$6+'NAV Rollforward'!$H$6-'Mgmt Fee Schedule'!$G$6)*'LP Register'!$F$4 -> 103445.34 | M34: =-('Distribution Waterfall'!$Q$6+'Distribution Waterfall'!$U$6)*'LP Register'!$F$4 -> 0 | N34: =F34+G34-K34+L34+M34 -> 2808633.3 | O34: =B34&"|"&D34 -> 3|LP-01
B35: 3 | C35: =Quarters!$E$6 -> Q3 2022 | D35: LP-02 | E35: Meridian University Endowment | F35: =N20 -> 1458890.9 | G35: ='LP Capital Calls'!$H$35 -> 570000 | H35: ='Distribution Waterfall'!$L$6*'LP Register'!$F$5 -> 0 | I35: ='Distribution Waterfall'!$N$6*'LP Register'!$F$5 -> 0 | J35: ='Distribution Waterfall'!$T$6*'LP Register'!$F$5 -> 0 | K35: =H35+I35+J35 -> 0 | L35: =('NAV Rollforward'!$G$6+'NAV Rollforward'!$H$6-'Mgmt Fee Schedule'!$G$6)*'LP Register'!$F$5 -> 77584.004 | M35: =-('Distribution Waterfall'!$Q$6+'Distribution Waterfall'!$U$6)*'LP Register'!$F$5 -> 0 | N35: =F35+G35-K35+L35+M35 -> 2106474.9 | O35: =B35&"|"&D35 -> 3|LP-02
B36: 3 | C36: =Quarters!$E$6 -> Q3 2022 | D36: LP-03 | E36: Harborview Insurance Co. | F36: =N21 -> 1337316.7 | G36: ='LP Capital Calls'!$H$36 -> 522500 | H36: ='Distribution Waterfall'!$L$6*'LP Register'!$F$6 -> 0 | I36: ='Distribution Waterfall'!$N$6*'LP Register'!$F$6 -> 0 | J36: ='Distribution Waterfall'!$T$6*'LP Register'!$F$6 -> 0 | K36: =H36+I36+J36 -> 0 | L36: =('NAV Rollforward'!$G$6+'NAV Rollforward'!$H$6-'Mgmt Fee Schedule'!$G$6)*'LP Register'!$F$6 -> 71118.671 | M36: =-('Distribution Waterfall'!$Q$6+'Distribution Waterfall'!$U$6)*'LP Register'!$F$6 -> 0 | N36: =F36+G36-K36+L36+M36 -> 1930935.4 | O36: =B36&"|"&D36 -> 3|LP-03
B37: 3 | C37: =Quarters!$E$6 -> Q3 2022 | D37: LP-04 | E37: Cascade Partners Fund of Funds | F37: =N22 -> 1215742.5 | G37: ='LP Capital Calls'!$H$37 -> 475000 | H37: ='Distribution Waterfall'!$L$6*'LP Register'!$F$7 -> 0 | I37: ='Distribution Waterfall'!$N$6*'LP Register'!$F$7 -> 0 | J37: ='Distribution Waterfall'!$T$6*'LP Register'!$F$7 -> 0 | K37: =H37+I37+J37 -> 0 | L37: =('NAV Rollforward'!$G$6+'NAV Rollforward'!$H$6-'Mgmt Fee Schedule'!$G$6)*'LP Register'!$F$7 -> 64653.337 | M37: =-('Distribution Waterfall'!$Q$6+'Distribution Waterfall'!$U$6)*'LP Register'!$F$7 -> 0 | N37: =F37+G37-K37+L37+M37 -> 1755395.8 | O37: =B37&"|"&D37 -> 3|LP-04
B38: 3 | C38: =Quarters!$E$6 -> Q3 2022 | D38: LP-05 | E38: Elmwood Family Office | F38: =N23 -> 972593.96 | G38: ='LP Capital Calls'!$H$38 -> 380000 | H38: ='Distribution Waterfall'!$L$6*'LP Register'!$F$8 -> 0 | I38: ='Distribution Waterfall'!$N$6*'LP Register'!$F$8 -> 0 | J38: ='Distribution Waterfall'!$T$6*'LP Register'!$F$8 -> 0 | K38: =H38+I38+J38 -> 0 | L38: =('NAV Rollforward'!$G$6+'NAV Rollforward'!$H$6-'Mgmt Fee Schedule'!$G$6)*'LP Register'!$F$8 -> 51722.67 | M38: =-('Distribution Waterfall'!$Q$6+'Distribution Waterfall'!$U$6)*'LP Register'!$F$8 -> 0 | N38: =F38+G38-K38+L38+M38 -> 1404316.6 | O38: =B38&"|"&D38 -> 3|LP-05
B39: 3 | C39: =Quarters!$E$6 -> Q3 2022 | D39: LP-06 | E39: Tanager Sovereign Partners | F39: =N24 -> 972593.96 | G39: ='LP Capital Calls'!$H$39 -> 380000 | H39: ='Distribution Waterfall'!$L$6*'LP Register'!$F$9 -> 0 | I39: ='Distribution Waterfall'!$N$6*'LP Register'!$F$9 -> 0 | J39: ='Distribution Waterfall'!$T$6*'LP Register'!$F$9 -> 0 | K39: =H39+I39+J39 -> 0 | L39: =('NAV Rollforward'!$G$6+'NAV Rollforward'!$H$6-'Mgmt Fee Schedule'!$G$6)*'LP Register'!$F$9 -> 51722.67 | M39: =-('Distribution Waterfall'!$Q$6+'Distribution Waterfall'!$U$6)*'LP Register'!$F$9 -> 0 | N39: =F39+G39-K39+L39+M39 -> 1404316.6 | O39: =B39&"|"&D39 -> 3|LP-06
B40: 3 | C40: =Quarters!$E$6 -> Q3 2022 | D40: LP-07 | E40: Birchwood College Endowment | F40: =N25 -> 729445.47 | G40: ='LP Capital Calls'!$H$40 -> 285000 | H40: ='Distribution Waterfall'!$L$6*'LP Register'!$F$10 -> 0 | I40: ='Distribution Waterfall'!$N$6*'LP Register'!$F$10 -> 0 | J40: ='Distribution Waterfall'!$T$6*'LP Register'!$F$10 -> 0 | K40: =H40+I40+J40 -> 0 | L40: =('NAV Rollforward'!$G$6+'NAV Rollforward'!$H$6-'Mgmt Fee Schedule'!$G$6)*'LP Register'!$F$10 -> 38792.002 | M40: =-('Distribution Waterfall'!$Q$6+'Distribution Waterfall'!$U$6)*'LP Register'!$F$10 -> 0 | N40: =F40+G40-K40+L40+M40 -> 1053237.5 | O40: =B40&"|"&D40 -> 3|LP-07
B41: 3 | C41: =Quarters!$E$6 -> Q3 2022 | D41: LP-08 | E41: Kestrel Insurance Group | F41: =N26 -> 607871.23 | G41: ='LP Capital Calls'!$H$41 -> 237500 | H41: ='Distribution Waterfall'!$L$6*'LP Register'!$F$11 -> 0 | I41: ='Distribution Waterfall'!$N$6*'LP Register'!$F$11 -> 0 | J41: ='Distribution Waterfall'!$T$6*'LP Register'!$F$11 -> 0 | K41: =H41+I41+J41 -> 0 | L41: =('NAV Rollforward'!$G$6+'NAV Rollforward'!$H$6-'Mgmt Fee Schedule'!$G$6)*'LP Register'!$F$11 -> 32326.669 | M41: =-('Distribution Waterfall'!$Q$6+'Distribution Waterfall'!$U$6)*'LP Register'!$F$11 -> 0 | N41: =F41+G41-K41+L41+M41 -> 877697.9 | O41: =B41&"|"&D41 -> 3|LP-08
B42: 3 | C42: =Quarters!$E$6 -> Q3 2022 | D42: LP-09 | E42: Wrenfield Family Office | F42: =N27 -> 486296.98 | G42: ='LP Capital Calls'!$H$42 -> 190000 | H42: ='Distribution Waterfall'!$L$6*'LP Register'!$F$12 -> 0 | I42: ='Distribution Waterfall'!$N$6*'LP Register'!$F$12 -> 0 | J42: ='Distribution Waterfall'!$T$6*'LP Register'!$F$12 -> 0 | K42: =H42+I42+J42 -> 0 | L42: =('NAV Rollforward'!$G$6+'NAV Rollforward'!$H$6-'Mgmt Fee Schedule'!$G$6)*'LP Register'!$F$12 -> 25861.335 | M42: =-('Distribution Waterfall'!$Q$6+'Distribution Waterfall'!$U$6)*'LP Register'!$F$12 -> 0 | N42: =F42+G42-K42+L42+M42 -> 702158.32 | O42: =B42&"|"&D42 -> 3|LP-09
B43: 3 | C43: =Quarters!$E$6 -> Q3 2022 | D43: LP-10 | E43: Alder Street Foundation | F43: =N28 -> 486296.98 | G43: ='LP Capital Calls'!$H$43 -> 190000 | H43: ='Distribution Waterfall'!$L$6*'LP Register'!$F$13 -> 0 | I43: ='Distribution Waterfall'!$N$6*'LP Register'!$F$13 -> 0 | J43: ='Distribution Waterfall'!$T$6*'LP Register'!$F$13 -> 0 | K43: =H43+I43+J43 -> 0 | L43: =('NAV Rollforward'!$G$6+'NAV Rollforward'!$H$6-'Mgmt Fee Schedule'!$G$6)*'LP Register'!$F$13 -> 25861.335 | M43: =-('Distribution Waterfall'!$Q$6+'Distribution Waterfall'!$U$6)*'LP Register'!$F$13 -> 0 | N43: =F43+G43-K43+L43+M43 -> 702158.32 | O43: =B43&"|"&D43 -> 3|LP-10
B44: 3 | C44: =Quarters!$E$6 -> Q3 2022 | D44: LP-11 | E44: Pinecrest Pension Trust | F44: =N29 -> 437667.28 | G44: ='LP Capital Calls'!$H$44 -> 171000 | H44: ='Distribution Waterfall'!$L$6*'LP Register'!$F$14 -> 0 | I44: ='Distribution Waterfall'!$N$6*'LP Register'!$F$14 -> 0 | J44: ='Distribution Waterfall'!$T$6*'LP Register'!$F$14 -> 0 | K44: =H44+I44+J44 -> 0 | L44: =('NAV Rollforward'!$G$6+'NAV Rollforward'!$H$6-'Mgmt Fee Schedule'!$G$6)*'LP Register'!$F$14 -> 23275.201 | M44: =-('Distribution Waterfall'!$Q$6+'Distribution Waterfall'!$U$6)*'LP Register'!$F$14 -> 0 | N44: =F44+G44-K44+L44+M44 -> 631942.48 | O44: =B44&"|"&D44 -> 3|LP-11
B45: 3 | C45: =Quarters!$E$6 -> Q3 2022 | D45: LP-12 | E45: Ivywood Capital Partners (FoF) | F45: =N30 -> 364722.74 | G45: ='LP Capital Calls'!$H$45 -> 142500 | H45: ='Distribution Waterfall'!$L$6*'LP Register'!$F$15 -> 0 | I45: ='Distribution Waterfall'!$N$6*'LP Register'!$F$15 -> 0 | J45: ='Distribution Waterfall'!$T$6*'LP Register'!$F$15 -> 0 | K45: =H45+I45+J45 -> 0 | L45: =('NAV Rollforward'!$G$6+'NAV Rollforward'!$H$6-'Mgmt Fee Schedule'!$G$6)*'LP Register'!$F$15 -> 19396.001 | M45: =-('Distribution Waterfall'!$Q$6+'Distribution Waterfall'!$U$6)*'LP Register'!$F$15 -> 0 | N45: =F45+G45-K45+L45+M45 -> 526618.74 | O45: =B45&"|"&D45 -> 3|LP-12
B46: 3 | C46: =Quarters!$E$6 -> Q3 2022 | D46: LP-13 | E46: Grayling Family Office | F46: =N31 -> 364722.74 | G46: ='LP Capital Calls'!$H$46 -> 142500 | H46: ='Distribution Waterfall'!$L$6*'LP Register'!$F$16 -> 0 | I46: ='Distribution Waterfall'!$N$6*'LP Register'!$F$16 -> 0 | J46: ='Distribution Waterfall'!$T$6*'LP Register'!$F$16 -> 0 | K46: =H46+I46+J46 -> 0 | L46: =('NAV Rollforward'!$G$6+'NAV Rollforward'!$H$6-'Mgmt Fee Schedule'!$G$6)*'LP Register'!$F$16 -> 19396.001 | M46: =-('Distribution Waterfall'!$Q$6+'Distribution Waterfall'!$U$6)*'LP Register'!$F$16 -> 0 | N46: =F46+G46-K46+L46+M46 -> 526618.74 | O46: =B46&"|"&D46 -> 3|LP-13
B47: 3 | C47: =Quarters!$E$6 -> Q3 2022 | D47: LP-14 | E47: Redstone Family Office | F47: =N32 -> 389037.59 | G47: ='LP Capital Calls'!$H$47 -> 152000 | H47: ='Distribution Waterfall'!$L$6*'LP Register'!$F$17 -> 0 | I47: ='Distribution Waterfall'!$N$6*'LP Register'!$F$17 -> 0 | J47: ='Distribution Waterfall'!$T$6*'LP Register'!$F$17 -> 0 | K47: =H47+I47+J47 -> 0 | L47: =('NAV Rollforward'!$G$6+'NAV Rollforward'!$H$6-'Mgmt Fee Schedule'!$G$6)*'LP Register'!$F$17 -> 20689.068 | M47: =-('Distribution Waterfall'!$Q$6+'Distribution Waterfall'!$U$6)*'LP Register'!$F$17 -> 0 | N47: =F47+G47-K47+L47+M47 -> 561726.65 | O47: =B47&"|"&D47 -> 3|LP-14
B48: 3 | C48: =Quarters!$E$6 -> Q3 2022 | D48: LP-15 | E48: Sable Foundation | F48: =N33 -> 389037.59 | G48: ='LP Capital Calls'!$H$48 -> 152000 | H48: ='Distribution Waterfall'!$L$6*'LP Register'!$F$18 -> 0 | I48: ='Distribution Waterfall'!$N$6*'LP Register'!$F$18 -> 0 | J48: ='Distribution Waterfall'!$T$6*'LP Register'!$F$18 -> 0 | K48: =H48+I48+J48 -> 0 | L48: =('NAV Rollforward'!$G$6+'NAV Rollforward'!$H$6-'Mgmt Fee Schedule'!$G$6)*'LP Register'!$F$18 -> 20689.068 | M48: =-('Distribution Waterfall'!$Q$6+'Distribution Waterfall'!$U$6)*'LP Register'!$F$18 -> 0 | N48: =F48+G48-K48+L48+M48 -> 561726.65 | O48: =B48&"|"&D48 -> 3|LP-15
B49: 4 | C49: =Quarters!$E$7 -> Q4 2022 | D49: LP-01 | E49: Northbridge State Pension Fund | F49: =N34 -> 2808633.3 | G49: ='LP Capital Calls'!$H$49 -> 840000 | H49: ='Distribution Waterfall'!$L$7*'LP Register'!$F$4 -> 0 | I49: ='Distribution Waterfall'!$N$7*'LP Register'!$F$4 -> 0 | J49: ='Distribution Waterfall'!$T$7*'LP Register'!$F$4 -> 0 | K49: =H49+I49+J49 -> 0 | L49: =('NAV Rollforward'!$G$7+'NAV Rollforward'!$H$7-'Mgmt Fee Schedule'!$G$7)*'LP Register'!$F$4 -> 121382.8 | M49: =-('Distribution Waterfall'!$Q$7+'Distribution Waterfall'!$U$7)*'LP Register'!$F$4 -> 0 | N49: =F49+G49-K49+L49+M49 -> 3770016.1 | O49: =B49&"|"&D49 -> 4|LP-01
B50: 4 | C50: =Quarters!$E$7 -> Q4 2022 | D50: LP-02 | E50: Meridian University Endowment | F50: =N35 -> 2106474.9 | G50: ='LP Capital Calls'!$H$50 -> 630000 | H50: ='Distribution Waterfall'!$L$7*'LP Register'!$F$5 -> 0 | I50: ='Distribution Waterfall'!$N$7*'LP Register'!$F$5 -> 0 | J50: ='Distribution Waterfall'!$T$7*'LP Register'!$F$5 -> 0 | K50: =H50+I50+J50 -> 0 | L50: =('NAV Rollforward'!$G$7+'NAV Rollforward'!$H$7-'Mgmt Fee Schedule'!$G$7)*'LP Register'!$F$5 -> 91037.1 | M50: =-('Distribution Waterfall'!$Q$7+'Distribution Waterfall'!$U$7)*'LP Register'!$F$5 -> 0 | N50: =F50+G50-K50+L50+M50 -> 2827512 | O50: =B50&"|"&D50 -> 4|LP-02
B51: 4 | C51: =Quarters!$E$7 -> Q4 2022 | D51: LP-03 | E51: Harborview Insurance Co. | F51: =N36 -> 1930935.4 | G51: ='LP Capital Calls'!$H$51 -> 577500 | H51: ='Distribution Waterfall'!$L$7*'LP Register'!$F$6 -> 0 | I51: ='Distribution Waterfall'!$N$7*'LP Register'!$F$6 -> 0 | J51: ='Distribution Waterfall'!$T$7*'LP Register'!$F$6 -> 0 | K51: =H51+I51+J51 -> 0 | L51: =('NAV Rollforward'!$G$7+'NAV Rollforward'!$H$7-'Mgmt Fee Schedule'!$G$7)*'LP Register'!$F$6 -> 83450.675 | M51: =-('Distribution Waterfall'!$Q$7+'Distribution Waterfall'!$U$7)*'LP Register'!$F$6 -> 0 | N51: =F51+G51-K51+L51+M51 -> 2591886 | O51: =B51&"|"&D51 -> 4|LP-03
B52: 4 | C52: =Quarters!$E$7 -> Q4 2022 | D52: LP-04 | E52: Cascade Partners Fund of Funds | F52: =N37 -> 1755395.8 | G52: ='LP Capital Calls'!$H$52 -> 525000 | H52: ='Distribution Waterfall'!$L$7*'LP Register'!$F$7 -> 0 | I52: ='Distribution Waterfall'!$N$7*'LP Register'!$F$7 -> 0 | J52: ='Distribution Waterfall'!$T$7*'LP Register'!$F$7 -> 0 | K52: =H52+I52+J52 -> 0 | L52: =('NAV Rollforward'!$G$7+'NAV Rollforward'!$H$7-'Mgmt Fee Schedule'!$G$7)*'LP Register'!$F$7 -> 75864.25 | M52: =-('Distribution Waterfall'!$Q$7+'Distribution Waterfall'!$U$7)*'LP Register'!$F$7 -> 0 | N52: =F52+G52-K52+L52+M52 -> 2356260 | O52: =B52&"|"&D52 -> 4|LP-04
B53: 4 | C53: =Quarters!$E$7 -> Q4 2022 | D53: LP-05 | E53: Elmwood Family Office | F53: =N38 -> 1404316.6 | G53: ='LP Capital Calls'!$H$53 -> 420000 | H53: ='Distribution Waterfall'!$L$7*'LP Register'!$F$8 -> 0 | I53: ='Distribution Waterfall'!$N$7*'LP Register'!$F$8 -> 0 | J53: ='Distribution Waterfall'!$T$7*'LP Register'!$F$8 -> 0 | K53: =H53+I53+J53 -> 0 | L53: =('NAV Rollforward'!$G$7+'NAV Rollforward'!$H$7-'Mgmt Fee Schedule'!$G$7)*'LP Register'!$F$8 -> 60691.4 | M53: =-('Distribution Waterfall'!$Q$7+'Distribution Waterfall'!$U$7)*'LP Register'!$F$8 -> 0 | N53: =F53+G53-K53+L53+M53 -> 1885008 | O53: =B53&"|"&D53 -> 4|LP-05
B54: 4 | C54: =Quarters!$E$7 -> Q4 2022 | D54: LP-06 | E54: Tanager Sovereign Partners | F54: =N39 -> 1404316.6 | G54: ='LP Capital Calls'!$H$54 -> 420000 | H54: ='Distribution Waterfall'!$L$7*'LP Register'!$F$9 -> 0 | I54: ='Distribution Waterfall'!$N$7*'LP Register'!$F$9 -> 0 | J54: ='Distribution Waterfall'!$T$7*'LP Register'!$F$9 -> 0 | K54: =H54+I54+J54 -> 0 | L54: =('NAV Rollforward'!$G$7+'NAV Rollforward'!$H$7-'Mgmt Fee Schedule'!$G$7)*'LP Register'!$F$9 -> 60691.4 | M54: =-('Distribution Waterfall'!$Q$7+'Distribution Waterfall'!$U$7)*'LP Register'!$F$9 -> 0 | N54: =F54+G54-K54+L54+M54 -> 1885008 | O54: =B54&"|"&D54 -> 4|LP-06
B55: 4 | C55: =Quarters!$E$7 -> Q4 2022 | D55: LP-07 | E55: Birchwood College Endowment | F55: =N40 -> 1053237.5 | G55: ='LP Capital Calls'!$H$55 -> 315000 | H55: ='Distribution Waterfall'!$L$7*'LP Register'!$F$10 -> 0 | I55: ='Distribution Waterfall'!$N$7*'LP Register'!$F$10 -> 0 | J55: ='Distribution Waterfall'!$T$7*'LP Register'!$F$10 -> 0 | K55: =H55+I55+J55 -> 0 | L55: =('NAV Rollforward'!$G$7+'NAV Rollforward'!$H$7-'Mgmt Fee Schedule'!$G$7)*'LP Register'!$F$10 -> 45518.55 | M55: =-('Distribution Waterfall'!$Q$7+'Distribution Waterfall'!$U$7)*'LP Register'!$F$10 -> 0 | N55: =F55+G55-K55+L55+M55 -> 1413756 | O55: =B55&"|"&D55 -> 4|LP-07
B56: 4 | C56: =Quarters!$E$7 -> Q4 2022 | D56: LP-08 | E56: Kestrel Insurance Group | F56: =N41 -> 877697.9 | G56: ='LP Capital Calls'!$H$56 -> 262500 | H56: ='Distribution Waterfall'!$L$7*'LP Register'!$F$11 -> 0 | I56: ='Distribution Waterfall'!$N$7*'LP Register'!$F$11 -> 0 | J56: ='Distribution Waterfall'!$T$7*'LP Register'!$F$11 -> 0 | K56: =H56+I56+J56 -> 0 | L56: =('NAV Rollforward'!$G$7+'NAV Rollforward'!$H$7-'Mgmt Fee Schedule'!$G$7)*'LP Register'!$F$11 -> 37932.125 | M56: =-('Distribution Waterfall'!$Q$7+'Distribution Waterfall'!$U$7)*'LP Register'!$F$11 -> 0 | N56: =F56+G56-K56+L56+M56 -> 1178130 | O56: =B56&"|"&D56 -> 4|LP-08
B57: 4 | C57: =Quarters!$E$7 -> Q4 2022 | D57: LP-09 | E57: Wrenfield Family Office | F57: =N42 -> 702158.32 | G57: ='LP Capital Calls'!$H$57 -> 210000 | H57: ='Distribution Waterfall'!$L$7*'LP Register'!$F$12 -> 0 | I57: ='Distribution Waterfall'!$N$7*'LP Register'!$F$12 -> 0 | J57: ='Distribution Waterfall'!$T$7*'LP Register'!$F$12 -> 0 | K57: =H57+I57+J57 -> 0 | L57: =('NAV Rollforward'!$G$7+'NAV Rollforward'!$H$7-'Mgmt Fee Schedule'!$G$7)*'LP Register'!$F$12 -> 30345.7 | M57: =-('Distribution Waterfall'!$Q$7+'Distribution Waterfall'!$U$7)*'LP Register'!$F$12 -> 0 | N57: =F57+G57-K57+L57+M57 -> 942504.02 | O57: =B57&"|"&D57 -> 4|LP-09
B58: 4 | C58: =Quarters!$E$7 -> Q4 2022 | D58: LP-10 | E58: Alder Street Foundation | F58: =N43 -> 702158.32 | G58: ='LP Capital Calls'!$H$58 -> 210000 | H58: ='Distribution Waterfall'!$L$7*'LP Register'!$F$13 -> 0 | I58: ='Distribution Waterfall'!$N$7*'LP Register'!$F$13 -> 0 | J58: ='Distribution Waterfall'!$T$7*'LP Register'!$F$13 -> 0 | K58: =H58+I58+J58 -> 0 | L58: =('NAV Rollforward'!$G$7+'NAV Rollforward'!$H$7-'Mgmt Fee Schedule'!$G$7)*'LP Register'!$F$13 -> 30345.7 | M58: =-('Distribution Waterfall'!$Q$7+'Distribution Waterfall'!$U$7)*'LP Register'!$F$13 -> 0 | N58: =F58+G58-K58+L58+M58 -> 942504.02 | O58: =B58&"|"&D58 -> 4|LP-10
B59: 4 | C59: =Quarters!$E$7 -> Q4 2022 | D59: LP-11 | E59: Pinecrest Pension Trust | F59: =N44 -> 631942.48 | G59: ='LP Capital Calls'!$H$59 -> 189000 | H59: ='Distribution Waterfall'!$L$7*'LP Register'!$F$14 -> 0 | I59: ='Distribution Waterfall'!$N$7*'LP Register'!$F$14 -> 0 | J59: ='Distribution Waterfall'!$T$7*'LP Register'!$F$14 -> 0 | K59: =H59+I59+J59 -> 0 | L59: =('NAV Rollforward'!$G$7+'NAV Rollforward'!$H$7-'Mgmt Fee Schedule'!$G$7)*'LP Register'!$F$14 -> 27311.13 | M59: =-('Distribution Waterfall'!$Q$7+'Distribution Waterfall'!$U$7)*'LP Register'!$F$14 -> 0 | N59: =F59+G59-K59+L59+M59 -> 848253.61 | O59: =B59&"|"&D59 -> 4|LP-11
B60: 4 | C60: =Quarters!$E$7 -> Q4 2022 | D60: LP-12 | E60: Ivywood Capital Partners (FoF) | F60: =N45 -> 526618.74 | G60: ='LP Capital Calls'!$H$60 -> 157500 | H60: ='Distribution Waterfall'!$L$7*'LP Register'!$F$15 -> 0 | I60: ='Distribution Waterfall'!$N$7*'LP Register'!$F$15 -> 0 | J60: ='Distribution Waterfall'!$T$7*'LP Register'!$F$15 -> 0 | K60: =H60+I60+J60 -> 0 | L60: =('NAV Rollforward'!$G$7+'NAV Rollforward'!$H$7-'Mgmt Fee Schedule'!$G$7)*'LP Register'!$F$15 -> 22759.275 | M60: =-('Distribution Waterfall'!$Q$7+'Distribution Waterfall'!$U$7)*'LP Register'!$F$15 -> 0 | N60: =F60+G60-K60+L60+M60 -> 706878.01 | O60: =B60&"|"&D60 -> 4|LP-12
B61: 4 | C61: =Quarters!$E$7 -> Q4 2022 | D61: LP-13 | E61: Grayling Family Office | F61: =N46 -> 526618.74 | G61: ='LP Capital Calls'!$H$61 -> 157500 | H61: ='Distribution Waterfall'!$L$7*'LP Register'!$F$16 -> 0 | I61: ='Distribution Waterfall'!$N$7*'LP Register'!$F$16 -> 0 | J61: ='Distribution Waterfall'!$T$7*'LP Register'!$F$16 -> 0 | K61: =H61+I61+J61 -> 0 | L61: =('NAV Rollforward'!$G$7+'NAV Rollforward'!$H$7-'Mgmt Fee Schedule'!$G$7)*'LP Register'!$F$16 -> 22759.275 | M61: =-('Distribution Waterfall'!$Q$7+'Distribution Waterfall'!$U$7)*'LP Register'!$F$16 -> 0 | N61: =F61+G61-K61+L61+M61 -> 706878.01 | O61: =B61&"|"&D61 -> 4|LP-13
B62: 4 | C62: =Quarters!$E$7 -> Q4 2022 | D62: LP-14 | E62: Redstone Family Office | F62: =N47 -> 561726.65 | G62: ='LP Capital Calls'!$H$62 -> 168000 | H62: ='Distribution Waterfall'!$L$7*'LP Register'!$F$17 -> 0 | I62: ='Distribution Waterfall'!$N$7*'LP Register'!$F$17 -> 0 | J62: ='Distribution Waterfall'!$T$7*'LP Register'!$F$17 -> 0 | K62: =H62+I62+J62 -> 0 | L62: =('NAV Rollforward'!$G$7+'NAV Rollforward'!$H$7-'Mgmt Fee Schedule'!$G$7)*'LP Register'!$F$17 -> 24276.56 | M62: =-('Distribution Waterfall'!$Q$7+'Distribution Waterfall'!$U$7)*'LP Register'!$F$17 -> 0 | N62: =F62+G62-K62+L62+M62 -> 754003.21 | O62: =B62&"|"&D62 -> 4|LP-14
B63: 4 | C63: =Quarters!$E$7 -> Q4 2022 | D63: LP-15 | E63: Sable Foundation | F63: =N48 -> 561726.65 | G63: ='LP Capital Calls'!$H$63 -> 168000 | H63: ='Distribution Waterfall'!$L$7*'LP Register'!$F$18 -> 0 | I63: ='Distribution Waterfall'!$N$7*'LP Register'!$F$18 -> 0 | J63: ='Distribution Waterfall'!$T$7*'LP Register'!$F$18 -> 0 | K63: =H63+I63+J63 -> 0 | L63: =('NAV Rollforward'!$G$7+'NAV Rollforward'!$H$7-'Mgmt Fee Schedule'!$G$7)*'LP Register'!$F$18 -> 24276.56 | M63: =-('Distribution Waterfall'!$Q$7+'Distribution Waterfall'!$U$7)*'LP Register'!$F$18 -> 0 | N63: =F63+G63-K63+L63+M63 -> 754003.21 | O63: =B63&"|"&D63 -> 4|LP-15
B64: 5 | C64: =Quarters!$E$8 -> Q1 2023 | D64: LP-01 | E64: Northbridge State Pension Fund | F64: =N49 -> 3770016.1 | G64: ='LP Capital Calls'!$H$64 -> 680000 | H64: ='Distribution Waterfall'!$L$8*'LP Register'!$F$4 -> 0 | I64: ='Distribution Waterfall'!$N$8*'LP Register'!$F$4 -> 0 | J64: ='Distribution Waterfall'!$T$8*'LP Register'!$F$4 -> 0 | K64: =H64+I64+J64 -> 0 | L64: =('NAV Rollforward'!$G$8+'NAV Rollforward'!$H$8-'Mgmt Fee Schedule'!$G$8)*'LP Register'!$F$4 -> 197757.9 | M64: =-('Distribution Waterfall'!$Q$8+'Distribution Waterfall'!$U$8)*'LP Register'!$F$4 -> 0 | N64: =F64+G64-K64+L64+M64 -> 4647774 | O64: =B64&"|"&D64 -> 5|LP-01
B65: 5 | C65: =Quarters!$E$8 -> Q1 2023 | D65: LP-02 | E65: Meridian University Endowment | F65: =N50 -> 2827512 | G65: ='LP Capital Calls'!$H$65 -> 510000 | H65: ='Distribution Waterfall'!$L$8*'LP Register'!$F$5 -> 0 | I65: ='Distribution Waterfall'!$N$8*'LP Register'!$F$5 -> 0 | J65: ='Distribution Waterfall'!$T$8*'LP Register'!$F$5 -> 0 | K65: =H65+I65+J65 -> 0 | L65: =('NAV Rollforward'!$G$8+'NAV Rollforward'!$H$8-'Mgmt Fee Schedule'!$G$8)*'LP Register'!$F$5 -> 148318.42 | M65: =-('Distribution Waterfall'!$Q$8+'Distribution Waterfall'!$U$8)*'LP Register'!$F$5 -> 0 | N65: =F65+G65-K65+L65+M65 -> 3485830.5 | O65: =B65&"|"&D65 -> 5|LP-02
B66: 5 | C66: =Quarters!$E$8 -> Q1 2023 | D66: LP-03 | E66: Harborview Insurance Co. | F66: =N51 -> 2591886 | G66: ='LP Capital Calls'!$H$66 -> 467500 | H66: ='Distribution Waterfall'!$L$8*'LP Register'!$F$6 -> 0 | I66: ='Distribution Waterfall'!$N$8*'LP Register'!$F$6 -> 0 | J66: ='Distribution Waterfall'!$T$8*'LP Register'!$F$6 -> 0 | K66: =H66+I66+J66 -> 0 | L66: =('NAV Rollforward'!$G$8+'NAV Rollforward'!$H$8-'Mgmt Fee Schedule'!$G$8)*'LP Register'!$F$6 -> 135958.55 | M66: =-('Distribution Waterfall'!$Q$8+'Distribution Waterfall'!$U$8)*'LP Register'!$F$6 -> 0 | N66: =F66+G66-K66+L66+M66 -> 3195344.6 | O66: =B66&"|"&D66 -> 5|LP-03
B67: 5 | C67: =Quarters!$E$8 -> Q1 2023 | D67: LP-04 | E67: Cascade Partners Fund of Funds | F67: =N52 -> 2356260 | G67: ='LP Capital Calls'!$H$67 -> 425000 | H67: ='Distribution Waterfall'!$L$8*'LP Register'!$F$7 -> 0 | I67: ='Distribution Waterfall'!$N$8*'LP Register'!$F$7 -> 0 | J67: ='Distribution Waterfall'!$T$8*'LP Register'!$F$7 -> 0 | K67: =H67+I67+J67 -> 0 | L67: =('NAV Rollforward'!$G$8+'NAV Rollforward'!$H$8-'Mgmt Fee Schedule'!$G$8)*'LP Register'!$F$7 -> 123598.68 | M67: =-('Distribution Waterfall'!$Q$8+'Distribution Waterfall'!$U$8)*'LP Register'!$F$7 -> 0 | N67: =F67+G67-K67+L67+M67 -> 2904858.7 | O67: =B67&"|"&D67 -> 5|LP-04
B68: 5 | C68: =Quarters!$E$8 -> Q1 2023 | D68: LP-05 | E68: Elmwood Family Office | F68: =N53 -> 1885008 | G68: ='LP Capital Calls'!$H$68 -> 340000 | H68: ='Distribution Waterfall'!$L$8*'LP Register'!$F$8 -> 0 | I68: ='Distribution Waterfall'!$N$8*'LP Register'!$F$8 -> 0 | J68: ='Distribution Waterfall'!$T$8*'LP Register'!$F$8 -> 0 | K68: =H68+I68+J68 -> 0 | L68: =('NAV Rollforward'!$G$8+'NAV Rollforward'!$H$8-'Mgmt Fee Schedule'!$G$8)*'LP Register'!$F$8 -> 98878.948 | M68: =-('Distribution Waterfall'!$Q$8+'Distribution Waterfall'!$U$8)*'LP Register'!$F$8 -> 0 | N68: =F68+G68-K68+L68+M68 -> 2323887 | O68: =B68&"|"&D68 -> 5|LP-05
B69: 5 | C69: =Quarters!$E$8 -> Q1 2023 | D69: LP-06 | E69: Tanager Sovereign Partners | F69: =N54 -> 1885008 | G69: ='LP Capital Calls'!$H$69 -> 340000 | H69: ='Distribution Waterfall'!$L$8*'LP Register'!$F$9 -> 0 | I69: ='Distribution Waterfall'!$N$8*'LP Register'!$F$9 -> 0 | J69: ='Distribution Waterfall'!$T$8*'LP Register'!$F$9 -> 0 | K69: =H69+I69+J69 -> 0 | L69: =('NAV Rollforward'!$G$8+'NAV Rollforward'!$H$8-'Mgmt Fee Schedule'!$G$8)*'LP Register'!$F$9 -> 98878.948 | M69: =-('Distribution Waterfall'!$Q$8+'Distribution Waterfall'!$U$8)*'LP Register'!$F$9 -> 0 | N69: =F69+G69-K69+L69+M69 -> 2323887 | O69: =B69&"|"&D69 -> 5|LP-06
B70: 5 | C70: =Quarters!$E$8 -> Q1 2023 | D70: LP-07 | E70: Birchwood College Endowment | F70: =N55 -> 1413756 | G70: ='LP Capital Calls'!$H$70 -> 255000 | H70: ='Distribution Waterfall'!$L$8*'LP Register'!$F$10 -> 0 | I70: ='Distribution Waterfall'!$N$8*'LP Register'!$F$10 -> 0 | J70: ='Distribution Waterfall'!$T$8*'LP Register'!$F$10 -> 0 | K70: =H70+I70+J70 -> 0 | L70: =('NAV Rollforward'!$G$8+'NAV Rollforward'!$H$8-'Mgmt Fee Schedule'!$G$8)*'LP Register'!$F$10 -> 74159.211 | M70: =-('Distribution Waterfall'!$Q$8+'Distribution Waterfall'!$U$8)*'LP Register'!$F$10 -> 0 | N70: =F70+G70-K70+L70+M70 -> 1742915.2 | O70: =B70&"|"&D70 -> 5|LP-07
B71: 5 | C71: =Quarters!$E$8 -> Q1 2023 | D71: LP-08 | E71: Kestrel Insurance Group | F71: =N56 -> 1178130 | G71: ='LP Capital Calls'!$H$71 -> 212500 | H71: ='Distribution Waterfall'!$L$8*'LP Register'!$F$11 -> 0 | I71: ='Distribution Waterfall'!$N$8*'LP Register'!$F$11 -> 0 | J71: ='Distribution Waterfall'!$T$8*'LP Register'!$F$11 -> 0 | K71: =H71+I71+J71 -> 0 | L71: =('NAV Rollforward'!$G$8+'NAV Rollforward'!$H$8-'Mgmt Fee Schedule'!$G$8)*'LP Register'!$F$11 -> 61799.343 | M71: =-('Distribution Waterfall'!$Q$8+'Distribution Waterfall'!$U$8)*'LP Register'!$F$11 -> 0 | N71: =F71+G71-K71+L71+M71 -> 1452429.4 | O71: =B71&"|"&D71 -> 5|LP-08
B72: 5 | C72: =Quarters!$E$8 -> Q1 2023 | D72: LP-09 | E72: Wrenfield Family Office | F72: =N57 -> 942504.02 | G72: ='LP Capital Calls'!$H$72 -> 170000 | H72: ='Distribution Waterfall'!$L$8*'LP Register'!$F$12 -> 0 | I72: ='Distribution Waterfall'!$N$8*'LP Register'!$F$12 -> 0 | J72: ='Distribution Waterfall'!$T$8*'LP Register'!$F$12 -> 0 | K72: =H72+I72+J72 -> 0 | L72: =('NAV Rollforward'!$G$8+'NAV Rollforward'!$H$8-'Mgmt Fee Schedule'!$G$8)*'LP Register'!$F$12 -> 49439.474 | M72: =-('Distribution Waterfall'!$Q$8+'Distribution Waterfall'!$U$8)*'LP Register'!$F$12 -> 0 | N72: =F72+G72-K72+L72+M72 -> 1161943.5 | O72: =B72&"|"&D72 -> 5|LP-09
B73: 5 | C73: =Quarters!$E$8 -> Q1 2023 | D73: LP-10 | E73: Alder Street Foundation | F73: =N58 -> 942504.02 | G73: ='LP Capital Calls'!$H$73 -> 170000 | H73: ='Distribution Waterfall'!$L$8*'LP Register'!$F$13 -> 0 | I73: ='Distribution Waterfall'!$N$8*'LP Register'!$F$13 -> 0 | J73: ='Distribution Waterfall'!$T$8*'LP Register'!$F$13 -> 0 | K73: =H73+I73+J73 -> 0 | L73: =('NAV Rollforward'!$G$8+'NAV Rollforward'!$H$8-'Mgmt Fee Schedule'!$G$8)*'LP Register'!$F$13 -> 49439.474 | M73: =-('Distribution Waterfall'!$Q$8+'Distribution Waterfall'!$U$8)*'LP Register'!$F$13 -> 0 | N73: =F73+G73-K73+L73+M73 -> 1161943.5 | O73: =B73&"|"&D73 -> 5|LP-10
B74: 5 | C74: =Quarters!$E$8 -> Q1 2023 | D74: LP-11 | E74: Pinecrest Pension Trust | F74: =N59 -> 848253.61 | G74: ='LP Capital Calls'!$H$74 -> 153000 | H74: ='Distribution Waterfall'!$L$8*'LP Register'!$F$14 -> 0 | I74: ='Distribution Waterfall'!$N$8*'LP Register'!$F$14 -> 0 | J74: ='Distribution Waterfall'!$T$8*'LP Register'!$F$14 -> 0 | K74: =H74+I74+J74 -> 0 | L74: =('NAV Rollforward'!$G$8+'NAV Rollforward'!$H$8-'Mgmt Fee Schedule'!$G$8)*'LP Register'!$F$14 -> 44495.527 | M74: =-('Distribution Waterfall'!$Q$8+'Distribution Waterfall'!$U$8)*'LP Register'!$F$14 -> 0 | N74: =F74+G74-K74+L74+M74 -> 1045749.1 | O74: =B74&"|"&D74 -> 5|LP-11
B75: 5 | C75: =Quarters!$E$8 -> Q1 2023 | D75: LP-12 | E75: Ivywood Capital Partners (FoF) | F75: =N60 -> 706878.01 | G75: ='LP Capital Calls'!$H$75 -> 127500 | H75: ='Distribution Waterfall'!$L$8*'LP Register'!$F$15 -> 0 | I75: ='Distribution Waterfall'!$N$8*'LP Register'!$F$15 -> 0 | J75: ='Distribution Waterfall'!$T$8*'LP Register'!$F$15 -> 0 | K75: =H75+I75+J75 -> 0 | L75: =('NAV Rollforward'!$G$8+'NAV Rollforward'!$H$8-'Mgmt Fee Schedule'!$G$8)*'LP Register'!$F$15 -> 37079.605 | M75: =-('Distribution Waterfall'!$Q$8+'Distribution Waterfall'!$U$8)*'LP Register'!$F$15 -> 0 | N75: =F75+G75-K75+L75+M75 -> 871457.62 | O75: =B75&"|"&D75 -> 5|LP-12
B76: 5 | C76: =Quarters!$E$8 -> Q1 2023 | D76: LP-13 | E76: Grayling Family Office | F76: =N61 -> 706878.01 | G76: ='LP Capital Calls'!$H$76 -> 127500 | H76: ='Distribution Waterfall'!$L$8*'LP Register'!$F$16 -> 0 | I76: ='Distribution Waterfall'!$N$8*'LP Register'!$F$16 -> 0 | J76: ='Distribution Waterfall'!$T$8*'LP Register'!$F$16 -> 0 | K76: =H76+I76+J76 -> 0 | L76: =('NAV Rollforward'!$G$8+'NAV Rollforward'!$H$8-'Mgmt Fee Schedule'!$G$8)*'LP Register'!$F$16 -> 37079.605 | M76: =-('Distribution Waterfall'!$Q$8+'Distribution Waterfall'!$U$8)*'LP Register'!$F$16 -> 0 | N76: =F76+G76-K76+L76+M76 -> 871457.62 | O76: =B76&"|"&D76 -> 5|LP-13
B77: 5 | C77: =Quarters!$E$8 -> Q1 2023 | D77: LP-14 | E77: Redstone Family Office | F77: =N62 -> 754003.21 | G77: ='LP Capital Calls'!$H$77 -> 136000 | H77: ='Distribution Waterfall'!$L$8*'LP Register'!$F$17 -> 0 | I77: ='Distribution Waterfall'!$N$8*'LP Register'!$F$17 -> 0 | J77: ='Distribution Waterfall'!$T$8*'LP Register'!$F$17 -> 0 | K77: =H77+I77+J77 -> 0 | L77: =('NAV Rollforward'!$G$8+'NAV Rollforward'!$H$8-'Mgmt Fee Schedule'!$G$8)*'LP Register'!$F$17 -> 39551.579 | M77: =-('Distribution Waterfall'!$Q$8+'Distribution Waterfall'!$U$8)*'LP Register'!$F$17 -> 0 | N77: =F77+G77-K77+L77+M77 -> 929554.79 | O77: =B77&"|"&D77 -> 5|LP-14
B78: 5 | C78: =Quarters!$E$8 -> Q1 2023 | D78: LP-15 | E78: Sable Foundation | F78: =N63 -> 754003.21 | G78: ='LP Capital Calls'!$H$78 -> 136000 | H78: ='Distribution Waterfall'!$L$8*'LP Register'!$F$18 -> 0 | I78: ='Distribution Waterfall'!$N$8*'LP Register'!$F$18 -> 0 | J78: ='Distribution Waterfall'!$T$8*'LP Register'!$F$18 -> 0 | K78: =H78+I78+J78 -> 0 | L78: =('NAV Rollforward'!$G$8+'NAV Rollforward'!$H$8-'Mgmt Fee Schedule'!$G$8)*'LP Register'!$F$18 -> 39551.579 | M78: =-('Distribution Waterfall'!$Q$8+'Distribution Waterfall'!$U$8)*'LP Register'!$F$18 -> 0 | N78: =F78+G78-K78+L78+M78 -> 929554.79 | O78: =B78&"|"&D78 -> 5|LP-15
B79: 6 | C79: =Quarters!$E$9 -> Q2 2023 | D79: LP-01 | E79: Northbridge State Pension Fund | F79: =N64 -> 4647774 | G79: ='LP Capital Calls'!$H$79 -> 840000 | H79: ='Distribution Waterfall'!$L$9*'LP Register'!$F$4 -> 0 | I79: ='Distribution Waterfall'!$N$9*'LP Register'!$F$4 -> 0 | J79: ='Distribution Waterfall'!$T$9*'LP Register'!$F$4 -> 0 | K79: =H79+I79+J79 -> 0 | L79: =('NAV Rollforward'!$G$9+'NAV Rollforward'!$H$9-'Mgmt Fee Schedule'!$G$9)*'LP Register'!$F$4 -> 146209.68 | M79: =-('Distribution Waterfall'!$Q$9+'Distribution Waterfall'!$U$9)*'LP Register'!$F$4 -> 0 | N79: =F79+G79-K79+L79+M79 -> 5633983.6 | O79: =B79&"|"&D79 -> 6|LP-01
B80: 6 | C80: =Quarters!$E$9 -> Q2 2023 | D80: LP-02 | E80: Meridian University Endowment | F80: =N65 -> 3485830.5 | G80: ='LP Capital Calls'!$H$80 -> 630000 | H80: ='Distribution Waterfall'!$L$9*'LP Register'!$F$5 -> 0 | I80: ='Distribution Waterfall'!$N$9*'LP Register'!$F$5 -> 0 | J80: ='Distribution Waterfall'!$T$9*'LP Register'!$F$5 -> 0 | K80: =H80+I80+J80 -> 0 | L80: =('NAV Rollforward'!$G$9+'NAV Rollforward'!$H$9-'Mgmt Fee Schedule'!$G$9)*'LP Register'!$F$5 -> 109657.26 | M80: =-('Distribution Waterfall'!$Q$9+'Distribution Waterfall'!$U$9)*'LP Register'!$F$5 -> 0 | N80: =F80+G80-K80+L80+M80 -> 4225487.7 | O80: =B80&"|"&D80 -> 6|LP-02
B81: 6 | C81: =Quarters!$E$9 -> Q2 2023 | D81: LP-03 | E81: Harborview Insurance Co. | F81: =N66 -> 3195344.6 | G81: ='LP Capital Calls'!$H$81 -> 577500 | H81: ='Distribution Waterfall'!$L$9*'LP Register'!$F$6 -> 0 | I81: ='Distribution Waterfall'!$N$9*'LP Register'!$F$6 -> 0 | J81: ='Distribution Waterfall'!$T$9*'LP Register'!$F$6 -> 0 | K81: =H81+I81+J81 -> 0 | L81: =('NAV Rollforward'!$G$9+'NAV Rollforward'!$H$9-'Mgmt Fee Schedule'!$G$9)*'LP Register'!$F$6 -> 100519.16 | M81: =-('Distribution Waterfall'!$Q$9+'Distribution Waterfall'!$U$9)*'LP Register'!$F$6 -> 0 | N81: =F81+G81-K81+L81+M81 -> 3873363.8 | O81: =B81&"|"&D81 -> 6|LP-03
B82: 6 | C82: =Quarters!$E$9 -> Q2 2023 | D82: LP-04 | E82: Cascade Partners Fund of Funds | F82: =N67 -> 2904858.7 | G82: ='LP Capital Calls'!$H$82 -> 525000 | H82: ='Distribution Waterfall'!$L$9*'LP Register'!$F$7 -> 0 | I82: ='Distribution Waterfall'!$N$9*'LP Register'!$F$7 -> 0 | J82: ='Distribution Waterfall'!$T$9*'LP Register'!$F$7 -> 0 | K82: =H82+I82+J82 -> 0 | L82: =('NAV Rollforward'!$G$9+'NAV Rollforward'!$H$9-'Mgmt Fee Schedule'!$G$9)*'LP Register'!$F$7 -> 91381.053 | M82: =-('Distribution Waterfall'!$Q$9+'Distribution Waterfall'!$U$9)*'LP Register'!$F$7 -> 0 | N82: =F82+G82-K82+L82+M82 -> 3521239.8 | O82: =B82&"|"&D82 -> 6|LP-04
B83: 6 | C83: =Quarters!$E$9 -> Q2 2023 | D83: LP-05 | E83: Elmwood Family Office | F83: =N68 -> 2323887 | G83: ='LP Capital Calls'!$H$83 -> 420000 | H83: ='Distribution Waterfall'!$L$9*'LP Register'!$F$8 -> 0 | I83: ='Distribution Waterfall'!$N$9*'LP Register'!$F$8 -> 0 | J83: ='Distribution Waterfall'!$T$9*'LP Register'!$F$8 -> 0 | K83: =H83+I83+J83 -> 0 | L83: =('NAV Rollforward'!$G$9+'NAV Rollforward'!$H$9-'Mgmt Fee Schedule'!$G$9)*'LP Register'!$F$8 -> 73104.842 | M83: =-('Distribution Waterfall'!$Q$9+'Distribution Waterfall'!$U$9)*'LP Register'!$F$8 -> 0 | N83: =F83+G83-K83+L83+M83 -> 2816991.8 | O83: =B83&"|"&D83 -> 6|LP-05
B84: 6 | C84: =Quarters!$E$9 -> Q2 2023 | D84: LP-06 | E84: Tanager Sovereign Partners | F84: =N69 -> 2323887 | G84: ='LP Capital Calls'!$H$84 -> 420000 | H84: ='Distribution Waterfall'!$L$9*'LP Register'!$F$9 -> 0 | I84: ='Distribution Waterfall'!$N$9*'LP Register'!$F$9 -> 0 | J84: ='Distribution Waterfall'!$T$9*'LP Register'!$F$9 -> 0 | K84: =H84+I84+J84 -> 0 | L84: =('NAV Rollforward'!$G$9+'NAV Rollforward'!$H$9-'Mgmt Fee Schedule'!$G$9)*'LP Register'!$F$9 -> 73104.842 | M84: =-('Distribution Waterfall'!$Q$9+'Distribution Waterfall'!$U$9)*'LP Register'!$F$9 -> 0 | N84: =F84+G84-K84+L84+M84 -> 2816991.8 | O84: =B84&"|"&D84 -> 6|LP-06
B85: 6 | C85: =Quarters!$E$9 -> Q2 2023 | D85: LP-07 | E85: Birchwood College Endowment | F85: =N70 -> 1742915.2 | G85: ='LP Capital Calls'!$H$85 -> 315000 | H85: ='Distribution Waterfall'!$L$9*'LP Register'!$F$10 -> 0 | I85: ='Distribution Waterfall'!$N$9*'LP Register'!$F$10 -> 0 | J85: ='Distribution Waterfall'!$T$9*'LP Register'!$F$10 -> 0 | K85: =H85+I85+J85 -> 0 | L85: =('NAV Rollforward'!$G$9+'NAV Rollforward'!$H$9-'Mgmt Fee Schedule'!$G$9)*'LP Register'!$F$10 -> 54828.632 | M85: =-('Distribution Waterfall'!$Q$9+'Distribution Waterfall'!$U$9)*'LP Register'!$F$10 -> 0 | N85: =F85+G85-K85+L85+M85 -> 2112743.9 | O85: =B85&"|"&D85 -> 6|LP-07
B86: 6 | C86: =Quarters!$E$9 -> Q2 2023 | D86: LP-08 | E86: Kestrel Insurance Group | F86: =N71 -> 1452429.4 | G86: ='LP Capital Calls'!$H$86 -> 262500 | H86: ='Distribution Waterfall'!$L$9*'LP Register'!$F$11 -> 0 | I86: ='Distribution Waterfall'!$N$9*'LP Register'!$F$11 -> 0 | J86: ='Distribution Waterfall'!$T$9*'LP Register'!$F$11 -> 0 | K86: =H86+I86+J86 -> 0 | L86: =('NAV Rollforward'!$G$9+'NAV Rollforward'!$H$9-'Mgmt Fee Schedule'!$G$9)*'LP Register'!$F$11 -> 45690.526 | M86: =-('Distribution Waterfall'!$Q$9+'Distribution Waterfall'!$U$9)*'LP Register'!$F$11 -> 0 | N86: =F86+G86-K86+L86+M86 -> 1760619.9 | O86: =B86&"|"&D86 -> 6|LP-08
B87: 6 | C87: =Quarters!$E$9 -> Q2 2023 | D87: LP-09 | E87: Wrenfield Family Office | F87: =N72 -> 1161943.5 | G87: ='LP Capital Calls'!$H$87 -> 210000 | H87: ='Distribution Waterfall'!$L$9*'LP Register'!$F$12 -> 0 | I87: ='Distribution Waterfall'!$N$9*'LP Register'!$F$12 -> 0 | J87: ='Distribution Waterfall'!$T$9*'LP Register'!$F$12 -> 0 | K87: =H87+I87+J87 -> 0 | L87: =('NAV Rollforward'!$G$9+'NAV Rollforward'!$H$9-'Mgmt Fee Schedule'!$G$9)*'LP Register'!$F$12 -> 36552.421 | M87: =-('Distribution Waterfall'!$Q$9+'Distribution Waterfall'!$U$9)*'LP Register'!$F$12 -> 0 | N87: =F87+G87-K87+L87+M87 -> 1408495.9 | O87: =B87&"|"&D87 -> 6|LP-09
B88: 6 | C88: =Quarters!$E$9 -> Q2 2023 | D88: LP-10 | E88: Alder Street Foundation | F88: =N73 -> 1161943.5 | G88: ='LP Capital Calls'!$H$88 -> 210000 | H88: ='Distribution Waterfall'!$L$9*'LP Register'!$F$13 -> 0 | I88: ='Distribution Waterfall'!$N$9*'LP Register'!$F$13 -> 0 | J88: ='Distribution Waterfall'!$T$9*'LP Register'!$F$13 -> 0 | K88: =H88+I88+J88 -> 0 | L88: =('NAV Rollforward'!$G$9+'NAV Rollforward'!$H$9-'Mgmt Fee Schedule'!$G$9)*'LP Register'!$F$13 -> 36552.421 | M88: =-('Distribution Waterfall'!$Q$9+'Distribution Waterfall'!$U$9)*'LP Register'!$F$13 -> 0 | N88: =F88+G88-K88+L88+M88 -> 1408495.9 | O88: =B88&"|"&D88 -> 6|LP-10
B89: 6 | C89: =Quarters!$E$9 -> Q2 2023 | D89: LP-11 | E89: Pinecrest Pension Trust | F89: =N74 -> 1045749.1 | G89: ='LP Capital Calls'!$H$89 -> 189000 | H89: ='Distribution Waterfall'!$L$9*'LP Register'!$F$14 -> 0 | I89: ='Distribution Waterfall'!$N$9*'LP Register'!$F$14 -> 0 | J89: ='Distribution Waterfall'!$T$9*'LP Register'!$F$14 -> 0 | K89: =H89+I89+J89 -> 0 | L89: =('NAV Rollforward'!$G$9+'NAV Rollforward'!$H$9-'Mgmt Fee Schedule'!$G$9)*'LP Register'!$F$14 -> 32897.179 | M89: =-('Distribution Waterfall'!$Q$9+'Distribution Waterfall'!$U$9)*'LP Register'!$F$14 -> 0 | N89: =F89+G89-K89+L89+M89 -> 1267646.3 | O89: =B89&"|"&D89 -> 6|LP-11
B90: 6 | C90: =Quarters!$E$9 -> Q2 2023 | D90: LP-12 | E90: Ivywood Capital Partners (FoF) | F90: =N75 -> 871457.62 | G90: ='LP Capital Calls'!$H$90 -> 157500 | H90: ='Distribution Waterfall'!$L$9*'LP Register'!$F$15 -> 0 | I90: ='Distribution Waterfall'!$N$9*'LP Register'!$F$15 -> 0 | J90: ='Distribution Waterfall'!$T$9*'LP Register'!$F$15 -> 0 | K90: =H90+I90+J90 -> 0 | L90: =('NAV Rollforward'!$G$9+'NAV Rollforward'!$H$9-'Mgmt Fee Schedule'!$G$9)*'LP Register'!$F$15 -> 27414.316 | M90: =-('Distribution Waterfall'!$Q$9+'Distribution Waterfall'!$U$9)*'LP Register'!$F$15 -> 0 | N90: =F90+G90-K90+L90+M90 -> 1056371.9 | O90: =B90&"|"&D90 -> 6|LP-12
B91: 6 | C91: =Quarters!$E$9 -> Q2 2023 | D91: LP-13 | E91: Grayling Family Office | F91: =N76 -> 871457.62 | G91: ='LP Capital Calls'!$H$91 -> 157500 | H91: ='Distribution Waterfall'!$L$9*'LP Register'!$F$16 -> 0 | I91: ='Distribution Waterfall'!$N$9*'LP Register'!$F$16 -> 0 | J91: ='Distribution Waterfall'!$T$9*'LP Register'!$F$16 -> 0 | K91: =H91+I91+J91 -> 0 | L91: =('NAV Rollforward'!$G$9+'NAV Rollforward'!$H$9-'Mgmt Fee Schedule'!$G$9)*'LP Register'!$F$16 -> 27414.316 | M91: =-('Distribution Waterfall'!$Q$9+'Distribution Waterfall'!$U$9)*'LP Register'!$F$16 -> 0 | N91: =F91+G91-K91+L91+M91 -> 1056371.9 | O91: =B91&"|"&D91 -> 6|LP-13
B92: 6 | C92: =Quarters!$E$9 -> Q2 2023 | D92: LP-14 | E92: Redstone Family Office | F92: =N77 -> 929554.79 | G92: ='LP Capital Calls'!$H$92 -> 168000 | H92: ='Distribution Waterfall'!$L$9*'LP Register'!$F$17 -> 0 | I92: ='Distribution Waterfall'!$N$9*'LP Register'!$F$17 -> 0 | J92: ='Distribution Waterfall'!$T$9*'LP Register'!$F$17 -> 0 | K92: =H92+I92+J92 -> 0 | L92: =('NAV Rollforward'!$G$9+'NAV Rollforward'!$H$9-'Mgmt Fee Schedule'!$G$9)*'LP Register'!$F$17 -> 29241.937 | M92: =-('Distribution Waterfall'!$Q$9+'Distribution Waterfall'!$U$9)*'LP Register'!$F$17 -> 0 | N92: =F92+G92-K92+L92+M92 -> 1126796.7 | O92: =B92&"|"&D92 -> 6|LP-14
B93: 6 | C93: =Quarters!$E$9 -> Q2 2023 | D93: LP-15 | E93: Sable Foundation | F93: =N78 -> 929554.79 | G93: ='LP Capital Calls'!$H$93 -> 168000 | H93: ='Distribution Waterfall'!$L$9*'LP Register'!$F$18 -> 0 | I93: ='Distribution Waterfall'!$N$9*'LP Register'!$F$18 -> 0 | J93: ='Distribution Waterfall'!$T$9*'LP Register'!$F$18 -> 0 | K93: =H93+I93+J93 -> 0 | L93: =('NAV Rollforward'!$G$9+'NAV Rollforward'!$H$9-'Mgmt Fee Schedule'!$G$9)*'LP Register'!$F$18 -> 29241.937 | M93: =-('Distribution Waterfall'!$Q$9+'Distribution Waterfall'!$U$9)*'LP Register'!$F$18 -> 0 | N93: =F93+G93-K93+L93+M93 -> 1126796.7 | O93: =B93&"|"&D93 -> 6|LP-15
B94: 7 | C94: =Quarters!$E$10 -> Q3 2023 | D94: LP-01 | E94: Northbridge State Pension Fund | F94: =N79 -> 5633983.6 | G94: ='LP Capital Calls'!$H$94 -> 760000 | H94: ='Distribution Waterfall'!$L$10*'LP Register'!$F$4 -> 0 | I94: ='Distribution Waterfall'!$N$10*'LP Register'!$F$4 -> 0 | J94: ='Distribution Waterfall'!$T$10*'LP Register'!$F$4 -> 0 | K94: =H94+I94+J94 -> 0 | L94: =('NAV Rollforward'!$G$10+'NAV Rollforward'!$H$10-'Mgmt Fee Schedule'!$G$10)*'LP Register'!$F$4 -> 289461.55 | M94: =-('Distribution Waterfall'!$Q$10+'Distribution Waterfall'!$U$10)*'LP Register'!$F$4 -> 0 | N94: =F94+G94-K94+L94+M94 -> 6683445.2 | O94: =B94&"|"&D94 -> 7|LP-01
B95: 7 | C95: =Quarters!$E$10 -> Q3 2023 | D95: LP-02 | E95: Meridian University Endowment | F95: =N80 -> 4225487.7 | G95: ='LP Capital Calls'!$H$95 -> 570000 | H95: ='Distribution Waterfall'!$L$10*'LP Register'!$F$5 -> 0 | I95: ='Distribution Waterfall'!$N$10*'LP Register'!$F$5 -> 0 | J95: ='Distribution Waterfall'!$T$10*'LP Register'!$F$5 -> 0 | K95: =H95+I95+J95 -> 0 | L95: =('NAV Rollforward'!$G$10+'NAV Rollforward'!$H$10-'Mgmt Fee Schedule'!$G$10)*'LP Register'!$F$5 -> 217096.16 | M95: =-('Distribution Waterfall'!$Q$10+'Distribution Waterfall'!$U$10)*'LP Register'!$F$5 -> 0 | N95: =F95+G95-K95+L95+M95 -> 5012583.9 | O95: =B95&"|"&D95 -> 7|LP-02
B96: 7 | C96: =Quarters!$E$10 -> Q3 2023 | D96: LP-03 | E96: Harborview Insurance Co. | F96: =N81 -> 3873363.8 | G96: ='LP Capital Calls'!$H$96 -> 522500 | H96: ='Distribution Waterfall'!$L$10*'LP Register'!$F$6 -> 0 | I96: ='Distribution Waterfall'!$N$10*'LP Register'!$F$6 -> 0 | J96: ='Distribution Waterfall'!$T$10*'LP Register'!$F$6 -> 0 | K96: =H96+I96+J96 -> 0 | L96: =('NAV Rollforward'!$G$10+'NAV Rollforward'!$H$10-'Mgmt Fee Schedule'!$G$10)*'LP Register'!$F$6 -> 199004.81 | M96: =-('Distribution Waterfall'!$Q$10+'Distribution Waterfall'!$U$10)*'LP Register'!$F$6 -> 0 | N96: =F96+G96-K96+L96+M96 -> 4594868.6 | O96: =B96&"|"&D96 -> 7|LP-03
B97: 7 | C97: =Quarters!$E$10 -> Q3 2023 | D97: LP-04 | E97: Cascade Partners Fund of Funds | F97: =N82 -> 3521239.8 | G97: ='LP Capital Calls'!$H$97 -> 475000 | H97: ='Distribution Waterfall'!$L$10*'LP Register'!$F$7 -> 0 | I97: ='Distribution Waterfall'!$N$10*'LP Register'!$F$7 -> 0 | J97: ='Distribution Waterfall'!$T$10*'LP Register'!$F$7 -> 0 | K97: =H97+I97+J97 -> 0 | L97: =('NAV Rollforward'!$G$10+'NAV Rollforward'!$H$10-'Mgmt Fee Schedule'!$G$10)*'LP Register'!$F$7 -> 180913.47 | M97: =-('Distribution Waterfall'!$Q$10+'Distribution Waterfall'!$U$10)*'LP Register'!$F$7 -> 0 | N97: =F97+G97-K97+L97+M97 -> 4177153.2 | O97: =B97&"|"&D97 -> 7|LP-04
B98: 7 | C98: =Quarters!$E$10 -> Q3 2023 | D98: LP-05 | E98: Elmwood Family Office | F98: =N83 -> 2816991.8 | G98: ='LP Capital Calls'!$H$98 -> 380000 | H98: ='Distribution Waterfall'!$L$10*'LP Register'!$F$8 -> 0 | I98: ='Distribution Waterfall'!$N$10*'LP Register'!$F$8 -> 0 | J98: ='Distribution Waterfall'!$T$10*'LP Register'!$F$8 -> 0 | K98: =H98+I98+J98 -> 0 | L98: =('NAV Rollforward'!$G$10+'NAV Rollforward'!$H$10-'Mgmt Fee Schedule'!$G$10)*'LP Register'!$F$8 -> 144730.77 | M98: =-('Distribution Waterfall'!$Q$10+'Distribution Waterfall'!$U$10)*'LP Register'!$F$8 -> 0 | N98: =F98+G98-K98+L98+M98 -> 3341722.6 | O98: =B98&"|"&D98 -> 7|LP-05
B99: 7 | C99: =Quarters!$E$10 -> Q3 2023 | D99: LP-06 | E99: Tanager Sovereign Partners | F99: =N84 -> 2816991.8 | G99: ='LP Capital Calls'!$H$99 -> 380000 | H99: ='Distribution Waterfall'!$L$10*'LP Register'!$F$9 -> 0 | I99: ='Distribution Waterfall'!$N$10*'LP Register'!$F$9 -> 0 | J99: ='Distribution Waterfall'!$T$10*'LP Register'!$F$9 -> 0 | K99: =H99+I99+J99 -> 0 | L99: =('NAV Rollforward'!$G$10+'NAV Rollforward'!$H$10-'Mgmt Fee Schedule'!$G$10)*'LP Register'!$F$9 -> 144730.77 | M99: =-('Distribution Waterfall'!$Q$10+'Distribution Waterfall'!$U$10)*'LP Register'!$F$9 -> 0 | N99: =F99+G99-K99+L99+M99 -> 3341722.6 | O99: =B99&"|"&D99 -> 7|LP-06
B100: 7 | C100: =Quarters!$E$10 -> Q3 2023 | D100: LP-07 | E100: Birchwood College Endowment | F100: =N85 -> 2112743.9 | G100: ='LP Capital Calls'!$H$100 -> 285000 | H100: ='Distribution Waterfall'!$L$10*'LP Register'!$F$10 -> 0 | I100: ='Distribution Waterfall'!$N$10*'LP Register'!$F$10 -> 0 | J100: ='Distribution Waterfall'!$T$10*'LP Register'!$F$10 -> 0 | K100: =H100+I100+J100 -> 0 | L100: =('NAV Rollforward'!$G$10+'NAV Rollforward'!$H$10-'Mgmt Fee Schedule'!$G$10)*'LP Register'!$F$10 -> 108548.08 | M100: =-('Distribution Waterfall'!$Q$10+'Distribution Waterfall'!$U$10)*'LP Register'!$F$10 -> 0 | N100: =F100+G100-K100+L100+M100 -> 2506291.9 | O100: =B100&"|"&D100 -> 7|LP-07
...

Sheet LP Statement (Select LP)
A1: LP Capital Account Statement
A2: Pick any LP from the dropdown in C4 to view their full statement
B4: Select LP: | C4: Northbridge State Pension Fund
B5: LP ID | C5: =INDEX('LP Register'!$B$4:$B$18,MATCH($C$4,'LP Register'!$C$4:$C$18,0)) -> LP-01
B6: Commitment ($) | C6: =INDEX('LP Register'!$E$4:$E$18,MATCH($C$4,'LP Register'!$C$4:$C$18,0)) -> 8000000
B7: Commitment % | C7: =INDEX('LP Register'!$F$4:$F$18,MATCH($C$4,'LP Register'!$C$4:$C$18,0)) -> 0.16
B9: Qtr # | C9: Quarter | D9: Beginning Balance | E9: Contributions | F9: Dist: ROC | G9: Dist: Pref | H9: Dist: Carry Split | I9: Total Cash Dist. | J9: Gain/(Loss) Alloc. | K9: Less: Carry to GP | L9: Ending Balance
B10: 1 | C10: =Quarters!$E$4 -> Q1 2022 | D10: =INDEX('LP Capital Accounts'!$F$4:$F$273,MATCH(B10&"|"&$C$5,'LP Capital Accounts'!$O$4:$O$273,0)) -> 0 | E10: =INDEX('LP Capital Accounts'!$G$4:$G$273,MATCH(B10&"|"&$C$5,'LP Capital Accounts'!$O$4:$O$273,0)) -> 1000000 | F10: =INDEX('LP Capital Accounts'!$H$4:$H$273,MATCH(B10&"|"&$C$5,'LP Capital Accounts'!$O$4:$O$273,0)) -> 0 | G10: =INDEX('LP Capital Accounts'!$I$4:$I$273,MATCH(B10&"|"&$C$5,'LP Capital Accounts'!$O$4:$O$273,0)) -> 0 | H10: =INDEX('LP Capital Accounts'!$J$4:$J$273,MATCH(B10&"|"&$C$5,'LP Capital Accounts'!$O$4:$O$273,0)) -> 0 | I10: =INDEX('LP Capital Accounts'!$K$4:$K$273,MATCH(B10&"|"&$C$5,'LP Capital Accounts'!$O$4:$O$273,0)) -> 0 | J10: =INDEX('LP Capital Accounts'!$L$4:$L$273,MATCH(B10&"|"&$C$5,'LP Capital Accounts'!$O$4:$O$273,0)) -> -40000 | K10: =INDEX('LP Capital Accounts'!$M$4:$M$273,MATCH(B10&"|"&$C$5,'LP Capital Accounts'!$O$4:$O$273,0)) -> 0 | L10: =INDEX('LP Capital Accounts'!$N$4:$N$273,MATCH(B10&"|"&$C$5,'LP Capital Accounts'!$O$4:$O$273,0)) -> 960000
B11: 2 | C11: =Quarters!$E$5 -> Q2 2022 | D11: =INDEX('LP Capital Accounts'!$F$4:$F$273,MATCH(B11&"|"&$C$5,'LP Capital Accounts'!$O$4:$O$273,0)) -> 960000 | E11: =INDEX('LP Capital Accounts'!$G$4:$G$273,MATCH(B11&"|"&$C$5,'LP Capital Accounts'!$O$4:$O$273,0)) -> 920000 | F11: =INDEX('LP Capital Accounts'!$H$4:$H$273,MATCH(B11&"|"&$C$5,'LP Capital Accounts'!$O$4:$O$273,0)) -> 0 | G11: =INDEX('LP Capital Accounts'!$I$4:$I$273,MATCH(B11&"|"&$C$5,'LP Capital Accounts'!$O$4:$O$273,0)) -> 0 | H11: =INDEX('LP Capital Accounts'!$J$4:$J$273,MATCH(B11&"|"&$C$5,'LP Capital Accounts'!$O$4:$O$273,0)) -> 0 | I11: =INDEX('LP Capital Accounts'!$K$4:$K$273,MATCH(B11&"|"&$C$5,'LP Capital Accounts'!$O$4:$O$273,0)) -> 0 | J11: =INDEX('LP Capital Accounts'!$L$4:$L$273,MATCH(B11&"|"&$C$5,'LP Capital Accounts'!$O$4:$O$273,0)) -> 65187.926 | K11: =INDEX('LP Capital Accounts'!$M$4:$M$273,MATCH(B11&"|"&$C$5,'LP Capital Accounts'!$O$4:$O$273,0)) -> 0 | L11: =INDEX('LP Capital Accounts'!$N$4:$N$273,MATCH(B11&"|"&$C$5,'LP Capital Accounts'!$O$4:$O$273,0)) -> 1945187.9
B12: 3 | C12: =Quarters!$E$6 -> Q3 2022 | D12: =INDEX('LP Capital Accounts'!$F$4:$F$273,MATCH(B12&"|"&$C$5,'LP Capital Accounts'!$O$4:$O$273,0)) -> 1945187.9 | E12: =INDEX('LP Capital Accounts'!$G$4:$G$273,MATCH(B12&"|"&$C$5,'LP Capital Accounts'!$O$4:$O$273,0)) -> 760000 | F12: =INDEX('LP Capital Accounts'!$H$4:$H$273,MATCH(B12&"|"&$C$5,'LP Capital Accounts'!$O$4:$O$273,0)) -> 0 | G12: =INDEX('LP Capital Accounts'!$I$4:$I$273,MATCH(B12&"|"&$C$5,'LP Capital Accounts'!$O$4:$O$273,0)) -> 0 | H12: =INDEX('LP Capital Accounts'!$J$4:$J$273,MATCH(B12&"|"&$C$5,'LP Capital Accounts'!$O$4:$O$273,0)) -> 0 | I12: =INDEX('LP Capital Accounts'!$K$4:$K$273,MATCH(B12&"|"&$C$5,'LP Capital Accounts'!$O$4:$O$273,0)) -> 0 | J12: =INDEX('LP Capital Accounts'!$L$4:$L$273,MATCH(B12&"|"&$C$5,'LP Capital Accounts'!$O$4:$O$273,0)) -> 103445.34 | K12: =INDEX('LP Capital Accounts'!$M$4:$M$273,MATCH(B12&"|"&$C$5,'LP Capital Accounts'!$O$4:$O$273,0)) -> 0 | L12: =INDEX('LP Capital Accounts'!$N$4:$N$273,MATCH(B12&"|"&$C$5,'LP Capital Accounts'!$O$4:$O$273,0)) -> 2808633.3
B13: 4 | C13: =Quarters!$E$7 -> Q4 2022 | D13: =INDEX('LP Capital Accounts'!$F$4:$F$273,MATCH(B13&"|"&$C$5,'LP Capital Accounts'!$O$4:$O$273,0)) -> 2808633.3 | E13: =INDEX('LP Capital Accounts'!$G$4:$G$273,MATCH(B13&"|"&$C$5,'LP Capital Accounts'!$O$4:$O$273,0)) -> 840000 | F13: =INDEX('LP Capital Accounts'!$H$4:$H$273,MATCH(B13&"|"&$C$5,'LP Capital Accounts'!$O$4:$O$273,0)) -> 0 | G13: =INDEX('LP Capital Accounts'!$I$4:$I$273,MATCH(B13&"|"&$C$5,'LP Capital Accounts'!$O$4:$O$273,0)) -> 0 | H13: =INDEX('LP Capital Accounts'!$J$4:$J$273,MATCH(B13&"|"&$C$5,'LP Capital Accounts'!$O$4:$O$273,0)) -> 0 | I13: =INDEX('LP Capital Accounts'!$K$4:$K$273,MATCH(B13&"|"&$C$5,'LP Capital Accounts'!$O$4:$O$273,0)) -> 0 | J13: =INDEX('LP Capital Accounts'!$L$4:$L$273,MATCH(B13&"|"&$C$5,'LP Capital Accounts'!$O$4:$O$273,0)) -> 121382.8 | K13: =INDEX('LP Capital Accounts'!$M$4:$M$273,MATCH(B13&"|"&$C$5,'LP Capital Accounts'!$O$4:$O$273,0)) -> 0 | L13: =INDEX('LP Capital Accounts'!$N$4:$N$273,MATCH(B13&"|"&$C$5,'LP Capital Accounts'!$O$4:$O$273,0)) -> 3770016.1
B14: 5 | C14: =Quarters!$E$8 -> Q1 2023 | D14: =INDEX('LP Capital Accounts'!$F$4:$F$273,MATCH(B14&"|"&$C$5,'LP Capital Accounts'!$O$4:$O$273,0)) -> 3770016.1 | E14: =INDEX('LP Capital Accounts'!$G$4:$G$273,MATCH(B14&"|"&$C$5,'LP Capital Accounts'!$O$4:$O$273,0)) -> 680000 | F14: =INDEX('LP Capital Accounts'!$H$4:$H$273,MATCH(B14&"|"&$C$5,'LP Capital Accounts'!$O$4:$O$273,0)) -> 0 | G14: =INDEX('LP Capital Accounts'!$I$4:$I$273,MATCH(B14&"|"&$C$5,'LP Capital Accounts'!$O$4:$O$273,0)) -> 0 | H14: =INDEX('LP Capital Accounts'!$J$4:$J$273,MATCH(B14&"|"&$C$5,'LP Capital Accounts'!$O$4:$O$273,0)) -> 0 | I14: =INDEX('LP Capital Accounts'!$K$4:$K$273,MATCH(B14&"|"&$C$5,'LP Capital Accounts'!$O$4:$O$273,0)) -> 0 | J14: =INDEX('LP Capital Accounts'!$L$4:$L$273,MATCH(B14&"|"&$C$5,'LP Capital Accounts'!$O$4:$O$273,0)) -> 197757.9 | K14: =INDEX('LP Capital Accounts'!$M$4:$M$273,MATCH(B14&"|"&$C$5,'LP Capital Accounts'!$O$4:$O$273,0)) -> 0 | L14: =INDEX('LP Capital Accounts'!$N$4:$N$273,MATCH(B14&"|"&$C$5,'LP Capital Accounts'!$O$4:$O$273,0)) -> 4647774
B15: 6 | C15: =Quarters!$E$9 -> Q2 2023 | D15: =INDEX('LP Capital Accounts'!$F$4:$F$273,MATCH(B15&"|"&$C$5,'LP Capital Accounts'!$O$4:$O$273,0)) -> 4647774 | E15: =INDEX('LP Capital Accounts'!$G$4:$G$273,MATCH(B15&"|"&$C$5,'LP Capital Accounts'!$O$4:$O$273,0)) -> 840000 | F15: =INDEX('LP Capital Accounts'!$H$4:$H$273,MATCH(B15&"|"&$C$5,'LP Capital Accounts'!$O$4:$O$273,0)) -> 0 | G15: =INDEX('LP Capital Accounts'!$I$4:$I$273,MATCH(B15&"|"&$C$5,'LP Capital Accounts'!$O$4:$O$273,0)) -> 0 | H15: =INDEX('LP Capital Accounts'!$J$4:$J$273,MATCH(B15&"|"&$C$5,'LP Capital Accounts'!$O$4:$O$273,0)) -> 0 | I15: =INDEX('LP Capital Accounts'!$K$4:$K$273,MATCH(B15&"|"&$C$5,'LP Capital Accounts'!$O$4:$O$273,0)) -> 0 | J15: =INDEX('LP Capital Accounts'!$L$4:$L$273,MATCH(B15&"|"&$C$5,'LP Capital Accounts'!$O$4:$O$273,0)) -> 146209.68 | K15: =INDEX('LP Capital Accounts'!$M$4:$M$273,MATCH(B15&"|"&$C$5,'LP Capital Accounts'!$O$4:$O$273,0)) -> 0 | L15: =INDEX('LP Capital Accounts'!$N$4:$N$273,MATCH(B15&"|"&$C$5,'LP Capital Accounts'!$O$4:$O$273,0)) -> 5633983.6
B16: 7 | C16: =Quarters!$E$10 -> Q3 2023 | D16: =INDEX('LP Capital Accounts'!$F$4:$F$273,MATCH(B16&"|"&$C$5,'LP Capital Accounts'!$O$4:$O$273,0)) -> 5633983.6 | E16: =INDEX('LP Capital Accounts'!$G$4:$G$273,MATCH(B16&"|"&$C$5,'LP Capital Accounts'!$O$4:$O$273,0)) -> 760000 | F16: =INDEX('LP Capital Accounts'!$H$4:$H$273,MATCH(B16&"|"&$C$5,'LP Capital Accounts'!$O$4:$O$273,0)) -> 0 | G16: =INDEX('LP Capital Accounts'!$I$4:$I$273,MATCH(B16&"|"&$C$5,'LP Capital Accounts'!$O$4:$O$273,0)) -> 0 | H16: =INDEX('LP Capital Accounts'!$J$4:$J$273,MATCH(B16&"|"&$C$5,'LP Capital Accounts'!$O$4:$O$273,0)) -> 0 | I16: =INDEX('LP Capital Accounts'!$K$4:$K$273,MATCH(B16&"|"&$C$5,'LP Capital Accounts'!$O$4:$O$273,0)) -> 0 | J16: =INDEX('LP Capital Accounts'!$L$4:$L$273,MATCH(B16&"|"&$C$5,'LP Capital Accounts'!$O$4:$O$273,0)) -> 289461.55 | K16: =INDEX('LP Capital Accounts'!$M$4:$M$273,MATCH(B16&"|"&$C$5,'LP Capital Accounts'!$O$4:$O$273,0)) -> 0 | L16: =INDEX('LP Capital Accounts'!$N$4:$N$273,MATCH(B16&"|"&$C$5,'LP Capital Accounts'!$O$4:$O$273,0)) -> 6683445.2
B17: 8 | C17: =Quarters!$E$11 -> Q4 2023 | D17: =INDEX('LP Capital Accounts'!$F$4:$F$273,MATCH(B17&"|"&$C$5,'LP Capital Accounts'!$O$4:$O$273,0)) -> 6683445.2 | E17: =INDEX('LP Capital Accounts'!$G$4:$G$273,MATCH(B17&"|"&$C$5,'LP Capital Accounts'!$O$4:$O$273,0)) -> 600000 | F17: =INDEX('LP Capital Accounts'!$H$4:$H$273,MATCH(B17&"|"&$C$5,'LP Capital Accounts'!$O$4:$O$273,0)) -> 0 | G17: =INDEX('LP Capital Accounts'!$I$4:$I$273,MATCH(B17&"|"&$C$5,'LP Capital Accounts'!$O$4:$O$273,0)) -> 0 | H17: =INDEX('LP Capital Accounts'!$J$4:$J$273,MATCH(B17&"|"&$C$5,'LP Capital Accounts'!$O$4:$O$273,0)) -> 0 | I17: =INDEX('LP Capital Accounts'!$K$4:$K$273,MATCH(B17&"|"&$C$5,'LP Capital Accounts'!$O$4:$O$273,0)) -> 0 | J17: =INDEX('LP Capital Accounts'!$L$4:$L$273,MATCH(B17&"|"&$C$5,'LP Capital Accounts'!$O$4:$O$273,0)) -> 361987.41 | K17: =INDEX('LP Capital Accounts'!$M$4:$M$273,MATCH(B17&"|"&$C$5,'LP Capital Accounts'!$O$4:$O$273,0)) -> 0 | L17: =INDEX('LP Capital Accounts'!$N$4:$N$273,MATCH(B17&"|"&$C$5,'LP Capital Accounts'!$O$4:$O$273,0)) -> 7645432.6
B18: 9 | C18: =Quarters!$E$12 -> Q1 2024 | D18: =INDEX('LP Capital Accounts'!$F$4:$F$273,MATCH(B18&"|"&$C$5,'LP Capital Accounts'!$O$4:$O$273,0)) -> 7645432.6 | E18: =INDEX('LP Capital Accounts'!$G$4:$G$273,MATCH(B18&"|"&$C$5,'LP Capital Accounts'!$O$4:$O$273,0)) -> 680000 | F18: =INDEX('LP Capital Accounts'!$H$4:$H$273,MATCH(B18&"|"&$C$5,'LP Capital Accounts'!$O$4:$O$273,0)) -> 0 | G18: =INDEX('LP Capital Accounts'!$I$4:$I$273,MATCH(B18&"|"&$C$5,'LP Capital Accounts'!$O$4:$O$273,0)) -> 0 | H18: =INDEX('LP Capital Accounts'!$J$4:$J$273,MATCH(B18&"|"&$C$5,'LP Capital Accounts'!$O$4:$O$273,0)) -> 0 | I18: =INDEX('LP Capital Accounts'!$K$4:$K$273,MATCH(B18&"|"&$C$5,'LP Capital Accounts'!$O$4:$O$273,0)) -> 0 | J18: =INDEX('LP Capital Accounts'!$L$4:$L$273,MATCH(B18&"|"&$C$5,'LP Capital Accounts'!$O$4:$O$273,0)) -> 418332.61 | K18: =INDEX('LP Capital Accounts'!$M$4:$M$273,MATCH(B18&"|"&$C$5,'LP Capital Accounts'!$O$4:$O$273,0)) -> 0 | L18: =INDEX('LP Capital Accounts'!$N$4:$N$273,MATCH(B18&"|"&$C$5,'LP Capital Accounts'!$O$4:$O$273,0)) -> 8743765.2
B19: 10 | C19: =Quarters!$E$13 -> Q2 2024 | D19: =INDEX('LP Capital Accounts'!$F$4:$F$273,MATCH(B19&"|"&$C$5,'LP Capital Accounts'!$O$4:$O$273,0)) -> 8743765.2 | E19: =INDEX('LP Capital Accounts'!$G$4:$G$273,MATCH(B19&"|"&$C$5,'LP Capital Accounts'!$O$4:$O$273,0)) -> 600000 | F19: =INDEX('LP Capital Accounts'!$H$4:$H$273,MATCH(B19&"|"&$C$5,'LP Capital Accounts'!$O$4:$O$273,0)) -> 0 | G19: =INDEX('LP Capital Accounts'!$I$4:$I$273,MATCH(B19&"|"&$C$5,'LP Capital Accounts'!$O$4:$O$273,0)) -> 0 | H19: =INDEX('LP Capital Accounts'!$J$4:$J$273,MATCH(B19&"|"&$C$5,'LP Capital Accounts'!$O$4:$O$273,0)) -> 0 | I19: =INDEX('LP Capital Accounts'!$K$4:$K$273,MATCH(B19&"|"&$C$5,'LP Capital Accounts'!$O$4:$O$273,0)) -> 0 | J19: =INDEX('LP Capital Accounts'!$L$4:$L$273,MATCH(B19&"|"&$C$5,'LP Capital Accounts'!$O$4:$O$273,0)) -> 488580.29 | K19: =INDEX('LP Capital Accounts'!$M$4:$M$273,MATCH(B19&"|"&$C$5,'LP Capital Accounts'!$O$4:$O$273,0)) -> 0 | L19: =INDEX('LP Capital Accounts'!$N$4:$N$273,MATCH(B19&"|"&$C$5,'LP Capital Accounts'!$O$4:$O$273,0)) -> 9832345.5
B20: 11 | C20: =Quarters!$E$14 -> Q3 2024 | D20: =INDEX('LP Capital Accounts'!$F$4:$F$273,MATCH(B20&"|"&$C$5,'LP Capital Accounts'!$O$4:$O$273,0)) -> 9832345.5 | E20: =INDEX('LP Capital Accounts'!$G$4:$G$273,MATCH(B20&"|"&$C$5,'LP Capital Accounts'!$O$4:$O$273,0)) -> 40000 | F20: =INDEX('LP Capital Accounts'!$H$4:$H$273,MATCH(B20&"|"&$C$5,'LP Capital Accounts'!$O$4:$O$273,0)) -> 0 | G20: =INDEX('LP Capital Accounts'!$I$4:$I$273,MATCH(B20&"|"&$C$5,'LP Capital Accounts'!$O$4:$O$273,0)) -> 0 | H20: =INDEX('LP Capital Accounts'!$J$4:$J$273,MATCH(B20&"|"&$C$5,'LP Capital Accounts'!$O$4:$O$273,0)) -> 0 | I20: =INDEX('LP Capital Accounts'!$K$4:$K$273,MATCH(B20&"|"&$C$5,'LP Capital Accounts'!$O$4:$O$273,0)) -> 0 | J20: =INDEX('LP Capital Accounts'!$L$4:$L$273,MATCH(B20&"|"&$C$5,'LP Capital Accounts'!$O$4:$O$273,0)) -> 546194.73 | K20: =INDEX('LP Capital Accounts'!$M$4:$M$273,MATCH(B20&"|"&$C$5,'LP Capital Accounts'!$O$4:$O$273,0)) -> 0 | L20: =INDEX('LP Capital Accounts'!$N$4:$N$273,MATCH(B20&"|"&$C$5,'LP Capital Accounts'!$O$4:$O$273,0)) -> 10418540
B21: 12 | C21: =Quarters!$E$15 -> Q4 2024 | D21: =INDEX('LP Capital Accounts'!$F$4:$F$273,MATCH(B21&"|"&$C$5,'LP Capital Accounts'!$O$4:$O$273,0)) -> 10418540 | E21: =INDEX('LP Capital Accounts'!$G$4:$G$273,MATCH(B21&"|"&$C$5,'LP Capital Accounts'!$O$4:$O$273,0)) -> 40000 | F21: =INDEX('LP Capital Accounts'!$H$4:$H$273,MATCH(B21&"|"&$C$5,'LP Capital Accounts'!$O$4:$O$273,0)) -> 0 | G21: =INDEX('LP Capital Accounts'!$I$4:$I$273,MATCH(B21&"|"&$C$5,'LP Capital Accounts'!$O$4:$O$273,0)) -> 0 | H21: =INDEX('LP Capital Accounts'!$J$4:$J$273,MATCH(B21&"|"&$C$5,'LP Capital Accounts'!$O$4:$O$273,0)) -> 0 | I21: =INDEX('LP Capital Accounts'!$K$4:$K$273,MATCH(B21&"|"&$C$5,'LP Capital Accounts'!$O$4:$O$273,0)) -> 0 | J21: =INDEX('LP Capital Accounts'!$L$4:$L$273,MATCH(B21&"|"&$C$5,'LP Capital Accounts'!$O$4:$O$273,0)) -> 658205.25 | K21: =INDEX('LP Capital Accounts'!$M$4:$M$273,MATCH(B21&"|"&$C$5,'LP Capital Accounts'!$O$4:$O$273,0)) -> 0 | L21: =INDEX('LP Capital Accounts'!$N$4:$N$273,MATCH(B21&"|"&$C$5,'LP Capital Accounts'!$O$4:$O$273,0)) -> 11116745
B22: 13 | C22: =Quarters!$E$16 -> Q1 2025 | D22: =INDEX('LP Capital Accounts'!$F$4:$F$273,MATCH(B22&"|"&$C$5,'LP Capital Accounts'!$O$4:$O$273,0)) -> 11116745 | E22: =INDEX('LP Capital Accounts'!$G$4:$G$273,MATCH(B22&"|"&$C$5,'LP Capital Accounts'!$O$4:$O$273,0)) -> 36400 | F22: =INDEX('LP Capital Accounts'!$H$4:$H$273,MATCH(B22&"|"&$C$5,'LP Capital Accounts'!$O$4:$O$273,0)) -> 3105901.9 | G22: =INDEX('LP Capital Accounts'!$I$4:$I$273,MATCH(B22&"|"&$C$5,'LP Capital Accounts'!$O$4:$O$273,0)) -> 0 | H22: =INDEX('LP Capital Accounts'!$J$4:$J$273,MATCH(B22&"|"&$C$5,'LP Capital Accounts'!$O$4:$O$273,0)) -> 0 | I22: =INDEX('LP Capital Accounts'!$K$4:$K$273,MATCH(B22&"|"&$C$5,'LP Capital Accounts'!$O$4:$O$273,0)) -> 3105901.9 | J22: =INDEX('LP Capital Accounts'!$L$4:$L$273,MATCH(B22&"|"&$C$5,'LP Capital Accounts'!$O$4:$O$273,0)) -> 753308.68 | K22: =INDEX('LP Capital Accounts'!$M$4:$M$273,MATCH(B22&"|"&$C$5,'LP Capital Accounts'!$O$4:$O$273,0)) -> 0 | L22: =INDEX('LP Capital Accounts'!$N$4:$N$273,MATCH(B22&"|"&$C$5,'LP Capital Accounts'!$O$4:$O$273,0)) -> 8800552.2
B23: 14 | C23: =Quarters!$E$17 -> Q2 2025 | D23: =INDEX('LP Capital Accounts'!$F$4:$F$273,MATCH(B23&"|"&$C$5,'LP Capital Accounts'!$O$4:$O$273,0)) -> 8800552.2 | E23: =INDEX('LP Capital Accounts'!$G$4:$G$273,MATCH(B23&"|"&$C$5,'LP Capital Accounts'!$O$4:$O$273,0)) -> 36400 | F23: =INDEX('LP Capital Accounts'!$H$4:$H$273,MATCH(B23&"|"&$C$5,'LP Capital Accounts'!$O$4:$O$273,0)) -> 0 | G23: =INDEX('LP Capital Accounts'!$I$4:$I$273,MATCH(B23&"|"&$C$5,'LP Capital Accounts'!$O$4:$O$273,0)) -> 0 | H23: =INDEX('LP Capital Accounts'!$J$4:$J$273,MATCH(B23&"|"&$C$5,'LP Capital Accounts'!$O$4:$O$273,0)) -> 0 | I23: =INDEX('LP Capital Accounts'!$K$4:$K$273,MATCH(B23&"|"&$C$5,'LP Capital Accounts'!$O$4:$O$273,0)) -> 0 | J23: =INDEX('LP Capital Accounts'!$L$4:$L$273,MATCH(B23&"|"&$C$5,'LP Capital Accounts'!$O$4:$O$273,0)) -> 435721.65 | K23: =INDEX('LP Capital Accounts'!$M$4:$M$273,MATCH(B23&"|"&$C$5,'LP Capital Accounts'!$O$4:$O$273,0)) -> 0 | L23: =INDEX('LP Capital Accounts'!$N$4:$N$273,MATCH(B23&"|"&$C$5,'LP Capital Accounts'!$O$4:$O$273,0)) -> 9272673.9
B24: 15 | C24: =Quarters!$E$18 -> Q3 2025 | D24: =INDEX('LP Capital Accounts'!$F$4:$F$273,MATCH(B24&"|"&$C$5,'LP Capital Accounts'!$O$4:$O$273,0)) -> 9272673.9 | E24: =INDEX('LP Capital Accounts'!$G$4:$G$273,MATCH(B24&"|"&$C$5,'LP Capital Accounts'!$O$4:$O$273,0)) -> 31600 | F24: =INDEX('LP Capital Accounts'!$H$4:$H$273,MATCH(B24&"|"&$C$5,'LP Capital Accounts'!$O$4:$O$273,0)) -> 1758970.5 | G24: =INDEX('LP Capital Accounts'!$I$4:$I$273,MATCH(B24&"|"&$C$5,'LP Capital Accounts'!$O$4:$O$273,0)) -> 0 | H24: =INDEX('LP Capital Accounts'!$J$4:$J$273,MATCH(B24&"|"&$C$5,'LP Capital Accounts'!$O$4:$O$273,0)) -> 0 | I24: =INDEX('LP Capital Accounts'!$K$4:$K$273,MATCH(B24&"|"&$C$5,'LP Capital Accounts'!$O$4:$O$273,0)) -> 1758970.5 | J24: =INDEX('LP Capital Accounts'!$L$4:$L$273,MATCH(B24&"|"&$C$5,'LP Capital Accounts'!$O$4:$O$273,0)) -> 426577.82 | K24: =INDEX('LP Capital Accounts'!$M$4:$M$273,MATCH(B24&"|"&$C$5,'LP Capital Accounts'!$O$4:$O$273,0)) -> 0 | L24: =INDEX('LP Capital Accounts'!$N$4:$N$273,MATCH(B24&"|"&$C$5,'LP Capital Accounts'!$O$4:$O$273,0)) -> 7971881.2
B25: 16 | C25: =Quarters!$E$19 -> Q4 2025 | D25: =INDEX('LP Capital Accounts'!$F$4:$F$273,MATCH(B25&"|"&$C$5,'LP Capital Accounts'!$O$4:$O$273,0)) -> 7971881.2 | E25: =INDEX('LP Capital Accounts'!$G$4:$G$273,MATCH(B25&"|"&$C$5,'LP Capital Accounts'!$O$4:$O$273,0)) -> 31600 | F25: =INDEX('LP Capital Accounts'!$H$4:$H$273,MATCH(B25&"|"&$C$5,'LP Capital Accounts'!$O$4:$O$273,0)) -> 0 | G25: =INDEX('LP Capital Accounts'!$I$4:$I$273,MATCH(B25&"|"&$C$5,'LP Capital Accounts'!$O$4:$O$273,0)) -> 0 | H25: =INDEX('LP Capital Accounts'!$J$4:$J$273,MATCH(B25&"|"&$C$5,'LP Capital Accounts'!$O$4:$O$273,0)) -> 0 | I25: =INDEX('LP Capital Accounts'!$K$4:$K$273,MATCH(B25&"|"&$C$5,'LP Capital Accounts'!$O$4:$O$273,0)) -> 0 | J25: =INDEX('LP Capital Accounts'!$L$4:$L$273,MATCH(B25&"|"&$C$5,'LP Capital Accounts'!$O$4:$O$273,0)) -> 348905.99 | K25: =INDEX('LP Capital Accounts'!$M$4:$M$273,MATCH(B25&"|"&$C$5,'LP Capital Accounts'!$O$4:$O$273,0)) -> 0 | L25: =INDEX('LP Capital Accounts'!$N$4:$N$273,MATCH(B25&"|"&$C$5,'LP Capital Accounts'!$O$4:$O$273,0)) -> 8352387.2
B26: 17 | C26: =Quarters!$E$20 -> Q1 2026 | D26: =INDEX('LP Capital Accounts'!$F$4:$F$273,MATCH(B26&"|"&$C$5,'LP Capital Accounts'!$O$4:$O$273,0)) -> 8352387.2 | E26: =INDEX('LP Capital Accounts'!$G$4:$G$273,MATCH(B26&"|"&$C$5,'LP Capital Accounts'!$O$4:$O$273,0)) -> 27200 | F26: =INDEX('LP Capital Accounts'!$H$4:$H$273,MATCH(B26&"|"&$C$5,'LP Capital Accounts'!$O$4:$O$273,0)) -> 2368620.6 | G26: =INDEX('LP Capital Accounts'!$I$4:$I$273,MATCH(B26&"|"&$C$5,'LP Capital Accounts'!$O$4:$O$273,0)) -> 0 | H26: =INDEX('LP Capital Accounts'!$J$4:$J$273,MATCH(B26&"|"&$C$5,'LP Capital Accounts'!$O$4:$O$273,0)) -> 0 | I26: =INDEX('LP Capital Accounts'!$K$4:$K$273,MATCH(B26&"|"&$C$5,'LP Capital Accounts'!$O$4:$O$273,0)) -> 2368620.6 | J26: =INDEX('LP Capital Accounts'!$L$4:$L$273,MATCH(B26&"|"&$C$5,'LP Capital Accounts'!$O$4:$O$273,0)) -> 419791.51 | K26: =INDEX('LP Capital Accounts'!$M$4:$M$273,MATCH(B26&"|"&$C$5,'LP Capital Accounts'!$O$4:$O$273,0)) -> 0 | L26: =INDEX('LP Capital Accounts'!$N$4:$N$273,MATCH(B26&"|"&$C$5,'LP Capital Accounts'!$O$4:$O$273,0)) -> 6430758.1
B27: 18 | C27: =Quarters!$E$21 -> Q2 2026 | D27: =INDEX('LP Capital Accounts'!$F$4:$F$273,MATCH(B27&"|"&$C$5,'LP Capital Accounts'!$O$4:$O$273,0)) -> 6430758.1 | E27: =INDEX('LP Capital Accounts'!$G$4:$G$273,MATCH(B27&"|"&$C$5,'LP Capital Accounts'!$O$4:$O$273,0)) -> 27200 | F27: =INDEX('LP Capital Accounts'!$H$4:$H$273,MATCH(B27&"|"&$C$5,'LP Capital Accounts'!$O$4:$O$273,0)) -> 716907 | G27: =INDEX('LP Capital Accounts'!$I$4:$I$273,MATCH(B27&"|"&$C$5,'LP Capital Accounts'!$O$4:$O$273,0)) -> 1538755.2 | H27: =INDEX('LP Capital Accounts'!$J$4:$J$273,MATCH(B27&"|"&$C$5,'LP Capital Accounts'!$O$4:$O$273,0)) -> 447108.57 | I27: =INDEX('LP Capital Accounts'!$K$4:$K$273,MATCH(B27&"|"&$C$5,'LP Capital Accounts'!$O$4:$O$273,0)) -> 2702770.7 | J27: =INDEX('LP Capital Accounts'!$L$4:$L$273,MATCH(B27&"|"&$C$5,'LP Capital Accounts'!$O$4:$O$273,0)) -> 213402.97 | K27: =INDEX('LP Capital Accounts'!$M$4:$M$273,MATCH(B27&"|"&$C$5,'LP Capital Accounts'!$O$4:$O$273,0)) -> -496465.93 | L27: =INDEX('LP Capital Accounts'!$N$4:$N$273,MATCH(B27&"|"&$C$5,'LP Capital Accounts'!$O$4:$O$273,0)) -> 3472124.4
C28: INDEX/MATCH on a Quarter#|LP ID key pulls this LP's row from the LP Capital Accounts sheet — pick a different LP above and every row updates.

Sheet IRR & MOIC Summary
A1: Fund Performance Summary
A2: As of Q2 2026
B4: Gross Cash Flows (portfolio level, pre-fee, pre-carry)
B5: Date | C5: Description | D5: Cash Flow ($)
B6: =Quarters!$F$4 -> 44651 | C6: Investment: Vantage Robotics | D6: =-'Portfolio Companies'!$G$4 -> -6000000
B7: =Quarters!$F$5 -> 44742 | C7: Investment: Coastal Foods Group | D7: =-'Portfolio Companies'!$G$5 -> -5500000
B8: =Quarters!$F$6 -> 44834 | C8: Investment: Nimbus Data Systems | D8: =-'Portfolio Companies'!$G$6 -> -4500000
B9: =Quarters!$F$7 -> 44926 | C9: Investment: Harbor Dental Partners | D9: =-'Portfolio Companies'!$G$7 -> -5000000
B10: =Quarters!$F$8 -> 45016 | C10: Investment: Trailhead Outdoor Co. | D10: =-'Portfolio Companies'!$G$8 -> -4000000
B11: =Quarters!$F$9 -> 45107 | C11: Investment: Summit Logistics | D11: =-'Portfolio Companies'!$G$9 -> -5000000
B12: =Quarters!$F$10 -> 45199 | C12: Investment: BluePeak Software | D12: =-'Portfolio Companies'!$G$10 -> -4500000
B13: =Quarters!$F$11 -> 45291 | C13: Investment: Ridgeline Materials | D13: =-'Portfolio Companies'!$G$11 -> -3500000
B14: =Quarters!$F$12 -> 45382 | C14: Investment: Fairmont Health Services | D14: =-'Portfolio Companies'!$G$12 -> -4000000
B15: =Quarters!$F$13 -> 45473 | C15: Investment: Alpine Consumer Brands | D15: =-'Portfolio Companies'!$G$13 -> -3500000
B16: =Quarters!$F$16 -> 45747 | C16: Full exit: Vantage Robotics | D16: ='Portfolio Marks'!$J$16 -> 19411887
B17: =Quarters!$F$18 -> 45930 | C17: Full exit: Coastal Foods Group | D17: ='Portfolio Marks'!$J$30 -> 10993566
B18: =Quarters!$F$21 -> 46203 | C18: Partial recap: Harbor Dental Partners | D18: ='Portfolio Marks'!$J$61 -> 6125185.5
B19: =Quarters!$F$20 -> 46112 | C19: Full exit: Summit Logistics | D19: ='Portfolio Marks'!$J$87 -> 14803879
B20: =Quarters!$F$21 -> 46203 | C20: Full exit: BluePeak Software | D20: ='Portfolio Marks'!$J$99 -> 7670711.2
B21: =Quarters!$F$21 -> 46203 | C21: Full exit: Fairmont Health Services | D21: ='Portfolio Marks'!$J$120 -> 6199332.5
B22: =Quarters!$F$21 -> 46203 | C22: Remaining portfolio fair value (terminal) | D22: ='NAV Rollforward'!$J$21 -> 21700778
B24: Gross IRR | D24: =XIRR(D6:D22,B6:B22) -> 0.25555392
B25: Gross MOIC | D25: =(SUMIF(C6:C22,"<>Investment*",D6:D22))/(-SUMIF(C6:C22,"Investment*",D6:D22)) -> 1.9100074
B28: Net Cash Flows (to LPs, post-fee, post-carry)
B29: Qtr # | C29: Date | D29: Description | E29: Cash Flow ($)
B30: 1 | C30: =Quarters!$F$4 -> 44651 | D30: =Quarters!$E$4&": capital call + distribution" -> Q1 2022: capital call + distribution | E30: =-'Capital Call Schedule'!$F$4+'Distribution Waterfall'!$V$4 -> -6250000
B31: 2 | C31: =Quarters!$F$5 -> 44742 | D31: =Quarters!$E$5&": capital call + distribution" -> Q2 2022: capital call + distribution | E31: =-'Capital Call Schedule'!$F$5+'Distribution Waterfall'!$V$5 -> -5750000
B32: 3 | C32: =Quarters!$F$6 -> 44834 | D32: =Quarters!$E$6&": capital call + distribution" -> Q3 2022: capital call + distribution | E32: =-'Capital Call Schedule'!$F$6+'Distribution Waterfall'!$V$6 -> -4750000
B33: 4 | C33: =Quarters!$F$7 -> 44926 | D33: =Quarters!$E$7&": capital call + distribution" -> Q4 2022: capital call + distribution | E33: =-'Capital Call Schedule'!$F$7+'Distribution Waterfall'!$V$7 -> -5250000
B34: 5 | C34: =Quarters!$F$8 -> 45016 | D34: =Quarters!$E$8&": capital call + distribution" -> Q1 2023: capital call + distribution | E34: =-'Capital Call Schedule'!$F$8+'Distribution Waterfall'!$V$8 -> -4250000
B35: 6 | C35: =Quarters!$F$9 -> 45107 | D35: =Quarters!$E$9&": capital call + distribution" -> Q2 2023: capital call + distribution | E35: =-'Capital Call Schedule'!$F$9+'Distribution Waterfall'!$V$9 -> -5250000
B36: 7 | C36: =Quarters!$F$10 -> 45199 | D36: =Quarters!$E$10&": capital call + distribution" -> Q3 2023: capital call + distribution | E36: =-'Capital Call Schedule'!$F$10+'Distribution Waterfall'!$V$10 -> -4750000
B37: 8 | C37: =Quarters!$F$11 -> 45291 | D37: =Quarters!$E$11&": capital call + distribution" -> Q4 2023: capital call + distribution | E37: =-'Capital Call Schedule'!$F$11+'Distribution Waterfall'!$V$11 -> -3750000
B38: 9 | C38: =Quarters!$F$12 -> 45382 | D38: =Quarters!$E$12&": capital call + distribution" -> Q1 2024: capital call + distribution | E38: =-'Capital Call Schedule'!$F$12+'Distribution Waterfall'!$V$12 -> -4250000
B39: 10 | C39: =Quarters!$F$13 -> 45473 | D39: =Quarters!$E$13&": capital call + distribution" -> Q2 2024: capital call + distribution | E39: =-'Capital Call Schedule'!$F$13+'Distribution Waterfall'!$V$13 -> -3750000
B40: 11 | C40: =Quarters!$F$14 -> 45565 | D40: =Quarters!$E$14&": capital call + distribution" -> Q3 2024: capital call + distribution | E40: =-'Capital Call Schedule'!$F$14+'Distribution Waterfall'!$V$14 -> -250000
B41: 12 | C41: =Quarters!$F$15 -> 45657 | D41: =Quarters!$E$15&": capital call + distribution" -> Q4 2024: capital call + distribution | E41: =-'Capital Call Schedule'!$F$15+'Distribution Waterfall'!$V$15 -> -250000
B42: 13 | C42: =Quarters!$F$16 -> 45747 | D42: =Quarters!$E$16&": capital call + distribution" -> Q1 2025: capital call + distribution | E42: =-'Capital Call Schedule'!$F$16+'Distribution Waterfall'!$V$16 -> 19184387
B43: 14 | C43: =Quarters!$F$17 -> 45838 | D43: =Quarters!$E$17&": capital call + distribution" -> Q2 2025: capital call + distribution | E43: =-'Capital Call Schedule'!$F$17+'Distribution Waterfall'!$V$17 -> -227500
B44: 15 | C44: =Quarters!$F$18 -> 45930 | D44: =Quarters!$E$18&": capital call + distribution" -> Q3 2025: capital call + distribution | E44: =-'Capital Call Schedule'!$F$18+'Distribution Waterfall'!$V$18 -> 10796066
B45: 16 | C45: =Quarters!$F$19 -> 46022 | D45: =Quarters!$E$19&": capital call + distribution" -> Q4 2025: capital call + distribution | E45: =-'Capital Call Schedule'!$F$19+'Distribution Waterfall'!$V$19 -> -197500
B46: 17 | C46: =Quarters!$F$20 -> 46112 | D46: =Quarters!$E$20&": capital call + distribution" -> Q1 2026: capital call + distribution | E46: =-'Capital Call Schedule'!$F$20+'Distribution Waterfall'!$V$20 -> 14633879
B47: 18 | C47: =Quarters!$F$21 -> 46203 | D47: =Quarters!$E$21&": capital call + distribution" -> Q2 2026: capital call + distribution | E47: =-'Capital Call Schedule'!$F$21+'Distribution Waterfall'!$V$21 -> 16722317
C48: =Quarters!$F$21 -> 46203 | D48: Terminal LP NAV (residual value) | E48: ='NAV Rollforward'!$J$21 -> 21700778
B50: Net IRR (to LPs) | E50: =XIRR(E30:E48,C30:C48) -> 0.20895442
B51: Net TVPI (Total Value / Paid-In) | E51: =('Distribution Waterfall'!$V$22+'NAV Rollforward'!$J$21)/'Capital Call Schedule'!$F$22 -> 1.6865049
B52: DPI (Distributed / Paid-In) | E52: ='Distribution Waterfall'!$V$22/'Capital Call Schedule'!$F$22 -> 1.2497816
B53: RVPI (Residual Value / Paid-In) | E53: ='NAV Rollforward'!$J$21/'Capital Call Schedule'!$F$22 -> 0.43672324
B56: Gross IRR (portfolio) | E56: ='IRR & MOIC Summary'!$D$24 -> 0.25555392
B57: Gross MOIC (portfolio) | E57: ='IRR & MOIC Summary'!$D$25 -> 1.9100074
B58: Note | C58: All 15 LPs share identical timing (pro-rata by commitment %), so net IRR/MOIC is the same for every LP as for the fund overall.

Sheet Variance Reconciliation
A1: GP Ledger vs. Fund Administrator — Variance Reconciliation
A2: Tie-out as of Q2 2026
B4: Summary of breaks
B5: Break | C5: Category | D5: GP Ledger ($) | E5: Fund Admin ($) | F5: Variance ($) | G5: Status
B6: R-1 | C6: Timing difference (Q9 capital call settlement lag) | D6: ='Capital Call Schedule'!$F$12 -> 4250000 | E6: ='Capital Call Schedule'!$F$12-('Capital Call Schedule'!$F$12*'LP Register'!$F$8+'Capital Call Schedule'!$F$12*'LP Register'!$F$12) -> 3740000 | F6: =E6-D6 -> -510000 | G6: Resolved — timing only, nets to zero by Q10
B7: R-2 | C7: Management fee basis error (Q13-Q16 billed on committed capital, not stepped-down) | D7: ='Mgmt Fee Schedule'!$G$16+'Mgmt Fee Schedule'!$G$17+'Mgmt Fee Schedule'!$G$18+'Mgmt Fee Schedule'!$G$19 -> 850000 | E7: =(Assumptions!$C$5*Assumptions!$C$9/4)+(Assumptions!$C$5*Assumptions!$C$9/4)+(Assumptions!$C$5*Assumptions!$C$9/4)+(Assumptions!$C$5*Assumptions!$C$9/4) -> 1000000 | F7: =D7-E7 -> -150000 | G7: Open — adjusting entry pending LP notice
B8: R-3 | C8: Distribution character misclassification (Q2 2026 recap booked outside the waterfall) | D8: ='Variance Reconciliation'!$F$36 -> 3102912.1 | E8: ='Variance Reconciliation'!$F$35 -> 2774008.7 | F8: =E8-D8 -> -328903.34 | G8: Open — reclassification and GP remittance pending
B9: R-4 | C9: Unreconciled cash break (Q3 2025 outgoing wire fee) | D9: 0 | E9: -375 | F9: =E9-D9 -> -375 | G9: Resolved — booked to fund operating expenses
C12: R-2 detail: fee basis error by quarter
C13: Quarter | D13: GP Ledger Fee ($) | E13: Fund Admin Fee ($) | F13: Variance ($)
C14: =Quarters!$E$16 -> Q1 2025 | D14: ='Mgmt Fee Schedule'!$G$16 -> 227500 | E14: =Assumptions!$C$5*Assumptions!$C$9/4 -> 250000 | F14: =D14-E14 -> -22500
C15: =Quarters!$E$17 -> Q2 2025 | D15: ='Mgmt Fee Schedule'!$G$17 -> 227500 | E15: =Assumptions!$C$5*Assumptions!$C$9/4 -> 250000 | F15: =D15-E15 -> -22500
C16: =Quarters!$E$18 -> Q3 2025 | D16: ='Mgmt Fee Schedule'!$G$18 -> 197500 | E16: =Assumptions!$C$5*Assumptions!$C$9/4 -> 250000 | F16: =D16-E16 -> -52500
C17: =Quarters!$E$19 -> Q4 2025 | D17: ='Mgmt Fee Schedule'!$G$19 -> 197500 | E17: =Assumptions!$C$5*Assumptions!$C$9/4 -> 250000 | F17: =D17-E17 -> -52500
C19: R-3 detail: counterfactual — Q2 2026 waterfall as the fund administrator (incorrectly) ran it
C20: Admin remitted the Harbor Dental recap 100% as return of capital, outside the tiers, then ran the tiered waterfall on the quarter's other two exits only.
C21: Harbor Dental recap proceeds (paid as pure ROC by admin) | F21: ='Portfolio Marks'!$J$61 -> 6125185.5
C22: Distributable run through admin's tiers (Q18 total less the recap) | F22: ='Distribution Waterfall'!$D$21-'Portfolio Marks'!$J$61 -> 13870044
C23: Cumulative contributions, EOP (unaffected) | F23: ='Distribution Waterfall'!$F$21 -> 49690000
C24: Cumulative ROC distributed, BOP — inflated by the mis-booked recap | F24: ='Distribution Waterfall'!$G$21+'Portfolio Marks'!$J$61 -> 51334517
C25: Cumulative preferred accrued, EOP (unaffected) | F25: ='Distribution Waterfall'!$I$21 -> 9617219.8
C26: Cumulative preferred paid, BOP (unaffected) | F26: ='Distribution Waterfall'!$J$21 -> 0
C27: Cumulative GP catch-up paid, BOP (unaffected) | F27: ='Distribution Waterfall'!$K$21 -> 0
C28: Tier 1 (admin): Return of Capital | F28: =MIN($F$22,MAX($F$23-$F$24,0)) -> 0
C29: Tier 2 (admin): Preferred Return | F29: =MIN($F$22-$F$28,MAX($F$25-$F$26,0)) -> 9617219.8
C30: Cumulative preferred paid, EOP (admin) | F30: =$F$26+$F$29 -> 9617219.8
C31: Target cumulative GP catch-up (admin) | F31: =(Assumptions!$C$13/(1-Assumptions!$C$13))*$F$30 -> 2404304.9
C32: Tier 3 (admin): GP Catch-up | F32: =MIN($F$22-$F$28-$F$29,MAX($F$31-$F$27,0)) -> 2404304.9
C33: Tier 4 (admin): Carry (total) | F33: =$F$22-$F$28-$F$29-$F$32 -> 1848519
C34: Tier 4 (admin): Carry to GP (20%) | F34: =$F$33*Assumptions!$C$13 -> 369703.8
C35: Total to GP under admin's (incorrect) sequencing | F35: =$F$32+$F$34 -> 2774008.7
C36: Total to GP per GP ledger (correct sequencing) | F36: ='Distribution Waterfall'!$W$21 -> 3102912.1
C38: Gross open variance (R-2 + R-3, absolute value) | F38: =ABS(E7-D7)+ABS(E8-D8) -> 478903.34
B41: Break descriptions & resolution
B42: R-1 | C42: Q9 (Q1 2024) capital call: GP ledger records LP contributions on trade date (2024-01-15). Fund administrator books on wire settlement date; two LPs' wires cleared after quarter-end and landed in the Q10 admin ledger.
C43: Resolution: No adjusting entry required — timing-only difference. Confirmed both LP wires received in full; Q10 fund admin capital call report shows the offsetting +$510,000.00, netting to zero across the two quarters.
B45: R-2 | C45: Per the LPA, management fee steps down from 2% of committed capital to 2% of remaining invested cost after the investment period ends (Q4 2024). Fund administrator's fee calculation continued billing 2% of committed capital for Q13-Q16 before the step-down was applied starting Q17.
C46: Resolution: Adjusting entry required: credit LP capital accounts $150,000.00 (pro rata by commitment %) for fees over-charged Q13-Q16; fund administrator instructed to apply the step-down formula (2% x prior-quarter remaining invested cost) going forward.
B48: R-3 | C48: Harbor Dental Partners Q2 2026 dividend recap ($6,125,185.45, 60% partial realization), paid alongside the BluePeak Software and Fairmont Health full exits in the same quarter: fund administrator's system flagged the recap as a recapitalization rather than a standard realization and remitted it 100% as return of capital outside the tiered waterfall, before running the preferred return / catch-up / carry tiers on the quarter's other two exits. The LPA requires every cash distribution — recap or sale — to pass through the same waterfall in the order it is received.
C49: Resolution: Adjusting entry required: re-sequence the Q2 2026 distribution through the waterfall in receipt order (recap included), and remit the GP the additional $328,903.34 in carried interest the misclassification under-paid.
B51: R-4 | C51: Q15 (Q3 2025) LP distribution: fund administrator's bank netted a $375.00 outgoing wire fee against one LP's distribution payment; the fee was not recorded in the GP's internal ledger.
C52: Resolution: Booked to fund operating expenses; immaterial, no LP notice required.
